Workbook
Name solver_eng: 1
Name solver_neg: 1
Name solver_num: 0
Name solver_opt: 'Solution SOLVEUR-REBALENCEMENT'!$M$17
Name solver_typ: 1
Name solver_val: 0
Name solver_ver: 3

Sheet Details RECAP
B1: AVANT REBALANCEMENT
A3: N° | E3: Mt investi hors commission | F3: Commisions de courtage | G3: Mt Investi | H3: Cours le 31/10 | I3: Cours actuel 24/10 | J3: Valorisation actuelle | K3: Poids dans le PTF | L3: Poids dans le MASI | M3: Performance du titres VENDREDI (w)/ (w-1) dans le PTF | N3: Performance du titres VENDREDI (w)/(w-1) dans le MASI | O3: Contribution de la performance dans le PTF
A4: 1 | B4: IAM | C4: 823 | D4: 120.45 | E4: =D4*C4 -> 99130.35 | F4: =E4*0.44% -> 436.17354 | G4: =E4+F4 -> 99566.524 | H4: 120 | I4: 119.4 | J4: =I4*C4 -> 98266.2 | K4: =J4/$J$19 -> 0.098732772 | L4: 0.073024613 | M4: =(D4/I4)-1 -> 0.0087939698 | N4: =(H4/I4)-1 -> 0.0050251256 | O4: =K4*M4 -> 0.00086825302
A5: 2 | B5: Sothema | C5: 50 | D5: 1795 | E5: =D5*C5 -> 89750 | F5: =E5*0.44% -> 394.9 | G5: =E5+F5 -> 90144.9 | H5: 1840 | I5: 1789 | J5: =I5*C5 -> 89450 | K5: =J5/$J$19 -> 0.089874712 | L5: 0.0053593552 | M5: =(D5/I5)-1 -> 0.003353829 | N5: =(H5/I5)-1 -> 0.028507546 | O5: =K5*M5 -> 0.00030142441
A6: 3 | B6: RISMA | C6: 216 | D6: 416 | E6: =D6*C6 -> 89856 | F6: =E6*0.44% -> 395.3664 | G6: =E6+F6 -> 90251.366 | H6: 419 | I6: 415 | J6: =I6*C6 -> 89640 | K6: =J6/$J$19 -> 0.090065614 | L6: 0.0026871853 | M6: =(D6/I6)-1 -> 0.0024096386 | N6: =(H6/I6)-1 -> 0.0096385542 | O6: =K6*M6 -> 0.00021702558
A7: 4 | B7: Sonasid | C7: 33 | D7: 2410 | E7: =D7*C7 -> 79530 | F7: =E7*0.44% -> 349.932 | G7: =E7+F7 -> 79879.932 | H7: 2500 | I7: 2475 | J7: =I7*C7 -> 81675 | K7: =J7/$J$19 -> 0.082062796 | L7: 0.0098032771 | M7: =(D7/I7)-1 -> -0.026262626 | N7: =(H7/I7)-1 -> 0.01010101 | O7: =K7*M7 -> -0.0021551845
A8: 5 | B8: ATTIJARIWAFA BANK | C8: 128 | D8: 768 | E8: =D8*C8 -> 98304 | F8: =E8*0.44% -> 432.5376 | G8: =E8+F8 -> 98736.538 | H8: 777 | I8: 799.9 | J8: =I8*C8 -> 102387.2 | K8: =J8/$J$19 -> 0.10287334 | L8: 0.17922163 | M8: =(D8/I8)-1 -> -0.039879985 | N8: =(H8/I8)-1 -> -0.028628579 | O8: =K8*M8 -> -0.0041025872
A9: 6 | B9: Sanlam | C9: 46 | D9: 1951 | E9: =D9*C9 -> 89746 | F9: =E9*0.44% -> 394.8824 | G9: =E9+F9 -> 90140.882 | H9: 2000 | I9: 1901 | J9: =I9*C9 -> 87446 | K9: =J9/$J$19 -> 0.087861197 | L9: 0.0015586257 | M9: =(D9/I9)-1 -> 0.026301946 | N9: =(H9/I9)-1 -> 0.052077854 | O9: =K9*M9 -> 0.0023109205
A10: 7 | B10: Marsa maroc | C10: 92 | D10: 975 | E10: =D10*C10 -> 89700 | F10: =E10*0.44% -> 394.68 | G10: =E10+F10 -> 90094.68 | H10: 998 | I10: 985 | J10: =I10*C10 -> 90620 | K10: =J10/$J$19 -> 0.091050267 | L10: 0.081416881 | M10: =(D10/I10)-1 -> -0.010152284 | N10: =(H10/I10)-1 -> 0.01319797 | O10: =K10*M10 -> -0.00092436819
A11: 8 | B11: Ciments du Maroc | C11: 37 | D11: 2003 | E11: =D11*C11 -> 74111 | F11: =E11*0.44% -> 326.0884 | G11: =E11+F11 -> 74437.088 | H11: 2000 | I11: 2020 | J11: =I11*C11 -> 74740 | K11: =J11/$J$19 -> 0.075094868 | L11: 0.046509832 | M11: =(D11/I11)-1 -> -0.0084158416 | N11: =(H11/I11)-1 -> -0.0099009901 | O11: =K11*M11 -> -0.00063198652
A12: 9 | B12: Label vie | C12: 18 | D12: 4698 | E12: =D12*C12 -> 84564 | F12: =E12*0.44% -> 372.0816 | G12: =E12+F12 -> 84936.082 | H12: 4650 | I12: 4690 | J12: =I12*C12 -> 84420 | K12: =J12/$J$19 -> 0.084820829 | L12: 0.019004359 | M12: =(D12/I12)-1 -> 0.0017057569 | N12: =(H12/I12)-1 -> -0.0085287846 | O12: =K12*M12 -> 0.00014468372
A13: 10 | B13: Tgcc | C13: 106 | D13: 931 | E13: =D13*C13 -> 98686 | F13: =E13*0.44% -> 434.2184 | G13: =E13+F13 -> 99120.218 | H13: 961 | I13: 920 | J13: =I13*C13 -> 97520 | K13: =J13/$J$19 -> 0.097983029 | L13: 0.031684414 | M13: =(D13/I13)-1 -> 0.011956522 | N13: =(H13/I13)-1 -> 0.044565217 | O13: =K13*M13 -> 0.0011715362
A14: 11 | B14: HPS | C14: 187 | D14: 528 | E14: =D14*C14 -> 98736 | F14: =E14*0.44% -> 434.4384 | G14: =E14+F14 -> 99170.438 | H14: 0 | I14: 530 | J14: =I14*C14 -> 99110 | K14: =J14/$J$19 -> 0.099580578 | L14: 0.0083459577 | M14: =(D14/I14)-1 -> -0.0037735849 | N14: =(H14/I14)-1 -> -1 | O14: =K14*M14 -> -0.00037577577
A15: 12 | G15: =SUM(G4:G14) -> 996478.65
A16: 13
A17: 14
A18: 15
A19: TOTAL | J19: =SUM(J4:J14) -> 995274.4 | K19: =SUM(K4:K14) -> 1 | L19: =SUM(L4:L14) -> 0.45861613 | M19: =AVERAGE(M4:M14) -> -0.0030875145 | N19: =AVERAGE(N4:N14) -> -0.080358643 | O19: =AVERAGE(O4:O14) -> -0.00028873262
B22: APRES REBALANCEMENT
A24: N° | E24: Mt investi hors commission et frais | F24: Commisions de courtage | G24: Frais de gestion | H24: Mt Investi | I24: Cours le 31/10 | J24: Cours actuel 7/11 | K24: Valorisation actuelle | L24: Poids dans le PTF | M24: Poids dans le MASI | N24: Performance du titres VENDREDI (w)/ (w-1) dans le PTF | O24: Performance du titres VENDREDI (w)/(w-1) dans le MASI | P24: Contribution de la performance dans le PTF
A25: 1 | B25: IAM | C25: 566 | D25: 120.45 | E25: =D25*C25 -> 68174.7 | F25: =E25*0.44% -> 299.96868 | G25: =D25*2% -> 2.409 | H25: =E25+F25 -> 68474.669 | I25: 120 | J25: 115.95 | K25: =J25*C25 -> 65627.7 | L25: =K25/$K$40 -> 0.065513667 | M25: 0.073024613 | N25: =J25/D25-1 -> -0.0373599 | O25: =(J25/I25)-1 -> -0.03375 | P25: =L25*N25 -> -0.0024475841
A26: 2 | B26: Sothema | C26: 57 | D26: =(1795*50+1799*7)/57 -> 1795.4912 | E26: =D26*C26 -> 102343 | F26: =E26*0.44% -> 450.3092 | G26: =D26*2% -> 35.909825 | H26: =E26+F26 -> 102793.31 | I26: 1840 | J26: 1834 | K26: =J26*C26 -> 104538 | L26: =K26/$K$40 -> 0.10435636 | M26: 0.0053593552 | N26: =J26/D26-1 -> 0.021447485 | O26: =(J26/I26)-1 -> -0.0032608696 | P26: =L26*N26 -> 0.0022381815
A27: 3 | B27: RISMA | C27: 253 | D27: =(416*216+394*37)/253 -> 412.78261 | E27: =D27*C27 -> 104434 | F27: =E27*0.44% -> 459.5096 | G27: =D27*2% -> 8.2556522 | H27: =E27+F27 -> 104893.51 | I27: 419 | J27: 419 | K27: =J27*C27 -> 106007 | L27: =K27/$K$40 -> 0.1058228 | M27: 0.0026871853 | N27: =(J27/D27)-1 -> 0.015062145 | O27: =(J27/I27)-1 -> 0 | P27: =L27*N27 -> 0.0015939184
A28: 4 | B28: Sonasid | C28: 41 | D28: =(2410*33+2438*8)/41 -> 2415.4634 | E28: =D28*C28 -> 99034 | F28: =E28*0.44% -> 435.7496 | G28: =D28*2% -> 48.309268 | H28: =E28+F28 -> 99469.75 | I28: 2500 | J28: 2438 | K28: =J28*C28 -> 99958 | L28: =K28/$K$40 -> 0.099784315 | M28: 0.0098032771 | N28: =(J28/D28)-1 -> 0.009330129 | O28: =(J28/I28)-1 -> -0.0248 | P28: =L28*N28 -> 0.00093100054
A29: 5 | B29: ATTIJARIWAFA BANK | C29: 258 | D29: =(768*128+760*130)/258 -> 763.96899 | E29: =D29*C29 -> 197104 | F29: =E29*0.44% -> 867.2576 | G29: =D29*2% -> 15.27938 | H29: =E29+F29 -> 197971.26 | I29: 777 | J29: 766 | K29: =J29*C29 -> 197628 | L29: =K29/$K$40 -> 0.19728461 | M29: 0.17922163 | N29: =(J29/D29)-1 -> 0.002658495 | O29: =(J29/I29)-1 -> -0.014157014 | P29: =L29*N29 -> 0.00052448014
A30: 6 | B30: Sanlam | C30: 50 | D30: =(1951*46+1923*4)/50 -> 1948.76 | E30: =D30*C30 -> 97438 | F30: =E30*0.44% -> 428.7272 | G30: =D30*2% -> 38.9752 | H30: =E30+F30 -> 97866.727 | I30: 2000 | J30: 2000 | K30: =J30*C30 -> 100000 | L30: =K30/$K$40 -> 0.099826242 | M30: 0.0015586257 | N30: =(J30/D30)-1 -> 0.026293643 | O30: =(J30/I30)-1 -> 0 | P30: =L30*N30 -> 0.0026247956
A31: 7 | B31: Marsa maroc | C31: 101 | D31: =(975*92+965.1*9)/101 -> 974.11782 | E31: =D31*C31 -> 98385.9 | F31: =E31*0.44% -> 432.89796 | G31: =D31*2% -> 19.482356 | H31: =E31+F31 -> 98818.798 | I31: 998 | J31: 979.9 | K31: =J31*C31 -> 98969.9 | L31: =K31/$K$40 -> 0.098797932 | M31: 0.081416881 | N31: =(J31/D31)-1 -> 0.0059358099 | O31: =(J31/I31)-1 -> -0.018136273 | P31: =L31*N31 -> 0.00058644575
A32: 8 | B32: Ciments du Maroc | C32: 49 | D32: =(2003*37+2000*12)/49 -> 2002.2653 | E32: =D32*C32 -> 98111 | F32: =E32*0.44% -> 431.6884 | G32: =D32*2% -> 40.045306 | H32: =E32+F32 -> 98542.688 | I32: 2000 | J32: 2000 | K32: =J32*C32 -> 98000 | L32: =K32/$K$40 -> 0.097829718 | M32: 0.046509832 | N32: =(J32/D32)-1 -> -0.0011313716 | O32: =(J32/I32)-1 -> 0 | P32: =L32*N32 -> -0.00011068177
A33: 9 | B33: Label vie | C33: 7 | D33: 4698 | E33: =D33*C33 -> 32886 | F33: =E33*0.44% -> 144.6984 | G33: =D33*2% -> 93.96 | H33: =E33+F33 -> 33030.698 | I33: 4650 | J33: 4646 | K33: =J33*C33 -> 32522 | L33: =K33/$K$40 -> 0.032465491 | M33: 0.019004359 | N33: =(J33/D33)-1 -> -0.01106854 | O33: =(J33/I33)-1 -> -0.00086021505 | P33: =L33*N33 -> -0.00035934557
A34: 10 | B34: Tgcc | C34: 105 | D34: 931 | E34: =D34*C34 -> 97755 | F34: =E34*0.44% -> 430.122 | G34: =D34*2% -> 18.62 | H34: =E34+F34 -> 98185.122 | I34: 961 | J34: 938 | K34: =J34*C34 -> 98490 | L34: =K34/$K$40 -> 0.098318866 | M34: 0.031684414 | N34: =(J34/D34)-1 -> 0.007518797 | O34: =(J34/I34)-1 -> -0.023933403 | P34: =L34*N34 -> 0.0007392396
A35: 11 | B35: HPS | C35: 0 | D35: 0 | E35: =D35*C35 -> 0 | F35: =E35*0.44% -> 0 | H35: =E35+F35 -> 0 | I35: 0 | J35: 0 | K35: =J35*C35 -> 0 | L35: 0 | M35: - | N35: - | O35: - | P35: -
A36: 12 | H36: =SUM(H25:H35) -> 1000046.5
A37: 13
A38: 14
A39: 15
A40: TOTAL | K40: =SUM(K25:K35) -> 1001740.6 | L40: =SUM(L25:L35) -> 1 | M40: =SUM(M25:M35) -> 0.45027017 | N40: =AVERAGE(N25:N35) -> 0.0038686692 | O40: =AVERAGE(O25:O35) -> -0.011889777 | P40: =AVERAGE(P25:P35) -> 0.000632045
B43: APRES SOUSCRIPTION
A46: N° | E46: Mt investi hors commission et frais | F46: Commisions de courtage | G46: Frais de gestion | H46: Cours Ajusté | I46: Mt Investi | J46: Cours le 31/10 | K46: Cours actuel 7/11 | L46: Valorisation actuelle | M46: Poids dans le PTF | N46: Poids dans le MASI | O46: Performance du titres VENDREDI (w)/ (w-1) dans le PTF | P46: Performance du titres VENDREDI (w)/(w-1) dans le MASI | Q46: Contribution de la performance dans le PTF
A47: 1 | B47: IAM | C47: 674 | D47: =(120.45*566+K47*108)/673 -> 119.90684 | E47: =D47*C47 -> 80817.207 | F47: =E47*0.44% -> 355.59571 | G47: =D47*2% -> 2.3981367 | H47: =D47*(1+0.44%) -> 120.43443 | I47: =E47+F47 -> 81172.803 | J47: 120 | K47: 115.95 | L47: =K47*C47 -> 78150.3 | M47: =L47/$L$62 -> 0.065116991 | N47: 0.073024613 | O47: =K47/D47-1 -> -0.032999245 | P47: =(K47/J47)-1 -> -0.03375 | Q47: =M47*O47 -> -0.0021488116
A48: 2 | B48: Sothema | C48: 69 | D48: =(1794.87719298246*57+K48*12)/69 -> 1801.6812 | E48: =D48*C48 -> 124316 | F48: =E48*0.44% -> 546.9904 | G48: =D48*2% -> 36.033623 | H48: =D48*(1+0.44%) -> 1809.6086 | I48: =E48+F48 -> 124862.99 | J48: 1840 | K48: 1834 | L48: =K48*C48 -> 126546 | M48: =L48/$L$62 -> 0.10544163 | N48: 0.0053593552 | O48: =K48/D48-1 -> 0.017938158 | P48: =(K48/J48)-1 -> -0.0032608696 | Q48: =M48*O48 -> 0.0018914285
A49: 3 | B49: RISMA | C49: 304 | D49: =(412.782608695652*253+K49*51)/304 -> 413.82566 | E49: =D49*C49 -> 125803 | F49: =E49*0.44% -> 553.5332 | G49: =D49*2% -> 8.2765132 | H49: =D49*(1+0.44%) -> 415.64649 | I49: =E49+F49 -> 126356.53 | J49: 419 | K49: 419 | L49: =K49*C49 -> 127376 | M49: =L49/$L$62 -> 0.10613321 | N49: 0.0026871853 | O49: =(K49/D49)-1 -> 0.012503676 | P49: =(K49/J49)-1 -> 0 | Q49: =M49*O49 -> 0.0013270553
A50: 4 | B50: Sonasid | C50: 49 | D50: =(2408.0487804878*41+K50*8)/49 -> 2412.9388 | E50: =D50*C50 -> 118234 | F50: =E50*0.44% -> 520.2296 | G50: =D50*2% -> 48.258776 | H50: =D50*(1+0.44%) -> 2423.5557 | I50: =E50+F50 -> 118754.23 | J50: 2500 | K50: 2438 | L50: =K50*C50 -> 119462 | M50: =L50/$L$62 -> 0.099539042 | N50: 0.0098032771 | O50: =(K50/D50)-1 -> 0.010386183 | P50: =(K50/J50)-1 -> -0.0248 | Q50: =M50*O50 -> 0.0010338307
A51: 5 | B51: ATTIJARIWAFA BANK | C51: 309 | D51: =(761.449612403101*258+K51*51)/309 -> 762.20065 | E51: =D51*C51 -> 235520 | F51: =E51*0.44% -> 1036.288 | G51: =D51*2% -> 15.244013 | H51: =D51*(1+0.44%) -> 765.55433 | I51: =E51+F51 -> 236556.29 | J51: 777 | K51: 766 | L51: =K51*C51 -> 236694 | M51: =L51/$L$62 -> 0.19721999 | N51: 0.17922163 | O51: =(K51/D51)-1 -> 0.0049847147 | P51: =(K51/J51)-1 -> -0.014157014 | Q51: =M51*O51 -> 0.00098308536
A52: 6 | B52: Sanlam | C52: 60 | D52: =(1948.76*50+10*K52)/60 -> 1957.3 | E52: =D52*C52 -> 117438 | F52: =E52*0.44% -> 516.7272 | G52: =D52*2% -> 39.146 | H52: =D52*(1+0.44%) -> 1965.9121 | I52: =E52+F52 -> 117954.73 | J52: 2000 | K52: 2000 | L52: =K52*C52 -> 120000 | M52: =L52/$L$62 -> 0.099987318 | N52: 0.0015586257 | O52: =(K52/D52)-1 -> 0.021815767 | P52: =(K52/J52)-1 -> 0 | Q52: =M52*O52 -> 0.0021813
A53: 7 | B53: Marsa maroc | C53: 121 | D53: =(974.117821782178*101+20*K53)/121 -> 975.07355 | E53: =D53*C53 -> 117983.9 | F53: =E53*0.44% -> 519.12916 | G53: =D53*2% -> 19.501471 | H53: =D53*(1+0.44%) -> 979.36388 | I53: =E53+F53 -> 118503.03 | J53: 998 | K53: 979.9 | L53: =K53*C53 -> 118567.9 | M53: =L53/$L$62 -> 0.098794053 | N53: 0.081416881 | O53: =(K53/D53)-1 -> 0.0049498279 | P53: =(K53/J53)-1 -> -0.018136273 | Q53: =M53*O53 -> 0.00048901356
A54: 8 | B54: Ciments du Maroc | C54: 59 | D54: =(2002.26530612245*49+10*K54)/59 -> 2001.8814 | E54: =D54*C54 -> 118111 | F54: =E54*0.44% -> 519.6884 | G54: =D54*2% -> 40.037627 | H54: =D54*(1+0.44%) -> 2010.6896 | I54: =E54+F54 -> 118630.69 | J54: 2000 | K54: 2000 | L54: =K54*C54 -> 118000 | M54: =L54/$L$62 -> 0.098320863 | N54: 0.046509832 | O54: =(K54/D54)-1 -> -0.00093979392 | P54: =(K54/J54)-1 -> 0 | Q54: =M54*O54 -> -9.2401349e-05
A55: 9 | B55: Label vie | C55: 8 | D55: =(4698*8+K55)/9 -> 4692.2222 | E55: =D55*C55 -> 37537.778 | F55: =E55*0.44% -> 165.16622 | G55: =D55*2% -> 93.844444 | H55: =D55*(1+0.44%) -> 4712.868 | I55: =E55+F55 -> 37702.944 | J55: 4650 | K55: 4646 | L55: =K55*C55 -> 37168 | M55: =L55/$L$62 -> 0.030969405 | N55: 0.019004359 | O55: =(K55/D55)-1 -> -0.009850817 | P55: =(K55/J55)-1 -> -0.00086021505 | Q55: =M55*O55 -> -0.00030507394
A56: 10 | B56: Tgcc | C56: 126 | D56: =(931*105+21*K56)/126 -> 932.16667 | E56: =D56*C56 -> 117453 | F56: =E56*0.44% -> 516.7932 | G56: =D56*2% -> 18.643333 | H56: =D56*(1+0.44%) -> 936.2682 | I56: =E56+F56 -> 117969.79 | J56: 961 | K56: 938 | L56: =K56*C56 -> 118188 | M56: =L56/$L$62 -> 0.09847751 | N56: 0.031684414 | O56: =(K56/D56)-1 -> 0.0062578223 | P56: =(K56/J56)-1 -> -0.023933403 | Q56: =M56*O56 -> 0.00061625475
A57: 11 | B57: HPS | C57: 0 | D57: 0 | E57: 0 | H57: 0 | I57: 0 | J57: 0 | K57: =J57*C57 -> 0 | L57: 0 | M57: - | N57: - | O57: - | P57: - | Q57: -
A58: 12 | I58: =SUM(I47:I56) -> 1198464
A59: 13
A60: 14
A61: 15
A62: TOTAL | K62: =SUM(K47:K57) -> 16136.85 | L62: =SUM(L47:L57) -> 1200152.2 | M62: =SUM(M47:M57) -> 1 | N62: =AVERAGE(N47:N57) -> 0.045027017 | O62: =AVERAGE(O47:O57) -> 0.0035046293 | P62: =AVERAGE(P47:P57) -> -0.011889777 | Q62: =AVERAGE(Q47:Q57) -> 0.00059756813
B64: ATTRIBUTION
A67: N° | E67: Mt investi hors commission et frais | F67: Commisions de courtage | G67: Frais de gestion | H67: Mt Investi | I67: Cours le 31/10 | J67: Cours actuel 7/11 | K67: Valorisation actuelle | L67: Poids dans le PTF | M67: Poids dans le MASI | N67: Poids dans le MASI20 | O67: Performance du titres VENDREDI (w)/ (w-1) dans le PTF | P67: Performance du titres VENDREDI (w)/(w-1) dans le MASI | Q67: Contribution de la performance dans le PTF | R67: Contribution de la performance dans MASI20 | S67: ATTRIBUTION
A68: 1 | B68: IAM | C68: 674 | D68: 119.90684 | E68: =D68*C68 -> 80817.207 | F68: =E68*0.44% -> 355.59571 | G68: =D68*2% -> 2.3981367 | H68: =E68+F68 -> 81172.803 | I68: 120 | J68: 115.95 | K68: =J68*C68 -> 78150.3 | L68: =K68/$K$83 -> 0.065116991 | M68: 0.073024613 | N68: 0.092650024 | O68: =J68/D68-1 -> -0.032999245 | P68: =(J68/I68)-1 -> -0.03375 | Q68: =L68*O68 -> -0.0021488116 | R68: =O68*N68 -> -0.0030573809 | S68: =Q68-R68 -> 0.00090856932
A69: 2 | B69: Sothema | C69: 69 | D69: 1801.6812 | E69: =D69*C69 -> 124316 | F69: =E69*0.44% -> 546.9904 | G69: =D69*2% -> 36.033623 | H69: =E69+F69 -> 124862.99 | I69: 1840 | J69: 1834 | K69: =J69*C69 -> 126546 | L69: =K69/$K$83 -> 0.10544163 | M69: 0.0053593552 | N69: 0 | O69: =J69/D69-1 -> 0.017938158 | P69: =(J69/I69)-1 -> -0.0032608696 | Q69: =L69*O69 -> 0.0018914285 | R69: =O69*N69 -> 0 | S69: =Q69-R69 -> 0.0018914285
A70: 3 | B70: RISMA | C70: 304 | D70: 413.82566 | E70: =D70*C70 -> 125803 | F70: =E70*0.44% -> 553.5332 | G70: =D70*2% -> 8.2765132 | H70: =E70+F70 -> 126356.53 | I70: 419 | J70: 419 | K70: =J70*C70 -> 127376 | L70: =K70/$K$83 -> 0.10613321 | M70: 0.0026871853 | N70: 0 | O70: =(J70/D70)-1 -> 0.012503676 | P70: =(J70/I70)-1 -> 0 | Q70: =L70*O70 -> 0.0013270553 | R70: =O70*N70 -> 0 | S70: =Q70-R70 -> 0.0013270553
A71: 4 | B71: Sonasid | C71: 49 | D71: 2412.9388 | E71: =D71*C71 -> 118234 | F71: =E71*0.44% -> 520.2296 | G71: =D71*2% -> 48.258776 | H71: =E71+F71 -> 118754.23 | I71: 2500 | J71: 2438 | K71: =J71*C71 -> 119462 | L71: =K71/$K$83 -> 0.099539042 | M71: 0.0098032771 | N71: 0.012437914 | O71: =(J71/D71)-1 -> 0.010386183 | P71: =(J71/I71)-1 -> -0.0248 | Q71: =L71*O71 -> 0.0010338307 | R71: =O71*N71 -> 0.00012918245 | S71: =Q71-R71 -> 0.00090464828
A72: 5 | B72: ATTIJARIWAFA BANK | C72: 309 | D72: 762.20065 | E72: =D72*C72 -> 235520 | F72: =E72*0.44% -> 1036.288 | G72: =D72*2% -> 15.244013 | H72: =E72+F72 -> 236556.29 | I72: 777 | J72: 766 | K72: =J72*C72 -> 236694 | L72: =K72/$K$83 -> 0.19721999 | M72: 0.17922163 | N72: 0.22738755 | O72: =(J72/D72)-1 -> 0.0049847147 | P72: =(J72/I72)-1 -> -0.014157014 | Q72: =L72*O72 -> 0.00098308536 | R72: =O72*N72 -> 0.0011334621 | S72: =Q72-R72 -> -0.00015037671
A73: 6 | B73: Sanlam | C73: 60 | D73: 1957.3 | E73: =D73*C73 -> 117438 | F73: =E73*0.44% -> 516.7272 | G73: =D73*2% -> 39.146 | H73: =E73+F73 -> 117954.73 | I73: 2000 | J73: 2000 | K73: =J73*C73 -> 120000 | L73: =K73/$K$83 -> 0.099987318 | M73: 0.0015586257 | N73: 0 | O73: =(J73/D73)-1 -> 0.021815767 | P73: =(J73/I73)-1 -> 0 | Q73: =L73*O73 -> 0.0021813 | R73: =O73*N73 -> 0 | S73: =Q73-R73 -> 0.0021813
A74: 7 | B74: Marsa maroc | C74: 121 | D74: 975.07355 | E74: =D74*C74 -> 117983.9 | F74: =E74*0.44% -> 519.12916 | G74: =D74*2% -> 19.501471 | H74: =E74+F74 -> 118503.03 | I74: 998 | J74: 979.9 | K74: =J74*C74 -> 118567.9 | L74: =K74/$K$83 -> 0.098794053 | M74: 0.081416881 | N74: 0.10329772 | O74: =(J74/D74)-1 -> 0.0049498279 | P74: =(J74/I74)-1 -> -0.018136273 | Q74: =L74*O74 -> 0.00048901356 | R74: =O74*N74 -> 0.00051130593 | S74: =Q74-R74 -> -2.2292375e-05
A75: 8 | B75: Ciments du Maroc | C75: 59 | D75: 2001.8814 | E75: =D75*C75 -> 118111 | F75: =E75*0.44% -> 519.6884 | G75: =D75*2% -> 40.037627 | H75: =E75+F75 -> 118630.69 | I75: 2000 | J75: 2000 | K75: =J75*C75 -> 118000 | L75: =K75/$K$83 -> 0.098320863 | M75: 0.046509832 | N75: 0.059009379 | O75: =(J75/D75)-1 -> -0.00093979392 | P75: =(J75/I75)-1 -> 0 | Q75: =L75*O75 -> -9.2401349e-05 | R75: =O75*N75 -> -5.5456656e-05 | S75: =Q75-R75 -> -3.6944694e-05
A76: 9 | B76: Label vie | C76: 8 | D76: 4692.2222 | E76: =D76*C76 -> 37537.778 | F76: =E76*0.44% -> 165.16622 | G76: =D76*2% -> 93.844444 | H76: =E76+F76 -> 37702.944 | I76: 4650 | J76: 4646 | K76: =J76*C76 -> 37168 | L76: =K76/$K$83 -> 0.030969405 | M76: 0.019004359 | N76: 0.024111792 | O76: =(J76/D76)-1 -> -0.009850817 | P76: =(J76/I76)-1 -> -0.00086021505 | Q76: =L76*O76 -> -0.00030507394 | R76: =O76*N76 -> -0.00023752085 | S76: =Q76-R76 -> -6.7553095e-05
A77: 10 | B77: Tgcc | C77: 126 | D77: 932.16667 | E77: =D77*C77 -> 117453 | F77: =E77*0.44% -> 516.7932 | G77: =D77*2% -> 18.643333 | H77: =E77+F77 -> 117969.79 | I77: 961 | J77: 938 | K77: =J77*C77 -> 118188 | L77: =K77/$K$83 -> 0.09847751 | M77: 0.031684414 | N77: 0.04019962 | O77: =(J77/D77)-1 -> 0.0062578223 | P77: =(J77/I77)-1 -> -0.023933403 | Q77: =L77*O77 -> 0.00061625475 | R77: =O77*N77 -> 0.00025156208 | S77: =Q77-R77 -> 0.00036469268
A78: 11 | B78: HPS | C78: 0 | D78: 0 | E78: =D78*C78 -> 0 | F78: =E78*0.44% -> 0 | H78: =E78+F78 -> 0 | I78: 0 | J78: 0 | K78: =J78*C78 -> 0 | L78: 0 | M78: - | N78: - | O78: - | P78: - | Q78: -
A79: 12 | H79: =SUM(H68:H78) -> 1198464
A80: 13
A81: 14
A82: 15
A83: TOTAL | K83: =SUM(K68:K78) -> 1200152.2 | L83: =SUM(L68:L78) -> 1 | M83: =SUM(M68:M78) -> 0.45027017 | O83: =AVERAGE(O68:O78) -> 0.0035046293 | P83: =AVERAGE(P68:P78) -> -0.011889777 | Q83: =AVERAGE(Q68:Q77) -> 0.00059756813 | R83: =AVERAGE(R68:R77) -> -0.00013248458 | S83: =AVERAGE(S68:S77) -> 0.00073005272

Sheet Masi
AE2: 45933 | AK2: 45940 | AQ2: 45947 | AW2: 45954 | BC2: 45961 | BI2: 45968 | BO2: 45975
B3: ENTREPRISE | C3: Cours 03/10/25 | D3: Cours 10/10/25 | E3: Cours 17/10/25 | F3: Cours 24/10/25 | G3: Cours 31/10/25 | H3: Cours 07/11/25 | I3: Cours 14/11/25 | J3: Nbre de titres | K3: Capitalisation Globale 14/11 | L3: Facteurs flottants | M3: Capitalisation flottante 03/10/25 | N3: Capitalisation flottante 10/10/25 | O3: Capitalisation flottante17/10/25 | P3: Capitalisation flottante 24/10/25 | Q3: Capitalisation flottante 31/10/25 | R3: Capitalisation flottante 07/11/25 | S3: Capitalisation flottante 14/11/25 | T3: poids 03/10/25 | U3: poids 10/10/25 | V3: poids 17/10/25 | W3: poids 24/10/25 | X3: poids 31/10/25 | Y3: poids 07/11/25 | Z3: poids 14/11/25 | AA3: Rnet | AB3: fondspropres | AC3: dividende par action | AD3: BPA | AE3: PER | AF3: PER*POIDS | AG3: PBR | AH3: PBR*POID | AI3: DY | AJ3: DY*POIDS | AK3: PER | AL3: PER*POIDS | AM3: PBR | AN3: PBR*POID | AO3: DY | AP3: DY*POIDS | AQ3: PER | AR3: PER*POIDS | AS3: PBR | AT3: PBR*POID | AU3: DY | AV3: DY*POIDS | AW3: PER | AX3: PER*POIDS | AY3: PBR | AZ3: PBR*POID | BA3: DY | BB3: DY*POIDS | BC3: PER | BD3: PER*POIDS | BE3: PBR | BF3: PBR*POID | BG3: DY | BH3: DY*POIDS | BI3: PER | BJ3: PER*POIDS | BK3: PBR | BL3: PBR*POID | BM3: DY | BN3: DY*POIDS | BO3: PER | BP3: PER*POIDS | BQ3: PBR | BR3: PBR*POID | BS3: DY | BT3: DY*POIDS
A4: 1 | B4: AFMA | C4: 1335 | D4: 1260 | E4: 1260 | F4: 1320 | G4: 1320 | H4: 1335 | I4: 1332 | J4: 1000000 | K4: =I4*J4 -> 1332000000 | L4: 0.4443 | M4: =(C4*J4)*L4 -> 593140500 | N4: =(D4*J4)*L4 -> 559818000 | O4: =(E4*J4)*L4 -> 559818000 | P4: =F4*J4*L4 -> 586476000 | Q4: =G4*J4*L4 -> 586476000 | R4: =H4*J4*L4 -> 593140500 | S4: =I4*J4*L4 -> 591807600 | T4: =M4/$M$81 -> 0.0022693756 | U4: =N4/$N$81 -> 0.0021727142 | V4: =O4/$O$81 -> 0.002180016 | W4: =P4/$P$81 -> 0.0021749759 | X4: =Q4/$Q$81 -> 0.0021535155 | Y4: =R4/$R$81 -> 0.0022189695 | Z4: =S4/$S$81 -> 0.0022911041 | AA4: 72354000 | AB4: 68519000 | AC4: 60 | AD4: =AA4/J4 -> 72.354 | AE4: =C4/AD4 -> 18.450949 | AF4: =AE4*T4 -> 0.041872134 | AG4: =(C4*J4)/AB4 -> 19.483647 | AH4: =AG4*T4 -> 0.044215712 | AI4: =AC4/C4 -> 0.04494382 | AJ4: =AI4*T4 -> 0.00010199441 | AK4: =D4/AD4 -> 17.414379 | AL4: =AK4*U4 -> 0.037836469 | AM4: =(D4*J4)/AB4 -> 18.38906 | AN4: =AM4*U4 -> 0.039954172 | AO4: =AC4/D4 -> 0.047619048 | AP4: =AO4*U4 -> 0.00010346258 | AQ4: =E4/AD4 -> 17.414379 | AR4: =AQ4*V4 -> 0.037963625 | AS4: =(E4*J4)/AB4 -> 18.38906 | AT4: =AS4*V4 -> 0.040088444 | AU4: =AC4/E4 -> 0.047619048 | AV4: =AU4*V4 -> 0.00010381028 | AW4: =F4/AD4 -> 18.243635 | AX4: =AW4*W4 -> 0.039679468 | AY4: =(F4*J4)/AB4 -> 19.264729 | AZ4: =AY4*W4 -> 0.041900323 | BA4: =AC4/F4 -> 0.045454545 | BB4: =BA4*W4 -> 9.8862543e-05 | BC4: =G4/AD4 -> 18.243635 | BD4: =BC4*X4 -> 0.039287951 | BE4: =(G4*J4)/AB4 -> 19.264729 | BF4: =BE4*X4 -> 0.041486893 | BG4: =AC4/G4 -> 0.045454545 | BH4: =BG4*X4 -> 9.7887066e-05 | BI4: =H4/AD4 -> 18.450949 | BJ4: =BI4*Y4 -> 0.040942094 | BK4: =(H4*J4)/AB4 -> 19.483647 | BL4: =BK4*Y4 -> 0.043233618 | BM4: =AC4/H4 -> 0.04494382 | BN4: =BM4*Y4 -> 9.9728967e-05 | BO4: =I4/AD4 -> 18.409487 | BP4: =BO4*Z4 -> 0.04217805 | BQ4: =(I4*J4)/AB4 -> 19.439863 | BR4: =BQ4*Z4 -> 0.04453875 | BS4: =AC4/I4 -> 0.045045045 | BT4: =BS4*Z4 -> 0.00010320289
A5: 2 | B5: AFRIC INDUSTRIES SA | C5: 334 | D5: 328 | E5: 331.55 | F5: 330 | G5: 334.45 | H5: 331 | I5: 334.8 | J5: 291500 | K5: =I5*J5 -> 97594200 | L5: 0.49 | M5: =(C5*J5)*L5 -> 47706890 | N5: =(D5*J5)*L5 -> 46849880 | O5: =(E5*J5)*L5 -> 47356944 | P5: =F5*J5*L5 -> 47135550 | Q5: =G5*J5*L5 -> 47771166 | R5: =H5*J5*L5 -> 47278385 | S5: =I5*J5*L5 -> 47821158 | T5: =M5/$M$81 -> 0.00018252817 | U5: =N5/$N$81 -> 0.00018182945 | V5: =O5/$O$81 -> 0.0001844151 | W5: =P5/$P$81 -> 0.00017480457 | X5: =Q5/$Q$81 -> 0.00017541373 | Y5: =R5/$R$81 -> 0.0001768709 | Z5: =S5/$S$81 -> 0.00018513322 | AA5: 9916766.7 | AB5: 48036443 | AC5: 22 | AD5: =AA5/J5 -> 34.019783 | AE5: =C5/AD5 -> 9.8178169 | AF5: =AE5*T5 -> 0.0017920282 | AG5: =(C5*J5)/AB5 -> 2.0268153 | AH5: =AG5*T5 -> 0.00036995089 | AI5: =AC5/C5 -> 0.065868263 | AJ5: =AI5*T5 -> 1.2022814e-05 | AK5: =D5/AD5 -> 9.641449 | AL5: =AK5*U5 -> 0.0017530994 | AM5: =(D5*J5)/AB5 -> 1.9904055 | AN5: =AM5*U5 -> 0.00036191434 | AO5: =AC5/D5 -> 0.067073171 | AP5: =AO5*U5 -> 1.2195878e-05 | AQ5: =E5/AD5 -> 9.7458 | AR5: =AQ5*V5 -> 0.0017972727 | AS5: =(E5*J5)/AB5 -> 2.011948 | AT5: =AS5*V5 -> 0.0003710336 | AU5: =AC5/E5 -> 0.066354999 | AV5: =AU5*V5 -> 1.2236864e-05 | AW5: =F5/AD5 -> 9.7002383 | AX5: =AW5*W5 -> 0.001695646 | AY5: =(F5*J5)/AB5 -> 2.0025421 | AZ5: =AY5*W5 -> 0.00035005352 | BA5: =AC5/F5 -> 0.066666667 | BB5: =BA5*W5 -> 1.1653638e-05 | BC5: =G5/AD5 -> 9.8310445 | BD5: =BC5*X5 -> 0.0017245002 | BE5: =(G5*J5)/AB5 -> 2.0295461 | BF5: =BE5*X5 -> 0.00035601025 | BG5: =AC5/G5 -> 0.065779638 | BH5: =BG5*X5 -> 1.1538652e-05 | BI5: =H5/AD5 -> 9.7296329 | BJ5: =BI5*Y5 -> 0.001720889 | BK5: =(H5*J5)/AB5 -> 2.0086104 | BL5: =BK5*Y5 -> 0.00035526473 | BM5: =AC5/H5 -> 0.066465257 | BN5: =BM5*Y5 -> 1.175577e-05 | BO5: =I5/AD5 -> 9.8413326 | BP5: =BO5*Z5 -> 0.0018219576 | BQ5: =(I5*J5)/AB5 -> 2.03167 | BR5: =BQ5*Z5 -> 0.00037612962 | BS5: =AC5/I5 -> 0.065710872 | BT5: =BS5*Z5 -> 1.2165266e-05
A6: 3 | B6: AFRIQUIA GAZ | C6: 4100 | D6: 4100 | E6: 4100 | F6: 4139 | G6: 4247 | H6: 4189 | I6: 4160 | J6: 3437500 | K6: =I6*J6 -> 14300000000 | L6: 0.2995 | M6: =(C6*J6)*L6 -> 4221078125 | N6: =(D6*J6)*L6 -> 4221078125 | O6: =(E6*J6)*L6 -> 4221078125 | P6: =F6*J6*L6 -> 4.2612298e+09 | Q6: =G6*J6*L6 -> 4.3724192e+09 | R6: =H6*J6*L6 -> 4.3127064e+09 | S6: =I6*J6*L6 -> 4282850000 | T6: =M6/$M$81 -> 0.016149987 | U6: =N6/$N$81 -> 0.016382461 | V6: =O6/$O$81 -> 0.016437517 | W6: =P6/$P$81 -> 0.015802987 | X6: =Q6/$Q$81 -> 0.016055341 | Y6: =R6/$R$81 -> 0.016134059 | Z6: =S6/$S$81 -> 0.016580482 | AA6: 747392000 | AB6: 3238073000 | AC6: 140 | AD6: =AA6/J6 -> 217.42313 | AE6: =C6/AD6 -> 18.85724 | AF6: =AE6*T6 -> 0.30454418 | AG6: =(C6*J6)/AB6 -> 4.3525115 | AH6: =AG6*T6 -> 0.070293005 | AI6: =AC6/C6 -> 0.034146341 | AJ6: =AI6*T6 -> 0.00055146298 | AK6: =D6/AD6 -> 18.85724 | AL6: =AK6*U6 -> 0.30892799 | AM6: =(D6*J6)/AB6 -> 4.3525115 | AN6: =AM6*U6 -> 0.071304849 | AO6: =AC6/D6 -> 0.034146341 | AP6: =AO6*U6 -> 0.0005594011 | AQ6: =E6/AD6 -> 18.85724 | AR6: =AQ6*V6 -> 0.30996619 | AS6: =(E6*J6)/AB6 -> 4.3525115 | AT6: =AS6*V6 -> 0.071544481 | AU6: =AC6/E6 -> 0.034146341 | AV6: =AU6*V6 -> 0.00056128106 | AW6: =F6/AD6 -> 19.036613 | AX6: =AW6*W6 -> 0.30083535 | AY6: =(F6*J6)/AB6 -> 4.3939134 | AZ6: =AY6*W6 -> 0.069436956 | BA6: =AC6/F6 -> 0.033824595 | BB6: =BA6*W6 -> 0.00053452963 | BC6: =G6/AD6 -> 19.533341 | BD6: =BC6*X6 -> 0.31361445 | BE6: =(G6*J6)/AB6 -> 4.508565 | BF6: =BE6*X6 -> 0.07238655 | BG6: =AC6/G6 -> 0.032964445 | BH6: =BG6*X6 -> 0.00052925543 | BI6: =H6/AD6 -> 19.26658 | BJ6: =BI6*Y6 -> 0.31084814 | BK6: =(H6*J6)/AB6 -> 4.4469929 | BL6: =BK6*Y6 -> 0.071748047 | BM6: =AC6/H6 -> 0.033420864 | BN6: =BM6*Y6 -> 0.00053921421 | BO6: =I6/AD6 -> 19.133199 | BP6: =BO6*Z6 -> 0.31723766 | BQ6: =(I6*J6)/AB6 -> 4.4162068 | BR6: =BQ6*Z6 -> 0.073222836 | BS6: =AC6/I6 -> 0.033653846 | BT6: =BS6*Z6 -> 0.00055799698
A7: 4 | B7: AGMA | C7: 6455 | D7: 6200 | E7: 6571 | F7: 6666 | G7: 6600 | H7: 6600 | I7: 6600 | J7: 200000 | K7: =I7*J7 -> 1320000000 | L7: 0.3154 | M7: =(C7*J7)*L7 -> 407181400 | N7: =(D7*J7)*L7 -> 391096000 | O7: =(E7*J7)*L7 -> 414498680 | P7: =F7*J7*L7 -> 420491280 | Q7: =G7*J7*L7 -> 416328000 | R7: =H7*J7*L7 -> 416328000 | S7: =I7*J7*L7 -> 416328000 | T7: =M7/$M$81 -> 0.0015578898 | U7: =N7/$N$81 -> 0.0015178859 | V7: =O7/$O$81 -> 0.0016141206 | W7: =P7/$P$81 -> 0.0015594132 | X7: =Q7/$Q$81 -> 0.0015287391 | Y7: =R7/$R$81 -> 0.0015575047 | Z7: =S7/$S$81 -> 0.0016117582 | AA7: 66626000 | AB7: 157799000 | AC7: 275 | AD7: =AA7/J7 -> 333.13 | AE7: =C7/AD7 -> 19.37682 | AF7: =AE7*T7 -> 0.030186949 | AG7: =(C7*J7)/AB7 -> 8.1812939 | AH7: =AG7*T7 -> 0.012745554 | AI7: =AC7/C7 -> 0.042602634 | AJ7: =AI7*T7 -> 6.6370207e-05 | AK7: =D7/AD7 -> 18.611353 | AL7: =AK7*U7 -> 0.02824991 | AM7: =(D7*J7)/AB7 -> 7.858098 | AN7: =AM7*U7 -> 0.011927696 | AO7: =AC7/D7 -> 0.044354839 | AP7: =AO7*U7 -> 6.7325583e-05 | AQ7: =E7/AD7 -> 19.725032 | AR7: =AQ7*V7 -> 0.03183858 | AS7: =(E7*J7)/AB7 -> 8.3283164 | AT7: =AS7*V7 -> 0.013442907 | AU7: =AC7/E7 -> 0.041850555 | AV7: =AU7*V7 -> 6.7551842e-05 | AW7: =F7/AD7 -> 20.010206 | AX7: =AW7*W7 -> 0.03120418 | AY7: =(F7*J7)/AB7 -> 8.4487227 | AZ7: =AY7*W7 -> 0.01317505 | BA7: =AC7/F7 -> 0.041254125 | BB7: =BA7*W7 -> 6.4332228e-05 | BC7: =G7/AD7 -> 19.812085 | BD7: =BC7*X7 -> 0.030287509 | BE7: =(G7*J7)/AB7 -> 8.365072 | BF7: =BE7*X7 -> 0.012788013 | BG7: =AC7/G7 -> 0.041666667 | BH7: =BG7*X7 -> 6.3697462e-05 | BI7: =H7/AD7 -> 19.812085 | BJ7: =BI7*Y7 -> 0.030857417 | BK7: =(H7*J7)/AB7 -> 8.365072 | BL7: =BK7*Y7 -> 0.013028639 | BM7: =AC7/H7 -> 0.041666667 | BN7: =BM7*Y7 -> 6.4896031e-05 | BO7: =I7/AD7 -> 19.812085 | BP7: =BO7*Z7 -> 0.031932292 | BQ7: =(I7*J7)/AB7 -> 8.365072 | BR7: =BQ7*Z7 -> 0.013482474 | BS7: =AC7/I7 -> 0.041666667 | BT7: =BS7*Z7 -> 6.7156593e-05
A8: 5 | B8: AKDITAL | C8: 1373 | D8: 1285 | E8: 1235 | F8: 1370 | G8: 1440 | H8: 1390 | I8: 1330 | J8: 14159207 | K8: =I8*J8 -> 18831745310 | L8: 0.4524 | M8: =(C8*J8)*L8 -> 8.7949235e+09 | N8: =(D8*J8)*L8 -> 8.2312284e+09 | O8: =(E8*J8)*L8 -> 7.9109472e+09 | P8: =F8*J8*L8 -> 8.7757066e+09 | Q8: =G8*J8*L8 -> 9.2241004e+09 | R8: =H8*J8*L8 -> 8.9038191e+09 | S8: =I8*J8*L8 -> 8.5194816e+09 | T8: =M8/$M$81 -> 0.033649674 | U8: =N8/$N$81 -> 0.031946288 | V8: =O8/$O$81 -> 0.030806425 | W8: =P8/$P$81 -> 0.032545152 | X8: =Q8/$Q$81 -> 0.033870513 | Y8: =R8/$R$81 -> 0.033309651 | Z8: =S8/$S$81 -> 0.032982035 | AA8: 347553992 | AB8: 2638508203 | AC8: 10 | AD8: =AA8/J8 -> 24.546148 | AE8: =C8/AD8 -> 55.935457 | AF8: =AE8*T8 -> 1.8822099 | AG8: =(C8*J8)/AB8 -> 7.3680238 | AH8: =AG8*T8 -> 0.2479316 | AI8: =AC8/C8 -> 0.0072833212 | AJ8: =AI8*T8 -> 0.00024508138 | AK8: =D8/AD8 -> 52.350373 | AL8: =AK8*U8 -> 1.6724001 | AM8: =(D8*J8)/AB8 -> 6.8957834 | AN8: =AM8*U8 -> 0.22029468 | AO8: =AC8/D8 -> 0.0077821012 | AP8: =AO8*U8 -> 0.00024860924 | AQ8: =E8/AD8 -> 50.313393 | AR8: =AQ8*V8 -> 1.5499758 | AS8: =(E8*J8)/AB8 -> 6.627465 | AT8: =AS8*V8 -> 0.2041685 | AU8: =AC8/E8 -> 0.008097166 | AV8: =AU8*V8 -> 0.00024944474 | AW8: =F8/AD8 -> 55.813238 | AX8: =AW8*W8 -> 1.8164503 | AY8: =(F8*J8)/AB8 -> 7.3519247 | AZ8: =AY8*W8 -> 0.23926951 | BA8: =AC8/F8 -> 0.0072992701 | BB8: =BA8*W8 -> 0.00023755586 | BC8: =G8/AD8 -> 58.665009 | BD8: =BC8*X8 -> 1.9870139 | BE8: =(G8*J8)/AB8 -> 7.7275705 | BF8: =BE8*X8 -> 0.26173677 | BG8: =AC8/G8 -> 0.0069444444 | BH8: =BG8*X8 -> 0.00023521189 | BI8: =H8/AD8 -> 56.62803 | BJ8: =BI8*Y8 -> 1.8862599 | BK8: =(H8*J8)/AB8 -> 7.4592521 | BL8: =BK8*Y8 -> 0.24846508 | BM8: =AC8/H8 -> 0.0071942446 | BN8: =BM8*Y8 -> 0.00023963778 | BO8: =I8/AD8 -> 54.183654 | BP8: =BO8*Z8 -> 1.7870872 | BQ8: =(I8*J8)/AB8 -> 7.1372699 | BR8: =BQ8*Z8 -> 0.23540169 | BS8: =AC8/I8 -> 0.007518797 | BT8: =BS8*Z8 -> 0.00024798522
A9: 6 | B9: ALLIANCES | C9: 510 | D9: 515 | E9: 519 | F9: 560 | G9: 617.9 | H9: 618.1 | I9: 595 | J9: 22078588 | K9: =I9*J9 -> 13136759860 | L9: 0.38 | M9: =(C9*J9)*L9 -> 4.2788304e+09 | N9: =(D9*J9)*L9 -> 4.3207797e+09 | O9: =(E9*J9)*L9 -> 4.3543391e+09 | P9: =F9*J9*L9 -> 4.6983235e+09 | Q9: =G9*J9*L9 -> 5.1840966e+09 | R9: =H9*J9*L9 -> 5.1857746e+09 | S9: =I9*J9*L9 -> 4.9919687e+09 | T9: =M9/$M$81 -> 0.016370949 | U9: =N9/$N$81 -> 0.016769413 | V9: =O9/$O$81 -> 0.016956455 | W9: =P9/$P$81 -> 0.017423971 | X9: =Q9/$Q$81 -> 0.019035787 | Y9: =R9/$R$81 -> 0.019400253 | Z9: =S9/$S$81 -> 0.01932574 | AA9: 301915000 | AB9: 3668286000 | AC9: 3.6 | AD9: =AA9/J9 -> 13.674561 | AE9: =C9/AD9 -> 37.29553 | AF9: =AE9*T9 -> 0.61056322 | AG9: =(C9*J9)/AB9 -> 3.0695752 | AH9: =AG9*T9 -> 0.05025186 | AI9: =AC9/C9 -> 0.0070588235 | AJ9: =AI9*T9 -> 0.00011555964 | AK9: =D9/AD9 -> 37.661172 | AL9: =AK9*U9 -> 0.63155576 | AM9: =(D9*J9)/AB9 -> 3.0996691 | AN9: =AM9*U9 -> 0.051979632 | AO9: =AC9/D9 -> 0.0069902913 | AP9: =AO9*U9 -> 0.00011722308 | AQ9: =E9/AD9 -> 37.953686 | AR9: =AQ9*V9 -> 0.64355998 | AS9: =(E9*J9)/AB9 -> 3.1237442 | AT9: =AS9*V9 -> 0.052967629 | AU9: =AC9/E9 -> 0.0069364162 | AV9: =AU9*V9 -> 0.00011761703 | AW9: =F9/AD9 -> 40.951954 | AX9: =AW9*W9 -> 0.71354565 | AY9: =(F9*J9)/AB9 -> 3.370514 | AZ9: =AY9*W9 -> 0.058727737 | BA9: =AC9/F9 -> 0.0064285714 | BB9: =BA9*W9 -> 0.00011201124 | BC9: =G9/AD9 -> 45.186094 | BD9: =BC9*X9 -> 0.86015286 | BE9: =(G9*J9)/AB9 -> 3.7190011 | BF9: =BE9*X9 -> 0.070794112 | BG9: =AC9/G9 -> 0.0058261855 | BH9: =BG9*X9 -> 0.00011090603 | BI9: =H9/AD9 -> 45.20072 | BJ9: =BI9*Y9 -> 0.87690539 | BK9: =(H9*J9)/AB9 -> 3.7202048 | BL9: =BK9*Y9 -> 0.072172914 | BM9: =AC9/H9 -> 0.0058243003 | BN9: =BM9*Y9 -> 0.0001129929 | BO9: =I9/AD9 -> 43.511451 | BP9: =BO9*Z9 -> 0.840891 | BQ9: =(I9*J9)/AB9 -> 3.5811711 | BR9: =BQ9*Z9 -> 0.069208782 | BS9: =AC9/I9 -> 0.0060504202 | BT9: =BS9*Z9 -> 0.00011692885
A10: 7 | B10: ALUMINIUM DU MAROC | C10: 1818 | D10: 1781 | E10: 1814 | F10: 1846 | G10: 1849 | H10: 1867 | I10: 1860 | J10: 465954 | K10: =I10*J10 -> 866674440 | L10: 0.6219 | M10: =(C10*J10)*L10 -> 5.2681421e+08 | N10: =(D10*J10)*L10 -> 5.1609247e+08 | O10: =(E10*J10)*L10 -> 5.256551e+08 | P10: =F10*J10*L10 -> 5.3492796e+08 | Q10: =G10*J10*L10 -> 5.3579729e+08 | R10: =H10*J10*L10 -> 5.4101327e+08 | S10: =I10*J10*L10 -> 5.3898483e+08 | T10: =M10/$M$81 -> 0.0020156089 | U10: =N10/$N$81 -> 0.0020030107 | V10: =O10/$O$81 -> 0.0020469805 | W10: =P10/$P$81 -> 0.0019838074 | X10: =Q10/$Q$81 -> 0.0019674253 | Y10: =R10/$R$81 -> 0.0020239588 | Z10: =S10/$S$81 -> 0.0020866078 | AA10: 36840000 | AB10: 270960000 | AC10: 100 | AD10: =AA10/J10 -> 79.063599 | AE10: =C10/AD10 -> 22.994147 | AF10: =AE10*T10 -> 0.046347208 | AG10: =(C10*J10)/AB10 -> 3.1263078 | AH10: =AG10*T10 -> 0.006301414 | AI10: =AC10/C10 -> 0.055005501 | AJ10: =AI10*T10 -> 0.00011086958 | AK10: =D10/AD10 -> 22.526169 | AL10: =AK10*U10 -> 0.045120158 | AM10: =(D10*J10)/AB10 -> 3.0626811 | AN10: =AM10*U10 -> 0.006134583 | AO10: =AC10/D10 -> 0.056148231 | AP10: =AO10*U10 -> 0.00011246551 | AQ10: =E10/AD10 -> 22.943555 | AR10: =AQ10*V10 -> 0.046965009 | AS10: =(E10*J10)/AB10 -> 3.1194293 | AT10: =AS10*V10 -> 0.0063854108 | AU10: =AC10/E10 -> 0.055126792 | AV10: =AU10*V10 -> 0.00011284347 | AW10: =F10/AD10 -> 23.348292 | AX10: =AW10*W10 -> 0.046318515 | AY10: =(F10*J10)/AB10 -> 3.1744578 | AZ10: =AY10*W10 -> 0.006297513 | BA10: =AC10/F10 -> 0.054171181 | BB10: =BA10*W10 -> 0.00010746519 | BC10: =G10/AD10 -> 23.386236 | BD10: =BC10*X10 -> 0.046010674 | BE10: =(G10*J10)/AB10 -> 3.1796167 | BF10: =BE10*X10 -> 0.0062556585 | BG10: =AC10/G10 -> 0.054083288 | BH10: =BG10*X10 -> 0.00010640483 | BI10: =H10/AD10 -> 23.613901 | BJ10: =BI10*Y10 -> 0.047793564 | BK10: =(H10*J10)/AB10 -> 3.2105703 | BL10: =BK10*Y10 -> 0.0064980621 | BM10: =AC10/H10 -> 0.053561864 | BN10: =BM10*Y10 -> 0.00010840701 | BO10: =I10/AD10 -> 23.525365 | BP10: =BO10*Z10 -> 0.049088209 | BQ10: =(I10*J10)/AB10 -> 3.1985328 | BR10: =BQ10*Z10 -> 0.0066740834 | BS10: =AC10/I10 -> 0.053763441 | BT10: =BS10*Z10 -> 0.00011218321
A11: 8 | B11: ARADEI CAPITAL | C11: 468 | D11: 468 | E11: 462 | F11: 470 | G11: 460 | H11: 460 | I11: 453.9 | J11: 12568130 | K11: =I11*J11 -> 5704674207 | L11: 0.499 | M11: =(C11*J11)*L11 -> 2.9350605e+09 | N11: =(D11*J11)*L11 -> 2.9350605e+09 | O11: =(E11*J11)*L11 -> 2.8974316e+09 | P11: =F11*J11*L11 -> 2.9476035e+09 | Q11: =G11*J11*L11 -> 2.8848886e+09 | R11: =H11*J11*L11 -> 2.8848886e+09 | S11: =I11*J11*L11 -> 2.8466324e+09 | T11: =M11/$M$81 -> 0.011229641 | U11: =N11/$N$81 -> 0.011391287 | V11: =O11/$O$81 -> 0.011283037 | W11: =P11/$P$81 -> 0.010931337 | X11: =Q11/$Q$81 -> 0.010593191 | Y11: =R11/$R$81 -> 0.010792518 | Z11: =S11/$S$81 -> 0.011020357 | AA11: 297453000 | AB11: 5191827000 | AC11: 22 | AD11: =AA11/J11 -> 23.667244 | AE11: =C11/AD11 -> 19.774165 | AF11: =AE11*T11 -> 0.22205677 | AG11: =(C11*J11)/AB11 -> 1.1329123 | AH11: =AG11*T11 -> 0.012722198 | AI11: =AC11/C11 -> 0.047008547 | AJ11: =AI11*T11 -> 0.00052788909 | AK11: =D11/AD11 -> 19.774165 | AL11: =AK11*U11 -> 0.2252532 | AM11: =(D11*J11)/AB11 -> 1.1329123 | AN11: =AM11*U11 -> 0.01290533 | AO11: =AC11/D11 -> 0.047008547 | AP11: =AO11*U11 -> 0.00053548787 | AQ11: =E11/AD11 -> 19.520651 | AR11: =AQ11*V11 -> 0.22025222 | AS11: =(E11*J11)/AB11 -> 1.1183878 | AT11: =AS11*V11 -> 0.012618811 | AU11: =AC11/E11 -> 0.047619048 | AV11: =AU11*V11 -> 0.00053728746 | AW11: =F11/AD11 -> 19.85867 | AX11: =AW11*W11 -> 0.21708182 | AY11: =(F11*J11)/AB11 -> 1.1377538 | AZ11: =AY11*W11 -> 0.012437171 | BA11: =AC11/F11 -> 0.046808511 | BB11: =BA11*W11 -> 0.0005116796 | BC11: =G11/AD11 -> 19.436146 | BD11: =BC11*X11 -> 0.2058908 | BE11: =(G11*J11)/AB11 -> 1.1135463 | BF11: =BE11*X11 -> 0.011796008 | BG11: =AC11/G11 -> 0.047826087 | BH11: =BG11*X11 -> 0.00050663086 | BI11: =H11/AD11 -> 19.436146 | BJ11: =BI11*Y11 -> 0.20976496 | BK11: =(H11*J11)/AB11 -> 1.1135463 | BL11: =BK11*Y11 -> 0.012017969 | BM11: =AC11/H11 -> 0.047826087 | BN11: =BM11*Y11 -> 0.00051616392 | BO11: =I11/AD11 -> 19.178405 | BP11: =BO11*Z11 -> 0.21135288 | BQ11: =(I11*J11)/AB11 -> 1.0987797 | BR11: =BQ11*Z11 -> 0.012108945 | BS11: =AC11/I11 -> 0.048468826 | BT11: =BS11*Z11 -> 0.00053414377
A12: 9 | B12: ATLANTASANAD | C12: 147 | D12: 150.2 | E12: 142.6 | F12: 155.9 | G12: 152 | H12: 150 | I12: 144.4 | J12: 60283595 | K12: =I12*J12 -> 8704951118 | L12: 0.13 | M12: =(C12*J12)*L12 -> 1.1520195e+09 | N12: =(D12*J12)*L12 -> 1.1770975e+09 | O12: =(E12*J12)*L12 -> 1.1175373e+09 | P12: =F12*J12*L12 -> 1.2217676e+09 | Q12: =G12*J12*L12 -> 1.1912038e+09 | R12: =H12*J12*L12 -> 1.1755301e+09 | S12: =I12*J12*L12 -> 1.1316436e+09 | T12: =M12/$M$81 -> 0.0044076655 | U12: =N12/$N$81 -> 0.0045684426 | V12: =O12/$O$81 -> 0.0043518592 | W12: =P12/$P$81 -> 0.0045309871 | X12: =Q12/$Q$81 -> 0.0043740509 | Y12: =R12/$R$81 -> 0.0043977194 | Z12: =S12/$S$81 -> 0.0043810072 | AA12: 453359000 | AB12: 2367775000 | AC12: 5.8 | AD12: =AA12/J12 -> 7.5204374 | AE12: =C12/AD12 -> 19.546736 | AF12: =AE12*T12 -> 0.086155471 | AG12: =(C12*J12)/AB12 -> 3.7426227 | AH12: =AG12*T12 -> 0.016496229 | AI12: =AC12/C12 -> 0.039455782 | AJ12: =AI12*T12 -> 0.00017390789 | AK12: =D12/AD12 -> 19.972243 | AL12: =AK12*U12 -> 0.091242045 | AM12: =(D12*J12)/AB12 -> 3.8240948 | AN12: =AM12*U12 -> 0.017470158 | AO12: =AC12/D12 -> 0.03861518 | AP12: =AO12*U12 -> 0.00017641123 | AQ12: =E12/AD12 -> 18.961663 | AR12: =AQ12*V12 -> 0.082518489 | AS12: =(E12*J12)/AB12 -> 3.6305986 | AT12: =AS12*V12 -> 0.015799854 | AU12: =AC12/E12 -> 0.040673212 | AV12: =AU12*V12 -> 0.00017700409 | AW12: =F12/AD12 -> 20.730177 | AX12: =AW12*W12 -> 0.093928166 | AY12: =(F12*J12)/AB12 -> 3.9692169 | AZ12: =AY12*W12 -> 0.01798447 | BA12: =AC12/F12 -> 0.037203335 | BB12: =BA12*W12 -> 0.00016856783 | BC12: =G12/AD12 -> 20.21159 | BD12: =BC12*X12 -> 0.088406526 | BE12: =(G12*J12)/AB12 -> 3.8699228 | BF12: =BE12*X12 -> 0.016927239 | BG12: =AC12/G12 -> 0.038157895 | BH12: =BG12*X12 -> 0.00016690457 | BI12: =H12/AD12 -> 19.945648 | BJ12: =BI12*Y12 -> 0.087715365 | BK12: =(H12*J12)/AB12 -> 3.8190028 | BL12: =BK12*Y12 -> 0.016794902 | BM12: =AC12/H12 -> 0.038666667 | BN12: =BM12*Y12 -> 0.00017004515 | BO12: =I12/AD12 -> 19.201011 | BP12: =BO12*Z12 -> 0.084119767 | BQ12: =(I12*J12)/AB12 -> 3.6764267 | BR12: =BQ12*Z12 -> 0.016106452 | BS12: =AC12/I12 -> 0.040166205 | BT12: =BS12*Z12 -> 0.00017596843
A13: 10 | B13: ATTIJARIWAFA BANK | C13: 740 | D13: 730 | E13: 728 | F13: 779.9 | G13: 777 | H13: 766 | I13: 736 | J13: 215140839 | K13: =I13*J13 -> 158343657504 | L13: 0.2907 | M13: =(C13*J13)*L13 -> 4.6280667e+10 | N13: =(D13*J13)*L13 -> 4.5655253e+10 | O13: =(E13*J13)*L13 -> 4.553017e+10 | P13: =F13*J13*L13 -> 4.8776071e+10 | Q13: =G13*J13*L13 -> 4.85947e+10 | R13: =H13*J13*L13 -> 4.7906744e+10 | S13: =I13*J13*L13 -> 4.6030501e+10 | T13: =M13/$M$81 -> 0.17707139 | U13: =N13/$N$81 -> 0.17719297 | V13: =O13/$O$81 -> 0.17730137 | W13: =P13/$P$81 -> 0.18088853 | X13: =Q13/$Q$81 -> 0.17843772 | Y13: =R13/$R$81 -> 0.17922163 | Z13: =S13/$S$81 -> 0.17820094 | AA13: 9504486000 | AB13: 72502834000 | AC13: 19 | AD13: =AA13/J13 -> 44.177972 | AE13: =C13/AD13 -> 16.750429 | AF13: =AE13*T13 -> 2.9660218 | AG13: =(C13*J13)/AB13 -> 2.1958345 | AH13: =AG13*T13 -> 0.38881946 | AI13: =AC13/C13 -> 0.025675676 | AJ13: =AI13*T13 -> 0.0045464276 | AK13: =D13/AD13 -> 16.524072 | AL13: =AK13*U13 -> 2.9279495 | AM13: =(D13*J13)/AB13 -> 2.166161 | AN13: =AM13*U13 -> 0.38382851 | AO13: =AC13/D13 -> 0.026027397 | AP13: =AO13*U13 -> 0.0046118719 | AQ13: =E13/AD13 -> 16.478801 | AR13: =AQ13*V13 -> 2.9217139 | AS13: =(E13*J13)/AB13 -> 2.1602263 | AT13: =AS13*V13 -> 0.38301108 | AU13: =AC13/E13 -> 0.026098901 | AV13: =AU13*V13 -> 0.0046273709 | AW13: =F13/AD13 -> 17.653594 | AX13: =AW13*W13 -> 3.1933327 | AY13: =(F13*J13)/AB13 -> 2.3142315 | AZ13: =AY13*W13 -> 0.41861792 | BA13: =AC13/F13 -> 0.024362098 | BB13: =BA13*W13 -> 0.004406824 | BC13: =G13/AD13 -> 17.587951 | BD13: =BC13*X13 -> 3.1383538 | BE13: =(G13*J13)/AB13 -> 2.3056262 | BF13: =BE13*X13 -> 0.41141067 | BG13: =AC13/G13 -> 0.024453024 | BH13: =BG13*X13 -> 0.0043633419 | BI13: =H13/AD13 -> 17.338958 | BJ13: =BI13*Y13 -> 3.1075163 | BK13: =(H13*J13)/AB13 -> 2.2729854 | BL13: =BK13*Y13 -> 0.40736814 | BM13: =AC13/H13 -> 0.024804178 | BN13: =BM13*Y13 -> 0.0044454451 | BO13: =I13/AD13 -> 16.659886 | BP13: =BO13*Z13 -> 2.9688074 | BQ13: =(I13*J13)/AB13 -> 2.1839651 | BR13: =BQ13*Z13 -> 0.38918462 | BS13: =AC13/I13 -> 0.025815217 | BT13: =BS13*Z13 -> 0.0046002959
A14: 11 | B14: AUTO HALL | C14: 95 | D14: 96.38 | E14: 95 | F14: 98.9 | G14: 96 | H14: 95.99 | I14: 94.49 | J14: 50294528 | K14: =I14*J14 -> 4.75233e+09 | L14: 0.3292 | M14: =(C14*J14)*L14 -> 1.5729111e+09 | N14: =(D14*J14)*L14 -> 1.5957597e+09 | O14: =(E14*J14)*L14 -> 1.5729111e+09 | P14: =F14*J14*L14 -> 1.6374832e+09 | Q14: =G14*J14*L14 -> 1.589468e+09 | R14: =H14*J14*L14 -> 1.5893025e+09 | S14: =I14*J14*L14 -> 1.564467e+09 | T14: =M14/$M$81 -> 0.0060180108 | U14: =N14/$N$81 -> 0.0061933159 | V14: =O14/$O$81 -> 0.0061251536 | W14: =P14/$P$81 -> 0.0060726894 | X14: =Q14/$Q$81 -> 0.0058364604 | Y14: =R14/$R$81 -> 0.0059456633 | Z14: =S14/$S$81 -> 0.0060566251 | AA14: 17092037 | AB14: 1.4585141e+09 | AC14: 2 | AD14: =AA14/J14 -> 0.3398389 | AE14: =C14/AD14 -> 279.54422 | AF14: =AE14*T14 -> 1.6823001 | AG14: =(C14*J14)/AB14 -> 3.2759232 | AH14: =AG14*T14 -> 0.019714541 | AI14: =AC14/C14 -> 0.021052632 | AJ14: =AI14*T14 -> 0.00012669496 | AK14: =D14/AD14 -> 283.60496 | AL14: =AK14*U14 -> 1.7564551 | AM14: =(D14*J14)/AB14 -> 3.3235103 | AN14: =AM14*U14 -> 0.020583549 | AO14: =AC14/D14 -> 0.020751193 | AP14: =AO14*U14 -> 0.00012851869 | AQ14: =E14/AD14 -> 279.54422 | AR14: =AQ14*V14 -> 1.7122513 | AS14: =(E14*J14)/AB14 -> 3.2759232 | AT14: =AS14*V14 -> 0.020065533 | AU14: =AC14/E14 -> 0.021052632 | AV14: =AU14*V14 -> 0.0001289506 | AW14: =F14/AD14 -> 291.02024 | AX14: =AW14*W14 -> 1.7672755 | AY14: =(F14*J14)/AB14 -> 3.4104085 | AZ14: =AY14*W14 -> 0.020710352 | BA14: =AC14/F14 -> 0.020222447 | BB14: =BA14*W14 -> 0.00012280464 | BC14: =G14/AD14 -> 282.48679 | BD14: =BC14*X14 -> 1.648723 | BE14: =(G14*J14)/AB14 -> 3.3104066 | BF14: =BE14*X14 -> 0.019321057 | BG14: =AC14/G14 -> 0.020833333 | BH14: =BG14*X14 -> 0.00012159293 | BI14: =H14/AD14 -> 282.45736 | BJ14: =BI14*Y14 -> 1.6793964 | BK14: =(H14*J14)/AB14 -> 3.3100618 | BL14: =BK14*Y14 -> 0.019680513 | BM14: =AC14/H14 -> 0.020835504 | BN14: =BM14*Y14 -> 0.00012388089 | BO14: =I14/AD14 -> 278.0435 | BP14: =BO14*Z14 -> 1.6840053 | BQ14: =(I14*J14)/AB14 -> 3.2583367 | BR14: =BQ14*Z14 -> 0.019734524 | BS14: =AC14/I14 -> 0.021166261 | BT14: =BS14*Z14 -> 0.00012819611
A15: 12 | B15: AUTO NEJMA | C15: 3285 | D15: 3680 | E15: 4122 | F15: 4601 | G15: 4850 | H15: 4875 | I15: 4700 | J15: 1023264 | K15: =I15*J15 -> 4809340800 | L15: 0.0324 | M15: =(C15*J15)*L15 -> 1.0891008e+08 | N15: =(D15*J15)*L15 -> 1.2200581e+08 | O15: =(E15*J15)*L15 -> 1.3665977e+08 | P15: =F15*J15*L15 -> 1.5254042e+08 | Q15: =G15*J15*L15 -> 1.607957e+08 | R15: =H15*J15*L15 -> 1.6162455e+08 | S15: =I15*J15*L15 -> 1.5582264e+08 | T15: =M15/$M$81 -> 0.00041669364 | U15: =N15/$N$81 -> 0.00047351776 | V15: =O15/$O$81 -> 0.00053217382 | W15: =P15/$P$81 -> 0.00056570387 | X15: =Q15/$Q$81 -> 0.00059043514 | Y15: =R15/$R$81 -> 0.00060464586 | Z15: =S15/$S$81 -> 0.00060324654 | AA15: 205383000 | AB15: 1257646000 | AC15: 120 | AD15: =AA15/J15 -> 200.7136 | AE15: =C15/AD15 -> 16.366604 | AF15: =AE15*T15 -> 0.0068198598 | AG15: =(C15*J15)/AB15 -> 2.6727889 | AH15: =AG15*T15 -> 0.0011137341 | AI15: =AC15/C15 -> 0.03652968 | AJ15: =AI15*T15 -> 1.5221685e-05 | AK15: =D15/AD15 -> 18.334582 | AL15: =AK15*U15 -> 0.0086817503 | AM15: =(D15*J15)/AB15 -> 2.9941744 | AN15: =AM15*U15 -> 0.0014177948 | AO15: =AC15/D15 -> 0.032608696 | AP15: =AO15*U15 -> 1.5440796e-05 | AQ15: =E15/AD15 -> 20.536725 | AR15: =AQ15*V15 -> 0.010929108 | AS15: =(E15*J15)/AB15 -> 3.3538008 | AT15: =AS15*V15 -> 0.001784805 | AU15: =AC15/E15 -> 0.029112082 | AV15: =AU15*V15 -> 1.5492688e-05 | AW15: =F15/AD15 -> 22.92321 | AX15: =AW15*W15 -> 0.012967749 | AY15: =(F15*J15)/AB15 -> 3.7435317 | AZ15: =AY15*W15 -> 0.0021177304 | BA15: =AC15/F15 -> 0.026081287 | BB15: =BA15*W15 -> 1.4754285e-05 | BC15: =G15/AD15 -> 24.163784 | BD15: =BC15*X15 -> 0.014267147 | BE15: =(G15*J15)/AB15 -> 3.9461267 | BF15: =BE15*X15 -> 0.0023299318 | BG15: =AC15/G15 -> 0.024742268 | BH15: =BG15*X15 -> 1.4608704e-05 | BI15: =H15/AD15 -> 24.288339 | BJ15: =BI15*Y15 -> 0.014685844 | BK15: =(H15*J15)/AB15 -> 3.9664675 | BL15: =BK15*Y15 -> 0.0023983082 | BM15: =AC15/H15 -> 0.024615385 | BN15: =BM15*Y15 -> 1.488359e-05 | BO15: =I15/AD15 -> 23.41645 | BP15: =BO15*Z15 -> 0.014125893 | BQ15: =(I15*J15)/AB15 -> 3.8240815 | BR15: =BQ15*Z15 -> 0.0023068639 | BS15: =AC15/I15 -> 0.025531915 | BT15: =BS15*Z15 -> 1.5402039e-05
... A80: 77 | B80: ZELLIDJA S.A | C80: 215.3 | D80: 215.35 | E80: 228 | F80: 218 | G80: 214 | H80: 214 | I80: 235 | J80: 57284900 | K80: =I80*J80 -> 13461951500 | L80: 0.1 | M80: =(C80*J80)*L80 -> 1233343897 | N80: =(D80*J80)*L80 -> 1.2336303e+09 | O80: =(E80*J80)*L80 -> 1306095720 | P80: =F80*J80*L80 -> 1248810820 | Q80: =G80*J80*L80 -> 1225896860 | R80: =H80*J80*L80 -> 1225896860 | S80: =I80*J80*L80 -> 1346195150 | T80: =M80/$M$81 -> 0.0047188153 | U80: =N80/$N$81 -> 0.0047878527 | V80: =O80/$O$81 -> 0.0050861343 | W80: =P80/$P$81 -> 0.0046312782 | X80: =Q80/$Q$81 -> 0.0045014422 | Y80: =R80/$R$81 -> 0.004586144 | Z80: =S80/$S$81 -> 0.0052116147 | AA80: 6315000 | AB80: 56572000 | AC80: 20 | AD80: =AA80/J80 -> 0.11023847 | AE80: =C80/AD80 -> 1953.0386 | AF80: =AE80*T80 -> 9.2160287 | AG80: =(C80*J80)/AB80 -> 218.01313 | AH80: =AG80*T80 -> 1.0287637 | AI80: =AC80/C80 -> 0.092893637 | AJ80: =AI80*T80 -> 0.00043834792 | AK80: =D80/AD80 -> 1953.4922 | AL80: =AK80*U80 -> 9.3530329 | AM80: =(D80*J80)/AB80 -> 218.06376 | AN80: =AM80*U80 -> 1.0440572 | AO80: =AC80/D80 -> 0.092872069 | AP80: =AO80*U80 -> 0.00044465779 | AQ80: =E80/AD80 -> 2068.2434 | AR80: =AQ80*V80 -> 10.519364 | AS80: =(E80*J80)/AB80 -> 230.87317 | AT80: =AS80*V80 -> 1.174252 | AU80: =AC80/E80 -> 0.087719298 | AV80: =AU80*V80 -> 0.00044615213 | AW80: =F80/AD80 -> 1977.531 | AX80: =AW80*W80 -> 9.1584961 | AY80: =(F80*J80)/AB80 -> 220.74716 | AZ80: =AY80*W80 -> 1.0223415 | BA80: =AC80/F80 -> 0.091743119 | BB80: =BA80*W80 -> 0.00042488791 | BC80: =G80/AD80 -> 1941.246 | BD80: =BC80*X80 -> 8.7384068 | BE80: =(G80*J80)/AB80 -> 216.69675 | BF80: =BE80*X80 -> 0.97544791 | BG80: =AC80/G80 -> 0.093457944 | BH80: =BG80*X80 -> 0.00042069554 | BI80: =H80/AD80 -> 1941.246 | BJ80: =BI80*Y80 -> 8.9028338 | BK80: =(H80*J80)/AB80 -> 216.69675 | BL80: =BK80*Y80 -> 0.99380251 | BM80: =AC80/H80 -> 0.093457944 | BN80: =BM80*Y80 -> 0.00042861159 | BO80: =I80/AD80 -> 2131.7421 | BP80: =BO80*Z80 -> 11.109819 | BQ80: =(I80*J80)/AB80 -> 237.96139 | BR80: =BQ80*Z80 -> 1.240163 | BS80: =AC80/I80 -> 0.085106383 | BT80: =BS80*Z80 -> 0.00044354167
B81: MASI | M81: =SUM(M4:M80) -> 2.6136727e+11 | N81: =SUM(N4:N80) -> 2.5765837e+11 | O81: =SUM(O4:O80) -> 2.5679537e+11 | P81: =SUM(P4:P80) -> 2.6964712e+11 | Q81: =SUM(Q4:Q80) -> 2.7233424e+11 | R81: =SUM(R4:R80) -> 2.6730448e+11 | S81: =SUM(S4:S80) -> 2.5830673e+11 | T81: =M81/$M$81 -> 1 | U81: =N81/$N$81 -> 1 | V81: =O81/$O$81 -> 1 | W81: =SUM(W4:W80) -> 1 | X81: =SUM(X4:X80) -> 1 | Y81: =SUM(Y4:Y80) -> 1 | Z81: =SUM(Z4:Z80) -> 1 | AF81: =SUM(AF4:AF80) -> 42.59146 | AH81: =SUM(AH4:AH80) -> 6.4335671 | AJ81: =SUM(AJ4:AJ80) -> 0.023867781 | AL81: =SUM(AL4:AL80) -> 42.741778 | AN81: =SUM(AN4:AN80) -> 6.3845461 | AP81: =SUM(AP4:AP80) -> 0.02421135 | AR81: =SUM(AR4:AR80) -> 43.919134 | AT81: =SUM(AT4:AT80) -> 6.4808029 | AV81: =SUM(AV4:AV80) -> 0.024292716 | AX81: =SUM(AX4:AX80) -> 44.025561 | AZ81: =SUM(AZ4:AZ80) -> 6.6082551 | BB81: =SUM(BB4:BB80) -> 0.023134891 | BD81: =SUM(BD4:BD80) -> 44.191078 | BF81: =SUM(BF4:BF80) -> 6.6607942 | BH81: =SUM(BH4:BH80) -> 0.02290662 | BJ81: =SUM(BJ4:BJ80) -> 44.7463 | BL81: =SUM(BL4:BL80) -> 6.5537677 | BN81: =SUM(BN4:BN80) -> 0.023337644 | BP81: =SUM(BP4:BP80) -> 46.05557 | BR81: =SUM(BR4:BR80) -> 6.6483778 | BT81: =SUM(BT4:BT80) -> 0.024150578

Sheet R-R MASI 20
B1: Les cours de clôture | V1: Les rendements
A2: Date | B2: AKDITAL | C2: ALLIANCES | D2: ATTIJARIWAFA BANK | E2: BANK OF AFRICA | F2: BCP | G2: CDM | H2: CFG BANK | I2: CIMENTS DU MAROC | J2: CMGP GROUP | K2: COSUMAR | L2: DOUJA PROM ADDOHA | M2: ITISSALAT AL-MAGHRIB | N2: JET CONTRACTORS | O2: LABEL VIE | P2: LAFARGEHOLCIM MAROC | Q2: RESIDENCES DAR SAADA | R2: SODEP-Marsa Maroc | S2: SONASID | T2: TAQA MOROCCO | U2: TGCC S.A | V2: AKDITAL | W2: ALLIANCES | X2: ATTIJARIWAFA BANK | Y2: BANK OF AFRICA | Z2: BCP | AA2: CDM | AB2: CFG BANK | AC2: CIMENTS DU MAROC | AD2: CMGP GROUP | AE2: COSUMAR | AF2: DOUJA PROM ADDOHA | AG2: ITISSALAT AL-MAGHRIB | AH2: JET CONTRACTORS | AI2: LABEL VIE | AJ2: LAFARGEHOLCIM MAROC | AK2: RESIDENCES DAR SAADA | AL2: SODEP-Marsa Maroc | AM2: SONASID | AN2: TAQA MOROCCO | AO2: TGCC S.A
A3: 45947 | B3: 1235 | C3: 519 | D3: 728 | E3: 225.4 | F3: 280 | G3: 990 | H3: 234 | I3: 1920 | J3: 376.6 | K3: 204 | L3: 36.79 | M3: 115.6 | N3: 2437 | O3: 4690 | P3: 1844 | Q3: 168.1 | R3: 920 | S3: 2415 | T3: 2309 | U3: 900 | V3: =(B3/B4)-1 -> 0.0089869281 | W3: =(C3/C4)-1 -> 0.027926322 | X3: =(D3/D4)-1 -> -0.002739726 | Y3: =(E3/E4)-1 -> 0.0087719298 | Z3: =(F3/F4)-1 -> 0.0035842294 | AA3: =(G3/G4)-1 -> 0 | AB3: =(H3/H4)-1 -> 0.0099266293 | AC3: =(I3/I4)-1 -> -0.034690799 | ... AO3: =(U3/U4)-1 -> 0
A4: 45946 | B4: 1224 | C4: 504.9 | D4: 730 | E4: 223.44 | F4: 279 | G4: 990 | H4: 231.7 | I4: 1989 | J4: 384 | K4: 204.25 | L4: 36 | M4: 115 | N4: 2400 | O4: 4750 | P4: 1860 | Q4: 169.1 | R4: 910 | S4: 2380 | T4: 2340 | U4: 900 | V4: =(B4/B5)-1 -> 0.0032786885 | W4: =(C4/C5)-1 -> 0.0055765784 | X4: =(D4/D5)-1 -> 0.020979021 | Y4: =(E4/E5)-1 -> 0.022187657 | Z4: =(F4/F5)-1 -> -0.001610306 | AA4: =(G4/G5)-1 -> 0 | AB4: =(H4/H5)-1 -> -0.02606137 | AC4: =(I4/I5)-1 -> 0.046842105 | ... AO4: =(U4/U5)-1 -> 0.034482759
A5: 45945 | B5: 1220 | C5: 502.1 | D5: 715 | E5: 218.59 | F5: 279.45 | G5: 990 | H5: 237.9 | I5: 1900 | J5: 368 | K5: 198.9 | L5: 34.91 | M5: 112.95 | N5: 2390 | O5: 4540 | P5: 1837 | Q5: 165 | R5: 903.8 | S5: 2350 | T5: 2340 | U5: 870 | V5: =(B5/B6)-1 -> 0 | W5: =(C5/C6)-1 -> -0.015297117 | X5: =(D5/D6)-1 -> -0.020547945 | Y5: =(E5/E6)-1 -> 0.0092806353 | Z5: =(F5/F6)-1 -> 0.0088447653 | AA5: =(G5/G6)-1 -> -0.01 | AB5: =(H5/H6)-1 -> 0.012340426 | AC5: =(I5/I6)-1 -> 0 | ... AO5: =(U5/U6)-1 -> -0.0057142857
A6: 45944 | B6: 1220 | C6: 509.9 | D6: 730 | E6: 216.58 | F6: 277 | G6: 1000 | H6: 235 | I6: 1900 | J6: 370 | K6: 198 | L6: 35.03 | M6: 113 | N6: 2399 | O6: 4550 | P6: 1806 | Q6: 166.9 | R6: 919 | S6: 2380 | T6: 2300 | U6: 875 | V6: =(B6/B7)-1 -> -0.054263566 | W6: =(C6/C7)-1 -> -0.019423077 | X6: =(D6/D7)-1 -> -0.013246823 | Y6: =(E6/E7)-1 -> -0.053946621 | Z6: =(F6/F7)-1 -> -0.034843206 | AA6: =(G6/G7)-1 -> -0.0039840637 | AB6: =(H6/H7)-1 -> -0.024896266 | AC6: =(I6/I7)-1 -> -0.025641026 | ... AO6: =(U6/U7)-1 -> -0.027669741
A7: 45943 | B7: 1290 | C7: 520 | D7: 739.8 | E7: 228.93 | F7: 287 | G7: 1004 | H7: 241 | I7: 1950 | J7: 384 | K7: 204.05 | L7: 36 | M7: 114.5 | N7: 2440 | O7: 4600 | P7: 1860 | Q7: 173 | R7: 931.1 | S7: 2425 | T7: 2400 | U7: 899.9 | V7: =(B7/B8)-1 -> 0.0038910506 | W7: =(C7/C8)-1 -> 0.0097087379 | X7: =(D7/D8)-1 -> 0.013424658 | Y7: =(E7/E8)-1 -> -0.0063802083 | Z7: =(F7/F8)-1 -> 0.0070175439 | AA7: =(G7/G8)-1 -> 0.013118063 | AB7: =(H7/H8)-1 -> 0.0041666667 | AC7: =(I7/I8)-1 -> 0.0051546392 | ... AO7: =(U7/U8)-1 -> 0.018908514
A8: 45940 | B8: 1285 | C8: 515 | D8: 730 | E8: 230.4 | F8: 285 | G8: 991 | H8: 240 | I8: 1940 | J8: 370 | K8: 204 | L8: 36.15 | M8: 114.5 | N8: 2469 | O8: 4600 | P8: 1800 | Q8: 178 | R8: 935 | S8: 2425 | T8: 2400 | U8: 883.2 | V8: =(B8/B9)-1 -> -0.011538462 | W8: =(C8/C9)-1 -> -0.019047619 | X8: =(D8/D9)-1 -> 0 | Y8: =(E8/E9)-1 -> 0.017757752 | Z8: =(F8/F9)-1 -> 0 | AA8: =(G8/G9)-1 -> -0.0040201005 | AB8: =(H8/H9)-1 -> 0 | AC8: =(I8/I9)-1 -> -0.0046177527 | ... AO8: =(U8/U9)-1 -> -0.018666667
A9: 45939 | B9: 1300 | C9: 525 | D9: 730 | E9: 226.38 | F9: 285 | G9: 995 | H9: 240 | I9: 1949 | J9: 381 | K9: 201 | L9: 36.79 | M9: 115.95 | N9: 2462 | O9: 4600 | P9: 1811 | Q9: 179.7 | R9: 922 | S9: 2390 | T9: 2448 | U9: 900 | V9: =(B9/B10)-1 -> -0.018867925 | W9: =(C9/C10)-1 -> -0.0037950664 | X9: =(D9/D10)-1 -> -0.021447721 | Y9: =(E9/E10)-1 -> -0.041493776 | Z9: =(F9/F10)-1 -> -0.024139702 | AA9: =(G9/G10)-1 -> -0.0089641434 | AB9: =(H9/H10)-1 -> -0.0041493776 | AC9: =(I9/I10)-1 -> 0.0036045314 | ... AO9: =(U9/U10)-1 -> -0.010989011
A10: 45938 | B10: 1325 | C10: 527 | D10: 746 | E10: 236.18 | F10: 292.05 | G10: 1004 | H10: 241 | I10: 1942 | J10: 389.95 | K10: 210 | L10: 37.05 | M10: 116 | N10: 2443 | O10: 4750 | P10: 1870 | Q10: 184 | R10: 935.5 | S10: 2400 | T10: 2450 | U10: 910 | V10: =(B10/B11)-1 -> -0.01266766 | W10: =(C10/C11)-1 -> 0.0038095238 | X10: =(D10/D11)-1 -> -0.0066577896 | Y10: =(E10/E11)-1 -> -0.012295082 | Z10: =(F10/F11)-1 -> 0.00017123288 | AA10: =(G10/G11)-1 -> 0.006012024 | AB10: =(H10/H11)-1 -> -0.012497439 | AC10: =(I10/I11)-1 -> -0.0041025641 | ... AO10: =(U10/U11)-1 -> -0.01194354
A11: 45937 | B11: 1342 | C11: 525 | D11: 751 | E11: 239.12 | F11: 292 | G11: 998 | H11: 244.05 | I11: 1950 | J11: 391.4 | K11: 208 | L11: 37.5 | M11: 117.05 | N11: 2460 | O11: 4700 | P11: 1880 | Q11: 185.9 | R11: 950 | S11: 2411 | T11: 2450 | U11: 921 | V11: =(B11/B12)-1 -> 0.002240478 | W11: =(C11/C12)-1 -> -0.0094339623 | X11: =(D11/D12)-1 -> -0.0066137566 | Y11: =(E11/E12)-1 -> -0.016129032 | Z11: =(F11/F12)-1 -> -0.020134228 | AA11: =(G11/G12)-1 -> -0.028237585 | AB11: =(H11/H12)-1 -> -0.0018404908 | AC11: =(I11/I12)-1 -> -0.025 | ... AO11: =(U11/U12)-1 -> -0.014973262
A12: 45936 | B12: 1339 | C12: 530 | D12: 756 | E12: 243.04 | F12: 298 | G12: 1027 | H12: 244.5 | I12: 2000 | J12: 392 | K12: 213.95 | L12: 38.24 | M12: 117.3 | N12: 2432 | O12: 4700 | P12: 1888 | Q12: 185 | R12: 950 | S12: 2382 | T12: 2425 | U12: 935 | V12: =(B12/B13)-1 -> -0.024763292 | W12: =(C12/C13)-1 -> 0.039215686 | X12: =(D12/D13)-1 -> 0.021621622 | Y12: =(E12/E13)-1 -> 0.029045643 | Z12: =(F12/F13)-1 -> 0.017412086 | AA12: =(G12/G13)-1 -> 0.027 | AB12: =(H12/H13)-1 -> -0.0020408163 | AC12: =(I12/I13)-1 -> 0.01010101 | ... AO12: =(U12/U13)-1 -> 0.021746257
A13: 45933 | B13: 1373 | C13: 510 | D13: 740 | E13: 236.18 | F13: 292.9 | G13: 1000 | H13: 245 | I13: 1980 | J13: 385 | K13: 207.5 | L13: 38.38 | M13: 116.4 | N13: 2439 | O13: 4599 | P13: 1898 | Q13: 173.8 | R13: 936 | S13: 2400 | T13: 2400 | U13: 915.1 | V13: =(B13/B14)-1 -> 0.032330827 | W13: =(C13/C14)-1 -> 0.040816327 | X13: =(D13/D14)-1 -> 0.020830459 | Y13: =(E13/E14)-1 -> -0.024291498 | Z13: =(F13/F14)-1 -> 0.045884663 | AA13: =(G13/G14)-1 -> 0.025641026 | AB13: =(H13/H14)-1 -> 0.042553191 | AC13: =(I13/I14)-1 -> 0.00050530571 | ... AO13: =(U13/U14)-1 -> 0.028202247
A14: 45932 | B14: 1330 | C14: 490 | D14: 724.9 | E14: 242.06 | F14: 280.05 | G14: 975 | H14: 235 | I14: 1979 | J14: 370 | K14: 203 | L14: 37 | M14: 114.1 | N14: 2360 | O14: 4600 | P14: 1878 | Q14: 160 | R14: 915 | S14: 2320 | T14: 2250 | U14: 890 | V14: =(B14/B15)-1 -> 0.0083396513 | W14: =(C14/C15)-1 -> -0.01010101 | X14: =(D14/D15)-1 -> -0.00013793103 | Y14: =(E14/E15)-1 -> 0.046610169 | Z14: =(F14/F15)-1 -> 0.00017857143 | AA14: =(G14/G15)-1 -> -0.0030674847 | AB14: =(H14/H15)-1 -> 0.008583691 | AC14: =(I14/I15)-1 -> 0.041578947 | ... AO14: =(U14/U15)-1 -> 0.011363636
... A209: 45643 | B209: 1059 | C209: 447.9 | D209: 575 | E209: 192.08 | F209: 285.3 | G209: 979.9 | H209: 218 | I209: 1911 | J209: 241.9 | K209: 191.1 | L209: 38 | M209: 86.3 | N209: 1680 | O209: 4099 | P209: 1960 | Q209: 79.45 | R209: 535 | S209: 960 | T209: 1391 | U209: 478 | V209: =(B209/B210)-1 -> -0.0056338028 | W209: =(C209/C210)-1 -> 0.014036676 | X209: =(D209/D210)-1 -> 0.0043668122 | Y209: =(E209/E210)-1 -> 0.018992042 | Z209: =(F209/F210)-1 -> 0 | AA209: =(G209/G210)-1 -> 0.020729167 | AB209: =(H209/H210)-1 -> 0.016317016 | AC209: =(I209/I210)-1 -> -0.019497178 | ... AO209: =(U209/U210)-1 -> 0
A210: 45642 | B210: 1065 | C210: 441.7 | D210: 572.5 | E210: 188.5 | F210: 285.3 | G210: 960 | H210: 214.5 | I210: 1949 | J210: 219.95 | K210: 191 | L210: 37.86 | M210: 86.24 | N210: 1631 | O210: 4085 | P210: 1940 | Q210: 79.9 | R210: 530 | S210: 936 | T210: 1360 | U210: 478
U211: Rendement Moyen | V211: =AVERAGE(V3:V210) -> 0.00084625262 | W211: =AVERAGE(W3:W210) -> 0.0010228972 | X211: =AVERAGE(X3:X210) -> 0.0012367961 | Y211: =AVERAGE(Y3:Y210) -> 0.0010811362 | Z211: =AVERAGE(Z3:Z210) -> 1.6909768e-05 | AA211: =AVERAGE(AA3:AA210) -> 0.00032395039 | AB211: =AVERAGE(AB3:AB210) -> 0.00054858994 | AC211: =AVERAGE(AC3:AC210) -> 0.00016148957 | ... AO211: =AVERAGE(AO3:AO210) -> 0.0033177525
U212: Risque | V212: =SQRT(V213) -> 0.016211792 | W212: =SQRT(W213) -> 0.022162532 | X212: =SQRT(X213) -> 0.012327751 | Y212: =SQRT(Y213) -> 0.020867424 | Z212: =SQRT(Z213) -> 0.01470827 | AA212: =SQRT(AA213) -> 0.018758628 | AB212: =SQRT(AB213) -> 0.01601431 | AC212: =SQRT(AC213) -> 0.02168426 | ... AO212: =SQRT(AO213) -> 0.022821593
U213: Variance | V213: =_xlfn.VAR.S(V3:V210) -> 0.00026282219 | W213: =_xlfn.VAR.S(W3:W210) -> 0.00049117783 | X213: =_xlfn.VAR.S(X3:X210) -> 0.00015197345 | Y213: =_xlfn.VAR.S(Y3:Y210) -> 0.00043544939 | Z213: =_xlfn.VAR.S(Z3:Z210) -> 0.00021633322 | AA213: =_xlfn.VAR.S(AA3:AA210) -> 0.00035188614 | AB213: =_xlfn.VAR.S(AB3:AB210) -> 0.00025645812 | AC213: =_xlfn.VAR.S(AC3:AC210) -> 0.00047020711 | ... AO213: =_xlfn.VAR.S(AO3:AO210) -> 0.0005208251

Sheet Masi 20
AE2: 45933 | AK2: 45940 | AQ2: 45947 | AW2: 45954 | BC2: 45961 | BI2: 45968 | BO2: 45975
B3: ENTREPRISE | C3: Cours 03/10/25 | D3: Cours 10/10/25 | E3: Cours 17/10/25 | F3: Cours 24/10/25 | G3: Cours 31/10/25 | H3: Cours 07/11/25 | I3: Cours 14/11/25 | J3: Nbre de titres | K3: Capitalisation Globale 14/11/25 | L3: Facteurs flottants | M3: Capitalisation flottante 03/10/25 | N3: Capitalisation flottante 10/10/25 | O3: Capitalisation flottante17/10/25 | P3: Capitalisation flottante 24/10/25 | Q3: Capitalisation flottante 31/10/25 | R3: Capitalisation flottante 07/11/25 | S3: Capitalisation flottante 14/11/25 | T3: poids 03/10/25 | U3: poids 10/10/25 | V3: poids 17/10/25 | W3: poids 24/10/25 | X3: poids 31/10/25 | Y3: poids 07/11/25 | Z3: poids 14/11/25 | AA3: Rnet | AB3: fondspropres | AC3: dividende par action | AD3: BPA | AE3: PER | AF3: PER*POIDS | AG3: PBR | AH3: PBR*POID | AI3: DY | AJ3: DY*POIDS | AK3: PER | AL3: PER*POIDS | AM3: PBR | AN3: PBR*POID | AO3: DY | AP3: DY*POIDS | AQ3: PER | AR3: PER*POIDS | AS3: PBR | AT3: PBR*POID | AU3: DY | AV3: DY*POIDS | AW3: PER | AX3: PER*POIDS | AY3: PBR | AZ3: PBR*POID | BA3: DY | BB3: DY*POIDS | BC3: PER | BD3: PER*POIDS | BE3: PBR | BF3: PBR*POID | BG3: DY | BH3: DY*POIDS | BI3: PER | BJ3: PER*POIDS | BK3: PBR | BL3: PBR*POID | BM3: DY | BN3: DY*POIDS | BO3: PER | BP3: PER*POIDS | BQ3: PBR | BR3: PBR*POID | BS3: DY | BT3: DY*POIDS
A4: 1 | B4: AKDITAL | C4: 1373 | D4: 1285 | E4: 1235 | F4: 1370 | G4: 1440 | H4: 1390 | I4: 1330 | J4: 14159207 | K4: =I4*J4 -> 18831745310 | L4: 0.4524 | M4: =(C4*J4)*L4 -> 8.7949235e+09 | N4: =(D4*J4)*L4 -> 8.2312284e+09 | O4: =(E4*J4)*L4 -> 7.9109472e+09 | P4: =F4*J4*L4 -> 8.7757066e+09 | Q4: =G4*J4*L4 -> 9.2241004e+09 | R4: =H4*J4*L4 -> 8.9038191e+09 | S4: =I4*J4*L4 -> 8.5194816e+09 | T4: =M4/$M$24 -> 0.042861286 | U4: =N4/$N$24 -> 0.040852531 | V4: =O4/$O$24 -> 0.039404546 | W4: =P4/$P$24 -> 0.041282943 | X4: =Q4/$Q$24 -> 0.042960284 | Y4: =R4/$R$24 -> 0.042261641 | Z4: =S4/$S$24 -> 0.0420111 | AA4: 347553992 | AB4: 2638508203 | AC4: 10 | AD4: =AA4/J4 -> 24.546148 | AE4: =C4/AD4 -> 55.935457 | AF4: =AE4*T4 -> 2.3974656 | AG4: =(C4*J4)/AB4 -> 7.3680238 | AH4: =AG4*T4 -> 0.31580298 | AI4: =AC4/C4 -> 0.0072833212 | AJ4: =AI4*T4 -> 0.00031217252 | AK4: =D4/AD4 -> 52.350373 | AL4: =AK4*U4 -> 2.1386452 | AM4: =(D4*J4)/AB4 -> 6.8957834 | AN4: =AM4*U4 -> 0.28171021 | AO4: =AC4/D4 -> 0.0077821012 | AP4: =AO4*U4 -> 0.00031791853 | AQ4: =E4/AD4 -> 50.313393 | AR4: =AQ4*V4 -> 1.9825764 | AS4: =(E4*J4)/AB4 -> 6.627465 | AT4: =AS4*V4 -> 0.26115225 | AU4: =AC4/E4 -> 0.008097166 | AV4: =AU4*V4 -> 0.00031906515 | AW4: =F4/AD4 -> 55.813238 | AX4: =AW4*W4 -> 2.3041347 | AY4: =(F4*J4)/AB4 -> 7.3519247 | AZ4: =AY4*W4 -> 0.30350909 | BA4: =AC4/F4 -> 0.0072992701 | BB4: =BA4*W4 -> 0.00030133535 | BC4: =G4/AD4 -> 58.665009 | BD4: =BC4*X4 -> 2.5202654 | BE4: =(G4*J4)/AB4 -> 7.7275705 | BF4: =BE4*X4 -> 0.33197862 | BG4: =AC4/G4 -> 0.0069444444 | BH4: =BG4*X4 -> 0.0002983353 | BI4: =H4/AD4 -> 56.62803 | BJ4: =BI4*Y4 -> 2.3931934 | BK4: =(H4*J4)/AB4 -> 7.4592521 | BL4: =BK4*Y4 -> 0.31524023 | BM4: =AC4/H4 -> 0.0071942446 | BN4: =BM4*Y4 -> 0.00030404058 | BO4: =I4/AD4 -> 54.183654 | BP4: =BO4*Z4 -> 2.2763149 | BQ4: =(I4*J4)/AB4 -> 7.1372699 | BR4: =BQ4*Z4 -> 0.29984456 | BS4: =AC4/I4 -> 0.007518797 | BT4: =BS4*Z4 -> 0.00031587293
A5: 2 | B5: ALLIANCES | C5: 510 | D5: 515 | E5: 519 | F5: 560 | G5: 617.9 | H5: 618.1 | I5: 595 | J5: 22078588 | K5: =I5*J5 -> 13136759860 | L5: 0.38 | M5: =(C5*J5)*L5 -> 4.2788304e+09 | N5: =(D5*J5)*L5 -> 4.3207797e+09 | O5: =(E5*J5)*L5 -> 4.3543391e+09 | P5: =F5*J5*L5 -> 4.6983235e+09 | Q5: =G5*J5*L5 -> 5.1840966e+09 | R5: =H5*J5*L5 -> 5.1857746e+09 | S5: =I5*J5*L5 -> 4.9919687e+09 | T5: =M5/$M$24 -> 0.020852504 | U5: =N5/$N$24 -> 0.021444525 | V5: =O5/$O$24 -> 0.021689028 | W5: =P5/$P$24 -> 0.022101995 | X5: =Q5/$Q$24 -> 0.024144388 | Y5: =R5/$R$24 -> 0.024614083 | Z5: =S5/$S$24 -> 0.024616298 | AA5: 301915000 | AB5: 3668286000 | AC5: 3.6 | AD5: =AA5/J5 -> 13.674561 | AE5: =C5/AD5 -> 37.29553 | AF5: =AE5*T5 -> 0.77770517 | AG5: =(C5*J5)/AB5 -> 3.0695752 | AH5: =AG5*T5 -> 0.064008329 | AI5: =AC5/C5 -> 0.0070588235 | AJ5: =AI5*T5 -> 0.00014719414 | AK5: =D5/AD5 -> 37.661172 | AL5: =AK5*U5 -> 0.80762596 | AM5: =(D5*J5)/AB5 -> 3.0996691 | AN5: =AM5*U5 -> 0.066470933 | AO5: =AC5/D5 -> 0.0069902913 | AP5: =AO5*U5 -> 0.00014990348 | AQ5: =E5/AD5 -> 37.953686 | AR5: =AQ5*V5 -> 0.82317857 | AS5: =(E5*J5)/AB5 -> 3.1237442 | AT5: =AS5*V5 -> 0.067750976 | AU5: =AC5/E5 -> 0.0069364162 | AV5: =AU5*V5 -> 0.00015044413 | AW5: =F5/AD5 -> 40.951954 | AX5: =AW5*W5 -> 0.90511989 | AY5: =(F5*J5)/AB5 -> 3.370514 | AZ5: =AY5*W5 -> 0.074495084 | BA5: =AC5/F5 -> 0.0064285714 | BB5: =BA5*W5 -> 0.00014208425 | BC5: =G5/AD5 -> 45.186094 | BD5: =BC5*X5 -> 1.0909906 | BE5: =(G5*J5)/AB5 -> 3.7190011 | BF5: =BE5*X5 -> 0.089793006 | BG5: =AC5/G5 -> 0.0058261855 | BH5: =BG5*X5 -> 0.00014066969 | BI5: =H5/AD5 -> 45.20072 | BJ5: =BI5*Y5 -> 1.1125743 | BK5: =(H5*J5)/AB5 -> 3.7202048 | BL5: =BK5*Y5 -> 0.091569431 | BM5: =AC5/H5 -> 0.0058243003 | BN5: =BM5*Y5 -> 0.00014335981 | BO5: =I5/AD5 -> 43.511451 | BP5: =BO5*Z5 -> 1.0710909 | BQ5: =(I5*J5)/AB5 -> 3.5811711 | BR5: =BQ5*Z5 -> 0.088155175 | BS5: =AC5/I5 -> 0.0060504202 | BT5: =BS5*Z5 -> 0.00014893895
A6: 3 | B6: ATTIJARIWAFA BANK | C6: 740 | D6: 730 | E6: 728 | F6: 779.9 | G6: 777 | H6: 766 | I6: 736 | J6: 215140839 | K6: =I6*J6 -> 158343657504 | L6: 0.2907 | M6: =(C6*J6)*L6 -> 4.6280667e+10 | N6: =(D6*J6)*L6 -> 4.5655253e+10 | O6: =(E6*J6)*L6 -> 4.553017e+10 | P6: =F6*J6*L6 -> 4.8776071e+10 | Q6: =G6*J6*L6 -> 4.85947e+10 | R6: =H6*J6*L6 -> 4.7906744e+10 | S6: =I6*J6*L6 -> 4.6030501e+10 | T6: =M6/$M$24 -> 0.22554476 | U6: =N6/$N$24 -> 0.22659226 | V6: =O6/$O$24 -> 0.22678645 | W6: =P6/$P$24 -> 0.22945386 | X6: =Q6/$Q$24 -> 0.22632474 | Y6: =R6/$R$24 -> 0.22738755 | Z6: =S6/$S$24 -> 0.2269847 | AA6: 9504486000 | AB6: 72502834000 | AC6: 19 | AD6: =AA6/J6 -> 44.177972 | AE6: =C6/AD6 -> 16.750429 | AF6: =AE6*T6 -> 3.7779716 | AG6: =(C6*J6)/AB6 -> 2.1958345 | AH6: =AG6*T6 -> 0.49525896 | AI6: =AC6/C6 -> 0.025675676 | AJ6: =AI6*T6 -> 0.0057910142 | AK6: =D6/AD6 -> 16.524072 | AL6: =AK6*U6 -> 3.7442268 | AM6: =(D6*J6)/AB6 -> 2.166161 | AN6: =AM6*U6 -> 0.49083532 | AO6: =AC6/D6 -> 0.026027397 | AP6: =AO6*U6 -> 0.0058976067 | AQ6: =E6/AD6 -> 16.478801 | AR6: =AQ6*V6 -> 3.7371688 | AS6: =(E6*J6)/AB6 -> 2.1602263 | AT6: =AS6*V6 -> 0.48991007 | AU6: =AC6/E6 -> 0.026098901 | AV6: =AU6*V6 -> 0.0059188772 | AW6: =F6/AD6 -> 17.653594 | AX6: =AW6*W6 -> 4.0506854 | AY6: =(F6*J6)/AB6 -> 2.3142315 | AZ6: =AY6*W6 -> 0.53100935 | BA6: =AC6/F6 -> 0.024362098 | BB6: =BA6*W6 -> 0.0055899774 | BC6: =G6/AD6 -> 17.587951 | BD6: =BC6*X6 -> 3.9805884 | BE6: =(G6*J6)/AB6 -> 2.3056262 | BF6: =BE6*X6 -> 0.52182025 | BG6: =AC6/G6 -> 0.024453024 | BH6: =BG6*X6 -> 0.0055343244 | BI6: =H6/AD6 -> 17.338958 | BJ6: =BI6*Y6 -> 3.9426632 | BK6: =(H6*J6)/AB6 -> 2.2729854 | BL6: =BK6*Y6 -> 0.51684859 | BM6: =AC6/H6 -> 0.024804178 | BN6: =BM6*Y6 -> 0.0056401612 | BO6: =I6/AD6 -> 16.659886 | BP6: =BO6*Z6 -> 3.7815393 | BQ6: =(I6*J6)/AB6 -> 2.1839651 | BR6: =BQ6*Z6 -> 0.49572666 | BS6: =AC6/I6 -> 0.025815217 | BT6: =BS6*Z6 -> 0.0058596594
A7: 4 | B7: BANK OF AFRICA | C7: 241 | D7: 235.1 | E7: 230 | F7: 245 | G7: 242 | H7: 235 | I7: 227 | J7: 215786333 | K7: =I7*J7 -> 48983497591 | L7: 0.2124 | M7: =(C7*J7)*L7 -> 1.1045757e+10 | N7: =(D7*J7)*L7 -> 1.0775342e+10 | O7: =(E7*J7)*L7 -> 1.0541594e+10 | P7: =F7*J7*L7 -> 1.1229089e+10 | Q7: =G7*J7*L7 -> 1.109159e+10 | R7: =H7*J7*L7 -> 1.0770759e+10 | S7: =I7*J7*L7 -> 1.0404095e+10 | T7: =M7/$M$24 -> 0.053830526 | U7: =N7/$N$24 -> 0.053479261 | V7: =O7/$O$24 -> 0.052507837 | W7: =P7/$P$24 -> 0.05282422 | X7: =Q7/$Q$24 -> 0.051657923 | Y7: =R7/$R$24 -> 0.051123001 | Z7: =S7/$S$24 -> 0.051304468 | AA7: 3427420000 | AB7: 36814698000 | AC7: 5 | AD7: =AA7/J7 -> 15.883397 | AE7: =C7/AD7 -> 15.173077 | AF7: =AE7*T7 -> 0.8167747 | AG7: =(C7*J7)/AB7 -> 1.4126017 | AH7: =AG7*T7 -> 0.076041095 | AI7: =AC7/C7 -> 0.020746888 | AJ7: =AI7*T7 -> 0.0011168159 | AK7: =D7/AD7 -> 14.80162 | AL7: =AK7*U7 -> 0.79157967 | AM7: =(D7*J7)/AB7 -> 1.3780194 | AN7: =AM7*U7 -> 0.073695457 | AO7: =AC7/D7 -> 0.021267546 | AP7: =AO7*U7 -> 0.0011373726 | AQ7: =E7/AD7 -> 14.48053 | AR7: =AQ7*V7 -> 0.76034128 | AS7: =(E7*J7)/AB7 -> 1.3481261 | AT7: =AS7*V7 -> 0.070787187 | AU7: =AC7/E7 -> 0.02173913 | AV7: =AU7*V7 -> 0.0011414747 | AW7: =F7/AD7 -> 15.424912 | AX7: =AW7*W7 -> 0.81480894 | AY7: =(F7*J7)/AB7 -> 1.4360474 | AZ7: =AY7*W7 -> 0.075858084 | BA7: =AC7/F7 -> 0.020408163 | BB7: =BA7*W7 -> 0.0010780453 | BC7: =G7/AD7 -> 15.236035 | BD7: =BC7*X7 -> 0.78706194 | BE7: =(G7*J7)/AB7 -> 1.4184632 | BF7: =BE7*X7 -> 0.07327486 | BG7: =AC7/G7 -> 0.020661157 | BH7: =BG7*X7 -> 0.0010673124 | BI7: =H7/AD7 -> 14.795324 | BJ7: =BI7*Y7 -> 0.75638134 | BK7: =(H7*J7)/AB7 -> 1.3774332 | BL7: =BK7*Y7 -> 0.07041852 | BM7: =AC7/H7 -> 0.021276596 | BN7: =BM7*Y7 -> 0.0010877234 | BO7: =I7/AD7 -> 14.291653 | BP7: =BO7*Z7 -> 0.73322565 | BQ7: =(I7*J7)/AB7 -> 1.3305419 | BR7: =BQ7*Z7 -> 0.068262743 | BS7: =AC7/I7 -> 0.022026432 | BT7: =BS7*Z7 -> 0.0011300544
A8: 5 | B8: BCP | C8: 292.9 | D8: 285 | E8: 280 | F8: 298 | G8: 309 | H8: 309 | I8: 287 | J8: 203312473 | K8: =I8*J8 -> 58350679751 | L8: 0.2941 | M8: =(C8*J8)*L8 -> 1.7513721e+10 | N8: =(D8*J8)*L8 -> 1.7041347e+10 | O8: =(E8*J8)*L8 -> 1.6742376e+10 | P8: =F8*J8*L8 -> 1.7818671e+10 | Q8: =G8*J8*L8 -> 1.8476407e+10 | R8: =H8*J8*L8 -> 1.8476407e+10 | S8: =I8*J8*L8 -> 1.7160935e+10 | T8: =M8/$M$24 -> 0.085351578 | U8: =N8/$N$24 -> 0.084578158 | V8: =O8/$O$24 -> 0.083394022 | W8: =P8/$P$24 -> 0.08382313 | X8: =Q8/$Q$24 -> 0.086051937 | Y8: =R8/$R$24 -> 0.087697569 | Z8: =S8/$S$24 -> 0.084623664 | AA8: 4145346000 | AB8: 57167311000 | AC8: 10.5 | AD8: =AA8/J8 -> 20.389039 | AE8: =C8/AD8 -> 14.365562 | AF8: =AE8*T8 -> 1.2261234 | AG8: =(C8*J8)/AB8 -> 1.0416831 | AH8: =AG8*T8 -> 0.088909299 | AI8: =AC8/C8 -> 0.035848412 | AJ8: =AI8*T8 -> 0.0030597186 | AK8: =D8/AD8 -> 13.978099 | AL8: =AK8*U8 -> 1.1822418 | AM8: =(D8*J8)/AB8 -> 1.0135872 | AN8: =AM8*U8 -> 0.085727339 | AO8: =AC8/D8 -> 0.036842105 | AP8: =AO8*U8 -> 0.0031160374 | AQ8: =E8/AD8 -> 13.732869 | AR8: =AQ8*V8 -> 1.1452392 | AS8: =(E8*J8)/AB8 -> 0.99580497 | AT8: =AS8*V8 -> 0.083044182 | AU8: =AC8/E8 -> 0.0375 | AV8: =AU8*V8 -> 0.0031272758 | AW8: =F8/AD8 -> 14.615696 | AX8: =AW8*W8 -> 1.2251334 | AY8: =(F8*J8)/AB8 -> 1.059821 | AZ8: =AY8*W8 -> 0.088837513 | BA8: =AC8/F8 -> 0.035234899 | BB8: =BA8*W8 -> 0.0029534995 | BC8: =G8/AD8 -> 15.155202 | BD8: =BC8*X8 -> 1.3041344 | BE8: =(G8*J8)/AB8 -> 1.0989419 | BF8: =BE8*X8 -> 0.09456608 | BG8: =AC8/G8 -> 0.033980583 | BH8: =BG8*X8 -> 0.0029240949 | BI8: =H8/AD8 -> 15.155202 | BJ8: =BI8*Y8 -> 1.3290743 | BK8: =(H8*J8)/AB8 -> 1.0989419 | BL8: =BK8*Y8 -> 0.096374534 | BM8: =AC8/H8 -> 0.033980583 | BN8: =BM8*Y8 -> 0.0029800145 | BO8: =I8/AD8 -> 14.07619 | BP8: =BO8*Z8 -> 1.1911788 | BQ8: =(I8*J8)/AB8 -> 1.0207001 | BR8: =BQ8*Z8 -> 0.086375382 | BS8: =AC8/I8 -> 0.036585366 | BT8: =BS8*Z8 -> 0.0030959877
A9: 6 | B9: CDM | C9: 978 | D9: 991 | E9: 990 | F9: 1030 | G9: 1050 | H9: 1025 | I9: 980 | J9: 10881214 | K9: =I9*J9 -> 10663589720 | L9: 0.4539 | M9: =(C9*J9)*L9 -> 4.8303254e+09 | N9: =(D9*J9)*L9 -> 4.8945322e+09 | O9: =(E9*J9)*L9 -> 4.8895932e+09 | P9: =F9*J9*L9 -> 5.0871525e+09 | Q9: =G9*J9*L9 -> 5.1859322e+09 | R9: =H9*J9*L9 -> 5.0624576e+09 | S9: =I9*J9*L9 -> 4.8402034e+09 | T9: =M9/$M$24 -> 0.023540166 | U9: =N9/$N$24 -> 0.024292125 | V9: =O9/$O$24 -> 0.024355137 | W9: =P9/$P$24 -> 0.023931136 | X9: =Q9/$Q$24 -> 0.024152937 | Y9: =R9/$R$24 -> 0.024028764 | Z9: =S9/$S$24 -> 0.023867915 | AA9: 740949000 | AB9: 7878853000 | AC9: 41.7 | AD9: =AA9/J9 -> 68.094332 | AE9: =C9/AD9 -> 14.362429 | AF9: =AE9*T9 -> 0.33809396 | AG9: =(C9*J9)/AB9 -> 1.3506823 | AH9: =AG9*T9 -> 0.031795286 | AI9: =AC9/C9 -> 0.042638037 | AJ9: =AI9*T9 -> 0.0010037065 | AK9: =D9/AD9 -> 14.55334 | AL9: =AK9*U9 -> 0.35353157 | AM9: =(D9*J9)/AB9 -> 1.3686362 | AN9: =AM9*U9 -> 0.03324708 | AO9: =AC9/D9 -> 0.042078708 | AP9: =AO9*U9 -> 0.0010221812 | AQ9: =E9/AD9 -> 14.538655 | AR9: =AQ9*V9 -> 0.35409093 | AS9: =(E9*J9)/AB9 -> 1.3672551 | AT9: =AS9*V9 -> 0.033299684 | AU9: =AC9/E9 -> 0.042121212 | AV9: =AU9*V9 -> 0.0010258679 | AW9: =F9/AD9 -> 15.126075 | AX9: =AW9*W9 -> 0.36198417 | AY9: =(F9*J9)/AB9 -> 1.4224977 | AZ9: =AY9*W9 -> 0.034041987 | BA9: =AC9/F9 -> 0.040485437 | BB9: =BA9*W9 -> 0.00096886251 | BC9: =G9/AD9 -> 15.419786 | BD9: =BC9*X9 -> 0.37243312 | BE9: =(G9*J9)/AB9 -> 1.450119 | BF9: =BE9*X9 -> 0.035024634 | BG9: =AC9/G9 -> 0.039714286 | BH9: =BG9*X9 -> 0.00095921666 | BI9: =H9/AD9 -> 15.052648 | BJ9: =BI9*Y9 -> 0.36169652 | BK9: =(H9*J9)/AB9 -> 1.4155924 | BL9: =BK9*Y9 -> 0.034014935 | BM9: =AC9/H9 -> 0.040682927 | BN9: =BM9*Y9 -> 0.00097756044 | BO9: =I9/AD9 -> 14.3918 | BP9: =BO9*Z9 -> 0.34350226 | BQ9: =(I9*J9)/AB9 -> 1.3534444 | BR9: =BQ9*Z9 -> 0.032303897 | BS9: =AC9/I9 -> 0.04255102 | BT9: =BS9*Z9 -> 0.0010156042
A10: 7 | B10: CFG BANK | C10: 245 | D10: 240 | E10: 234 | F10: 259.9 | G10: 255 | H10: 254.9 | I10: 253.5 | J10: 35007960 | K10: =I10*J10 -> 8874517860 | L10: 0.304 | M10: =(C10*J10)*L10 -> 2.6073929e+09 | N10: =(D10*J10)*L10 -> 2.5541808e+09 | O10: =(E10*J10)*L10 -> 2.4903262e+09 | P10: =F10*J10*L10 -> 2.7659649e+09 | Q10: =G10*J10*L10 -> 2.7138171e+09 | R10: =H10*J10*L10 -> 2.7127528e+09 | S10: =I10*J10*L10 -> 2.6978534e+09 | T10: =M10/$M$24 -> 0.0127069 | U10: =N10/$N$24 -> 0.012676692 | V10: =O10/$O$24 -> 0.012404352 | W10: =P10/$P$24 -> 0.013011736 | X10: =Q10/$Q$24 -> 0.012639319 | Y10: =R10/$R$24 -> 0.012875979 | Z10: =S10/$S$24 -> 0.013303602 | AA10: 275193000 | AB10: 1840062000 | AC10: 3.3 | AD10: =AA10/J10 -> 7.8608694 | AE10: =C10/AD10 -> 31.167036 | AF10: =AE10*T10 -> 0.39603641 | AG10: =(C10*J10)/AB10 -> 4.6612289 | AH10: =AG10*T10 -> 0.059229769 | AI10: =AC10/C10 -> 0.013469388 | AJ10: =AI10*T10 -> 0.00017115416 | AK10: =D10/AD10 -> 30.530974 | AL10: =AK10*U10 -> 0.38703176 | AM10: =(D10*J10)/AB10 -> 4.5661018 | AN10: =AM10*U10 -> 0.057883067 | AO10: =AC10/D10 -> 0.01375 | AP10: =AO10*U10 -> 0.00017430452 | AQ10: =E10/AD10 -> 29.7677 | AR10: =AQ10*V10 -> 0.36924903 | AS10: =(E10*J10)/AB10 -> 4.4519492 | AT10: =AS10*V10 -> 0.055223546 | AU10: =AC10/E10 -> 0.014102564 | AV10: =AU10*V10 -> 0.00017493317 | AW10: =F10/AD10 -> 33.062501 | AX10: =AW10*W10 -> 0.43020052 | AY10: =(F10*J10)/AB10 -> 4.9447077 | AZ10: =AY10*W10 -> 0.064339229 | BA10: =AC10/F10 -> 0.012697191 | BB10: =BA10*W10 -> 0.00016521249 | BC10: =G10/AD10 -> 32.43916 | BD10: =BC10*X10 -> 0.41000891 | BE10: =(G10*J10)/AB10 -> 4.8514832 | BF10: =BE10*X10 -> 0.061319446 | BG10: =AC10/G10 -> 0.012941176 | BH10: =BG10*X10 -> 0.00016356766 | BI10: =H10/AD10 -> 32.426439 | BJ10: =BI10*Y10 -> 0.41752214 | BK10: =(H10*J10)/AB10 -> 4.8495806 | BL10: =BK10*Y10 -> 0.062443097 | BM10: =AC10/H10 -> 0.012946253 | BN10: =BM10*Y10 -> 0.00016669568 | BO10: =I10/AD10 -> 32.248342 | BP10: =BO10*Z10 -> 0.42901909 | BQ10: =(I10*J10)/AB10 -> 4.822945 | BR10: =BQ10*Z10 -> 0.064162539 | BS10: =AC10/I10 -> 0.013017751 | BT10: =BS10*Z10 -> 0.00017318298
A11: 8 | B11: CIMENTS DU MAROC | C11: 1980 | D11: 1940 | E11: 1989 | F11: 2020 | G11: 2000 | H11: 2000 | I11: 1910 | J11: 14436004 | K11: =I11*J11 -> 27572767640 | L11: 0.4306 | M11: =(C11*J11)*L11 -> 1.2307964e+10 | N11: =(D11*J11)*L11 -> 1.2059318e+10 | O11: =(E11*J11)*L11 -> 1.2363909e+10 | P11: =F11*J11*L11 -> 1.255661e+10 | Q11: =G11*J11*L11 -> 1.2432287e+10 | R11: =H11*J11*L11 -> 1.2432287e+10 | S11: =I11*J11*L11 -> 1.1872834e+10 | T11: =M11/$M$24 -> 0.059981779 | U11: =N11/$N$24 -> 0.059851779 | V11: =O11/$O$24 -> 0.061584815 | W11: =P11/$P$24 -> 0.059069181 | X11: =Q11/$Q$24 -> 0.057902076 | Y11: =R11/$R$24 -> 0.059009379 | Z11: =S11/$S$24 -> 0.058547084 | AA11: 914161000 | AB11: 3329472000 | AC11: 60 | AD11: =AA11/J11 -> 63.325073 | AE11: =C11/AD11 -> 31.267236 | AF11: =AE11*T11 -> 1.8754645 | AG11: =(C11*J11)/AB11 -> 8.5849312 | AH11: =AG11*T11 -> 0.51493945 | AI11: =AC11/C11 -> 0.03030303 | AJ11: =AI11*T11 -> 0.0018176297 | AK11: =D11/AD11 -> 30.635575 | AL11: =AK11*U11 -> 1.8335937 | AM11: =(D11*J11)/AB11 -> 8.4114982 | AN11: =AM11*U11 -> 0.50344314 | AO11: =AC11/D11 -> 0.030927835 | AP11: =AO11*U11 -> 0.001851086 | AQ11: =E11/AD11 -> 31.40936 | AR11: =AQ11*V11 -> 1.9343396 | AS11: =(E11*J11)/AB11 -> 8.6239536 | AT11: =AS11*V11 -> 0.53110459 | AU11: =AC11/E11 -> 0.030165913 | AV11: =AU11*V11 -> 0.0018577622 | AW11: =F11/AD11 -> 31.898898 | AX11: =AW11*W11 -> 1.8842417 | AY11: =(F11*J11)/AB11 -> 8.7583641 | AZ11: =AY11*W11 -> 0.51734939 | BA11: =AC11/F11 -> 0.02970297 | BB11: =BA11*W11 -> 0.0017545301 | BC11: =G11/AD11 -> 31.583067 | BD11: =BC11*X11 -> 1.8287252 | BE11: =(G11*J11)/AB11 -> 8.6716476 | BF11: =BE11*X11 -> 0.5021064 | BG11: =AC11/G11 -> 0.03 | BH11: =BG11*X11 -> 0.0017370623 | BI11: =H11/AD11 -> 31.583067 | BJ11: =BI11*Y11 -> 1.8636972 | BK11: =(H11*J11)/AB11 -> 8.6716476 | BL11: =BK11*Y11 -> 0.51170854 | BM11: =AC11/H11 -> 0.03 | BN11: =BM11*Y11 -> 0.0017702814 | BO11: =I11/AD11 -> 30.161829 | BP11: =BO11*Z11 -> 1.7658871 | BQ11: =(I11*J11)/AB11 -> 8.2814235 | BR11: =BQ11*Z11 -> 0.4848532 | BS11: =AC11/I11 -> 0.031413613 | BT11: =BS11*Z11 -> 0.0018391754
A12: 9 | B12: CMGP GROUP | C12: 385 | D12: 370 | E12: 376.6 | F12: 387.5 | G12: 383.5 | H12: 375 | I12: 360 | J12: 17000900 | K12: =I12*J12 -> 6120324000 | L12: 0.5 | M12: =(C12*J12)*L12 -> 3272673250 | N12: =(D12*J12)*L12 -> 3145166500 | O12: =(E12*J12)*L12 -> 3201269470 | P12: =F12*J12*L12 -> 3293924375 | Q12: =G12*J12*L12 -> 3259922575 | R12: =H12*J12*L12 -> 3187668750 | S12: =I12*J12*L12 -> 3060162000 | T12: =M12/$M$24 -> 0.015949085 | U12: =N12/$N$24 -> 0.015609822 | V12: =O12/$O$24 -> 0.015945571 | W12: =P12/$P$24 -> 0.015495378 | X12: =Q12/$Q$24 -> 0.015182749 | Y12: =R12/$R$24 -> 0.015130149 | Z12: =S12/$S$24 -> 0.015090211 | AA12: 182532410 | AB12: 2634396857 | AC12: 6.3 | AD12: =AA12/J12 -> 10.736632 | AE12: =C12/AD12 -> 35.858544 | AF12: =AE12*T12 -> 0.57191098 | AG12: =(C12*J12)/AB12 -> 2.4845712 | AH12: =AG12*T12 -> 0.039626638 | AI12: =AC12/C12 -> 0.016363636 | AJ12: =AI12*T12 -> 0.00026098503 | AK12: =D12/AD12 -> 34.461458 | AL12: =AK12*U12 -> 0.53793724 | AM12: =(D12*J12)/AB12 -> 2.3877697 | AN12: =AM12*U12 -> 0.037272661 | AO12: =AC12/D12 -> 0.017027027 | AP12: =AO12*U12 -> 0.00026578887 | AQ12: =E12/AD12 -> 35.076176 | AR12: =AQ12*V12 -> 0.55930965 | AS12: =(E12*J12)/AB12 -> 2.4303624 | AT12: =AS12*V12 -> 0.038753515 | AU12: =AC12/E12 -> 0.016728625 | AV12: =AU12*V12 -> 0.00026674747 | AW12: =F12/AD12 -> 36.091392 | AX12: =AW12*W12 -> 0.55924977 | AY12: =(F12*J12)/AB12 -> 2.5007048 | AZ12: =AY12*W12 -> 0.038749366 | BA12: =AC12/F12 -> 0.016258065 | BB12: =BA12*W12 -> 0.00025192486 | BC12: =G12/AD12 -> 35.718836 | BD12: =BC12*X12 -> 0.54231011 | BE12: =(G12*J12)/AB12 -> 2.474891 | BF12: =BE12*X12 -> 0.037575649 | BG12: =AC12/G12 -> 0.01642764 | BH12: =BG12*X12 -> 0.00024941674 | BI12: =H12/AD12 -> 34.927153 | BJ12: =BI12*Y12 -> 0.52845305 | BK12: =(H12*J12)/AB12 -> 2.4200369 | BL12: =BK12*Y12 -> 0.036615519 | BM12: =AC12/H12 -> 0.0168 | BN12: =BM12*Y12 -> 0.00025418651 | BO12: =I12/AD12 -> 33.530067 | BP12: =BO12*Z12 -> 0.50597578 | BQ12: =(I12*J12)/AB12 -> 2.3232354 | BR12: =BQ12*Z12 -> 0.035058111 | BS12: =AC12/I12 -> 0.0175 | BT12: =BS12*Z12 -> 0.00026407868
A13: 10 | B13: COSUMAR | C13: 207.5 | D13: 204 | E13: 204 | F13: 218.1 | G13: 217 | H13: 210 | I13: 204 | J13: 94487143 | K13: =I13*J13 -> 19275377172 | L13: 0.5935 | M13: =(C13*J13)*L13 -> 1.163621e+10 | N13: =(D13*J13)*L13 -> 1.1439936e+10 | O13: =(E13*J13)*L13 -> 1.1439936e+10 | P13: =F13*J13*L13 -> 1.2230638e+10 | Q13: =G13*J13*L13 -> 1.2168952e+10 | R13: =H13*J13*L13 -> 1.1776405e+10 | S13: =I13*J13*L13 -> 1.1439936e+10 | T13: =M13/$M$24 -> 0.056708045 | U13: =N13/$N$24 -> 0.056777717 | V13: =O13/$O$24 -> 0.056982493 | W13: =P13/$P$24 -> 0.057535735 | X13: =Q13/$Q$24 -> 0.056675622 | Y13: =R13/$R$24 -> 0.055896262 | Z13: =S13/$S$24 -> 0.056412389 | AA13: 850400000 | AB13: 5885600000 | AC13: 10 | AD13: =AA13/J13 -> 9.0001663 | AE13: =C13/AD13 -> 23.05513 | AF13: =AE13*T13 -> 1.3074113 | AG13: =(C13*J13)/AB13 -> 3.3311951 | AH13: =AG13*T13 -> 0.18890557 | AI13: =AC13/C13 -> 0.048192771 | AJ13: =AI13*T13 -> 0.0027329179 | AK13: =D13/AD13 -> 22.666248 | AL13: =AK13*U13 -> 1.2869378 | AM13: =(D13*J13)/AB13 -> 3.2750063 | AN13: =AM13*U13 -> 0.18594738 | AO13: =AC13/D13 -> 0.049019608 | AP13: =AO13*U13 -> 0.0027832214 | AQ13: =E13/AD13 -> 22.666248 | AR13: =AQ13*V13 -> 1.2915793 | AS13: =(E13*J13)/AB13 -> 3.2750063 | AT13: =AS13*V13 -> 0.18661803 | AU13: =AC13/E13 -> 0.049019608 | AV13: =AU13*V13 -> 0.0027932595 | AW13: =F13/AD13 -> 24.232886 | AX13: =AW13*W13 -> 1.3942569 | AY13: =(F13*J13)/AB13 -> 3.501367 | AZ13: =AY13*W13 -> 0.20145373 | BA13: =AC13/F13 -> 0.045850527 | BB13: =BA13*W13 -> 0.0026380438 | BC13: =G13/AD13 -> 24.110666 | BD13: =BC13*X13 -> 1.366487 | BE13: =(G13*J13)/AB13 -> 3.4837077 | BF13: =BE13*X13 -> 0.1974413 | BG13: =AC13/G13 -> 0.046082949 | BH13: =BG13*X13 -> 0.0026117798 | BI13: =H13/AD13 -> 23.332902 | BJ13: =BI13*Y13 -> 1.304222 | BK13: =(H13*J13)/AB13 -> 3.37133 | BL13: =BK13*Y13 -> 0.18844475 | BM13: =AC13/H13 -> 0.047619048 | BN13: =BM13*Y13 -> 0.0026617267 | BO13: =I13/AD13 -> 22.666248 | BP13: =BO13*Z13 -> 1.2786572 | BQ13: =(I13*J13)/AB13 -> 3.2750063 | BR13: =BQ13*Z13 -> 0.18475093 | BS13: =AC13/I13 -> 0.049019608 | BT13: =BS13*Z13 -> 0.0027653132
A14: 11 | B14: DOUJA PROM ADDOHA | C14: 38.38 | D14: 36.15 | E14: 36.79 | F14: 40.9 | G14: 40.91 | H14: 39.71 | I14: 37.81 | J14: 402551254 | K14: =I14*J14 -> 1.5220463e+10 | L14: 0.3082 | M14: =(C14*J14)*L14 -> 4.7616645e+09 | N14: =(D14*J14)*L14 -> 4.4849966e+09 | O14: =(E14*J14)*L14 -> 4.564399e+09 | P14: =F14*J14*L14 -> 5.0743115e+09 | Q14: =G14*J14*L14 -> 5.0755522e+09 | R14: =H14*J14*L14 -> 4.9266726e+09 | S14: =I14*J14*L14 -> 4.6909467e+09 | T14: =M14/$M$24 -> 0.023205553 | U14: =N14/$N$24 -> 0.022259553 | V14: =O14/$O$24 -> 0.02273534 | W14: =P14/$P$24 -> 0.023870729 | X14: =Q14/$Q$24 -> 0.023638854 | Y14: =R14/$R$24 -> 0.023384265 | Z14: =S14/$S$24 -> 0.023131904 | AA14: 274184241 | AB14: 10201900882 | AC14: 0.5 | AD14: =AA14/J14 -> 0.68111635 | AE14: =C14/AD14 -> 56.348669 | AF14: =AE14*T14 -> 1.307602 | AG14: =(C14*J14)/AB14 -> 1.5144155 | AH14: =AG14*T14 -> 0.03514285 | AI14: =AC14/C14 -> 0.013027619 | AJ14: =AI14*T14 -> 0.00030231309 | AK14: =D14/AD14 -> 53.074633 | AL14: =AK14*U14 -> 1.1814176 | AM14: =(D14*J14)/AB14 -> 1.4264232 | AN14: =AM14*U14 -> 0.031751542 | AO14: =AC14/D14 -> 0.013831259 | AP14: =AO14*U14 -> 0.00030787763 | AQ14: =E14/AD14 -> 54.014266 | AR14: =AQ14*V14 -> 1.2280327 | AS14: =(E14*J14)/AB14 -> 1.4516766 | AT14: =AS14*V14 -> 0.03300436 | AU14: =AC14/E14 -> 0.01359065 | AV14: =AU14*V14 -> 0.00030898804 | AW14: =F14/AD14 -> 60.048478 | AX14: =AW14*W14 -> 1.433401 | AY14: =(F14*J14)/AB14 -> 1.6138508 | AZ14: =AY14*W14 -> 0.038523796 | BA14: =AC14/F14 -> 0.012224939 | BB14: =BA14*W14 -> 0.00029181821 | BC14: =G14/AD14 -> 60.06316 | BD14: =BC14*X14 -> 1.4198243 | BE14: =(G14*J14)/AB14 -> 1.6142454 | BF14: =BE14*X14 -> 0.038158912 | BG14: =AC14/G14 -> 0.012221951 | BH14: =BG14*X14 -> 0.00028891291 | BI14: =H14/AD14 -> 58.301346 | BJ14: =BI14*Y14 -> 1.3633342 | BK14: =(H14*J14)/AB14 -> 1.5668953 | BL14: =BK14*Y14 -> 0.036640695 | BM14: =AC14/H14 -> 0.012591287 | BN14: =BM14*Y14 -> 0.00029443799 | BO14: =I14/AD14 -> 55.511808 | BP14: =BO14*Z14 -> 1.2840938 | BQ14: =(I14*J14)/AB14 -> 1.4919242 | BR14: =BQ14*Z14 -> 0.034511047 | BS14: =AC14/I14 -> 0.013224015 | BT14: =BS14*Z14 -> 0.00030589664
A15: 12 | B15: ITISSALAT AL-MAGHRIB | C15: 116.4 | D15: 114.5 | E15: 115.6 | F15: 119.4 | G15: 120 | H15: 115.95 | I15: 112.9 | J15: 879095340 | K15: =I15*J15 -> 99249863886 | L15: 0.1915 | M15: =(C15*J15)*L15 -> 1.9595563e+10 | N15: =(D15*J15)*L15 -> 1.9275704e+10 | O15: =(E15*J15)*L15 -> 1.9460885e+10 | P15: =F15*J15*L15 -> 2.0100603e+10 | Q15: =G15*J15*L15 -> 2.0201611e+10 | R15: =H15*J15*L15 -> 1.9519807e+10 | S15: =I15*J15*L15 -> 1.9006349e+10 | T15: =M15/$M$24 -> 0.095497252 | U15: =N15/$N$24 -> 0.09566753 | V15: =O15/$O$24 -> 0.096934959 | W15: =P15/$P$24 -> 0.094557862 | X15: =Q15/$Q$24 -> 0.094086893 | Y15: =R15/$R$24 -> 0.092650024 | Z15: =S15/$S$24 -> 0.093723733 | AA15: 1801000000 | AB15: 18702000000 | AC15: 1.43 | AD15: =AA15/J15 -> 2.048697 | AE15: =C15/AD15 -> 56.816601 | AF15: =AE15*T15 -> 5.4258292 | AG15: =(C15*J15)/AB15 -> 5.4714307 | AH15: =AG15*T15 -> 0.5225066 | AI15: =AC15/C15 -> 0.012285223 | AJ15: =AI15*T15 -> 0.0011732051 | AK15: =D15/AD15 -> 55.889182 | AL15: =AK15*U15 -> 5.34678 | AM15: =(D15*J15)/AB15 -> 5.3821204 | AN15: =AM15*U15 -> 0.51489417 | AO15: =AC15/D15 -> 0.012489083 | AP15: =AO15*U15 -> 0.0011947997 | AQ15: =E15/AD15 -> 56.426108 | AR15: =AQ15*V15 -> 5.4696625 | AS15: =(E15*J15)/AB15 -> 5.4338264 | AT15: =AS15*V15 -> 0.52672774 | AU15: =AC15/E15 -> 0.012370242 | AV15: =AU15*V15 -> 0.0011991089 | AW15: =F15/AD15 -> 58.280946 | AX15: =AW15*W15 -> 5.5109216 | AY15: =(F15*J15)/AB15 -> 5.612447 | AZ15: =AY15*W15 -> 0.53070099 | BA15: =AC15/F15 -> 0.011976549 | BB15: =BA15*W15 -> 0.0011324769 | BC15: =G15/AD15 -> 58.573815 | BD15: =BC15*X15 -> 5.5110282 | BE15: =(G15*J15)/AB15 -> 5.6406502 | BF15: =BE15*X15 -> 0.53071125 | BG15: =AC15/G15 -> 0.011916667 | BH15: =BG15*X15 -> 0.0011212021 | BI15: =H15/AD15 -> 56.596949 | BJ15: =BI15*Y15 -> 5.2437087 | BK15: =(H15*J15)/AB15 -> 5.4502783 | BL15: =BK15*Y15 -> 0.50496842 | BM15: =AC15/H15 -> 0.012332902 | BN15: =BM15*Y15 -> 0.0011426437 | BO15: =I15/AD15 -> 55.108198 | BP15: =BO15*Z15 -> 5.164946 | BQ15: =(I15*J15)/AB15 -> 5.3069118 | BR15: =BQ15*Z15 -> 0.49738358 | BS15: =AC15/I15 -> 0.012666076 | BT15: =BS15*Z15 -> 0.0011871119
... A23: 20 | B23: TGCC S.A | C23: 915 | D23: 883.2 | E23: 900 | F23: 920 | G23: 961 | H23: 938 | I23: 899 | J23: 34674332 | K23: =I23*J23 -> 31172224468 | L23: 0.2604 | M23: =(C23*J23)*L23 -> 8.2617144e+09 | N23: =(D23*J23)*L23 -> 7.974586e+09 | O23: =(E23*J23)*L23 -> 8.1262764e+09 | P23: =F23*J23*L23 -> 8.3068604e+09 | Q23: =G23*J23*L23 -> 8.6770574e+09 | R23: =H23*J23*L23 -> 8.4693859e+09 | S23: =I23*J23*L23 -> 8.1172473e+09 | T23: =M23/$M$24 -> 0.040262739 | U23: =N23/$N$24 -> 0.039578785 | V23: =O23/$O$24 -> 0.040477104 | W23: =P23/$P$24 -> 0.039077383 | X23: =Q23/$Q$24 -> 0.040412488 | Y23: =R23/$R$24 -> 0.04019962 | Z23: =S23/$S$24 -> 0.04002761 | AA23: 521810000 | AB23: 1761218000 | AC23: 11.5 | AD23: =AA23/J23 -> 15.048884 | AE23: =C23/AD23 -> 60.801851 | AF23: =AE23*T23 -> 2.448049 | AG23: =(C23*J23)/AB23 -> 18.014246 | AH23: =AG23*T23 -> 0.72530287 | AI23: =AC23/C23 -> 0.012568306 | AJ23: =AI23*T23 -> 0.00050603442 | AK23: =D23/AD23 -> 58.688737 | AL23: =AK23*U23 -> 2.3228289 | AM23: =(D23*J23)/AB23 -> 17.388177 | AN23: =AM23*U23 -> 0.68820292 | AO23: =AC23/D23 -> 0.013020833 | AP23: =AO23*U23 -> 0.00051534877 | AQ23: =E23/AD23 -> 59.805099 | AR23: =AQ23*V23 -> 2.4207372 | AS23: =(E23*J23)/AB23 -> 17.71893 | AT23: =AS23*V23 -> 0.71721098 | AU23: =AC23/E23 -> 0.012777778 | AV23: =AU23*V23 -> 0.00051720744 | AW23: =F23/AD23 -> 61.134101 | AX23: =AW23*W23 -> 2.3889607 | AY23: =(F23*J23)/AB23 -> 18.112684 | AZ23: =AY23*W23 -> 0.7077963 | BA23: =AC23/F23 -> 0.0125 | BB23: =BA23*W23 -> 0.00048846729 | BC23: =G23/AD23 -> 63.858556 | BD23: =BC23*X23 -> 2.5806832 | BE23: =(G23*J23)/AB23 -> 18.91988 | BF23: =BE23*X23 -> 0.76459943 | BG23: =AC23/G23 -> 0.011966701 | BH23: =BG23*X23 -> 0.00048360418 | BI23: =H23/AD23 -> 62.330203 | BJ23: =BI23*Y23 -> 2.5056505 | BK23: =(H23*J23)/AB23 -> 18.467063 | BL23: =BK23*Y23 -> 0.74236891 | BM23: =AC23/H23 -> 0.012260128 | BN23: =BM23*Y23 -> 0.00049285249 | BO23: =I23/AD23 -> 59.738649 | BP23: =BO23*Z23 -> 2.3911953 | BQ23: =(I23*J23)/AB23 -> 17.699242 | BR23: =BQ23*Z23 -> 0.70845837 | BS23: =AC23/I23 -> 0.012791991 | BT23: =BS23*Z23 -> 0.00051203283
B24: MASI | M24: =SUM(M4:M23) -> 2.0519504e+11 | N24: =SUM(N4:N23) -> 2.0148637e+11 | O24: =SUM(O4:O23) -> 2.007623e+11 | P24: =SUM(P4:P23) -> 2.1257463e+11 | Q24: =SUM(Q4:Q23) -> 2.1471228e+11 | R24: =SUM(R4:R23) -> 2.1068323e+11 | S24: =SUM(S4:S23) -> 2.0279121e+11 | T24: =M24/$M$24 -> 1 | U24: =N24/$N$24 -> 1 | V24: =O24/$O$24 -> 1 | W24: =SUM(W4:W23) -> 1 | X24: =SUM(X4:X23) -> 1 | Y24: =SUM(Y4:Y23) -> 1 | Z24: =S24/$S$24 -> 1 | AF24: =SUM(AF4:AF23) -> 33.064006 | AH24: =SUM(AH4:AH23) -> 5.7781658 | AJ24: =SUM(AJ4:AJ23) -> 0.022654264 | AL24: =SUM(AL4:AL23) -> 32.396997 | AN24: =SUM(AN4:AN23) -> 5.7030631 | AP24: =SUM(AP4:AP23) -> 0.023071251 | AR24: =SUM(AR4:AR23) -> 32.357574 | AT24: =SUM(AT4:AT23) -> 5.6788506 | AV24: =SUM(AV4:AV23) -> 0.023154461 | AX24: =SUM(AX4:AX23) -> 34.11178 | AZ24: =SUM(AZ4:AZ23) -> 5.9737882 | BB24: =SUM(BB4:BB23) -> 0.021867815 | BD24: =SUM(BD4:BD23) -> 34.668528 | BF24: =SUM(BF4:BF23) -> 6.0795629 | BH24: =SUM(BH4:BH23) -> 0.021650102 | BJ24: =SUM(BJ4:BJ23) -> 33.892243 | BL24: =SUM(BL4:BL23) -> 5.9513232 | BN24: =SUM(BN4:BN23) -> 0.022064132 | BP24: =SUM(BP4:BP23) -> 32.731838 | BR24: =SUM(BR4:BR23) -> 5.7958422 | BT24: =SUM(BT4:BT23) -> 0.022922802

Sheet R-R PF
B1: Les cours de clôture | M1: Les rendements
A2: Date | B2: IAM | C2: Sothema | D2: RISMA | E2: Sonasid | F2: ATTIJARIWAFA BANK | G2: Sanlam | H2: Marsa maroc | I2: Ciments du Maroc | J2: Label vie | K2: Tgcc | L2: HPS | M2: IAM | N2: Sothema | O2: RISMA | P2: Sonasid | Q2: ATTIJARIWAFA BANK | R2: Sanlam | S2: Marsa maroc | T2: Ciments du Maroc | U2: Label vie | V2: Tgcc | W2: HPS
A3: 17/10/2025 | B3: 115.6 | C3: 1711 | D3: 420 | E3: 2415 | F3: 728 | G3: 2028 | H3: 920 | I3: 1920 | J3: 4690 | K3: 900 | L3: 5102 | M3: =(B3/B4)-1 -> 0.0052173913 | N3: =(C3/C4)-1 -> -0.059373282 | O3: =(D3/D4)-1 -> 0.037037037 | P3: =(E3/E4)-1 -> 0.014705882 | Q3: =(F3/F4)-1 -> -0.002739726 | R3: =(G3/G4)-1 -> 0.061780105 | S3: =(H3/H4)-1 -> 0.010989011 | T3: =(I3/I4)-1 -> -0.034690799 | ... W3: =(L3/L4)-1 -> 0.0023575639
A4: 16/10/2025 | B4: 115 | C4: 1819 | D4: 405 | E4: 2380 | F4: 730 | G4: 1910 | H4: 910 | I4: 1989 | J4: 4750 | K4: 900 | L4: 5090 | M4: =(B4/B5)-1 -> 0.018149624 | N4: =(C4/C5)-1 -> 0.012242627 | O4: =(D4/D5)-1 -> 0.0074626866 | P4: =(E4/E5)-1 -> 0.012765957 | Q4: =(F4/F5)-1 -> 0.020979021 | R4: =(G4/G5)-1 -> 0.0052631579 | S4: =(H4/H5)-1 -> 0.0068599248 | T4: =(I4/I5)-1 -> 0.046842105 | ... W4: =(L4/L5)-1 -> 0.0039447732
A5: 15/10/2025 | B5: 112.95 | C5: 1797 | D5: 402 | E5: 2350 | F5: 715 | G5: 1900 | H5: 903.8 | I5: 1900 | J5: 4540 | K5: 870 | L5: 5070 | M5: =(B5/B6)-1 -> -0.00044247788 | N5: =(C5/C6)-1 -> -0.012094557 | O5: =(D5/D6)-1 -> -0.016874541 | P5: =(E5/E6)-1 -> -0.012605042 | Q5: =(F5/F6)-1 -> -0.020547945 | R5: =(G5/G6)-1 -> -0.073170732 | S5: =(H5/H6)-1 -> -0.016539717 | T5: =(I5/I6)-1 -> 0 | ... W5: =(L5/L6)-1 -> 0
A6: 14/10/2025 | B6: 113 | C6: 1819 | D6: 408.9 | E6: 2380 | F6: 730 | G6: 2050 | H6: 919 | I6: 1900 | J6: 4550 | K6: 875 | L6: 5070 | M6: =(B6/B7)-1 -> -0.013100437 | N6: =(C6/C7)-1 -> -0.028830753 | O6: =(D6/D7)-1 -> 0.0045448962 | P6: =(E6/E7)-1 -> -0.018556701 | Q6: =(F6/F7)-1 -> -0.013246823 | R6: =(G6/G7)-1 -> 0.081794195 | S6: =(H6/H7)-1 -> -0.012995382 | T6: =(I6/I7)-1 -> -0.025641026 | ... W6: =(L6/L7)-1 -> -0.015533981
A7: 13/10/2025 | B7: 114.5 | C7: 1873 | D7: 407.05 | E7: 2425 | F7: 739.8 | G7: 1895 | H7: 931.1 | I7: 1950 | J7: 4600 | K7: 899.9 | L7: 5150 | M7: =(B7/B8)-1 -> 0 | N7: =(C7/C8)-1 -> 0.040555556 | O7: =(D7/D8)-1 -> -0.019156627 | P7: =(E7/E8)-1 -> 0 | Q7: =(F7/F8)-1 -> 0.013424658 | R7: =(G7/G8)-1 -> 0 | S7: =(H7/H8)-1 -> -0.004171123 | T7: =(I7/I8)-1 -> 0.0051546392 | ... W7: =(L7/L8)-1 -> 0.0098039216
A8: 10/10/2025 | B8: 114.5 | C8: 1800 | D8: 415 | E8: 2425 | F8: 730 | G8: 1895 | H8: 935 | I8: 1940 | J8: 4600 | K8: 883.2 | L8: 5100 | M8: =(B8/B9)-1 -> -0.01250539 | N8: =(C8/C9)-1 -> 0 | O8: =(D8/D9)-1 -> 0.0026576468 | P8: =(E8/E9)-1 -> 0.014644351 | Q8: =(F8/F9)-1 -> 0 | R8: =(G8/G9)-1 -> 0.014997322 | S8: =(H8/H9)-1 -> 0.014099783 | T8: =(I8/I9)-1 -> -0.0046177527 | ... W8: =(L8/L9)-1 -> 0.02
A9: 09/10/2025 | B9: 115.95 | C9: 1800 | D9: 413.9 | E9: 2390 | F9: 730 | G9: 1867 | H9: 922 | I9: 1949 | J9: 4600 | K9: 900 | L9: 5000 | M9: =(B9/B10)-1 -> -0.00043103448 | N9: =(C9/C10)-1 -> -0.04204364 | O9: =(D9/D10)-1 -> 0.021470879 | P9: =(E9/E10)-1 -> -0.0041666667 | Q9: =(F9/F10)-1 -> -0.021447721 | R9: =(G9/G10)-1 -> 0 | S9: =(H9/H10)-1 -> -0.014430786 | T9: =(I9/I10)-1 -> 0.0036045314 | ... W9: =(L9/L10)-1 -> -0.019607843
A10: 08/10/2025 | B10: 116 | C10: 1879 | D10: 405.2 | E10: 2400 | F10: 746 | G10: 1867 | H10: 935.5 | I10: 1942 | J10: 4750 | K10: 910 | L10: 5100 | M10: =(B10/B11)-1 -> -0.0089705254 | N10: =(C10/C11)-1 -> 0.026775956 | O10: =(D10/D11)-1 -> -0.011707317 | P10: =(E10/E11)-1 -> -0.0045624222 | Q10: =(F10/F11)-1 -> -0.0066577896 | R10: =(G10/G11)-1 -> 0.0091891892 | S10: =(H10/H11)-1 -> -0.015263158 | T10: =(I10/I11)-1 -> -0.0041025641 | ... W10: =(L10/L11)-1 -> 0
A11: 07/10/2025 | B11: 117.05 | C11: 1830 | D11: 410 | E11: 2411 | F11: 751 | G11: 1850 | H11: 950 | I11: 1950 | J11: 4700 | K11: 921 | L11: 5100 | M11: =(B11/B12)-1 -> -0.0021312873 | N11: =(C11/C12)-1 -> -0.031746032 | O11: =(D11/D12)-1 -> 0 | P11: =(E11/E12)-1 -> 0.012174643 | Q11: =(F11/F12)-1 -> -0.0066137566 | R11: =(G11/G12)-1 -> 0 | S11: =(H11/H12)-1 -> 0 | T11: =(I11/I12)-1 -> -0.025 | ... W11: =(L11/L12)-1 -> 0.040179482
A12: 06/10/2025 | B12: 117.3 | C12: 1890 | D12: 410 | E12: 2382 | F12: 756 | G12: 1850 | H12: 950 | I12: 2000 | J12: 4700 | K12: 935 | L12: 4903 | M12: =(B12/B13)-1 -> 0.0077319588 | N12: =(C12/C13)-1 -> 0.021621622 | O12: =(D12/D13)-1 -> 0 | P12: =(E12/E13)-1 -> -0.0075 | Q12: =(F12/F13)-1 -> 0.021621622 | R12: =(G12/G13)-1 -> 0 | S12: =(H12/H13)-1 -> 0.014957265 | T12: =(I12/I13)-1 -> 0.01010101 | ... W12: =(L12/L13)-1 -> 0.0006122449
A13: 03/10/2025 | B13: 116.4 | C13: 1850 | D13: 410 | E13: 2400 | F13: 740 | G13: 1850 | H13: 936 | I13: 1980 | J13: 4599 | K13: 915.1 | L13: 4900 | M13: =(B13/B14)-1 -> 0.020157756 | N13: =(C13/C14)-1 -> 0.045788581 | O13: =(D13/D14)-1 -> 0.051282051 | P13: =(E13/E14)-1 -> 0.034482759 | Q13: =(F13/F14)-1 -> 0.020830459 | R13: =(G13/G14)-1 -> 0.014254386 | S13: =(H13/H14)-1 -> 0.02295082 | T13: =(I13/I14)-1 -> 0.00050530571 | ... W13: =(L13/L14)-1 -> -0.02970297
A14: 02/10/2025 | B14: 114.1 | C14: 1769 | D14: 390 | E14: 2320 | F14: 724.9 | G14: 1824 | H14: 915 | I14: 1979 | J14: 4600 | K14: 890 | L14: 5050 | M14: =(B14/B15)-1 -> 0.0052863436 | N14: =(C14/C15)-1 -> -0.017222222 | O14: =(D14/D15)-1 -> 0.012987013 | P14: =(E14/E15)-1 -> 0 | Q14: =(F14/F15)-1 -> -0.00013793103 | R14: =(G14/G15)-1 -> 0 | S14: =(H14/H15)-1 -> 0.0054945055 | T14: =(I14/I15)-1 -> 0.041578947 | ... W14: =(L14/L15)-1 -> 0.030612245
... A179: 30/01/2025 | B179: 106.3 | C179: 950 | D179: 280 | E179: 1150 | F179: 636 | G179: 1810 | H179: 609 | I179: 1920 | J179: 4300 | K179: 547.4 | L179: 6910 | M179: =(B179/B180)-1 -> 0.095763323 | N179: =(C179/C180)-1 -> 0.014848841 | O179: =(D179/D180)-1 -> 0.02189781 | P179: =(E179/E180)-1 -> 0.026785714 | Q179: =(F179/F180)-1 -> 0.0096840768 | R179: =(G179/G180)-1 -> 0.0055555556 | S179: =(H179/H180)-1 -> 0.004784689 | T179: =(I179/I180)-1 -> 0.0099947396 | ... W179: =(L179/L180)-1 -> 0.025222552
A180: 29/01/2025 | B180: 97.01 | C180: 936,1 | D180: 274 | E180: 1120 | F180: 629.9 | G180: 1800 | H180: 606.1 | I180: 1901 | J180: 4325 | K180: 543 | L180: 6740 | M180: =(B180/B181)-1 -> 0.041997852 | N180: =(C180/C181)-1 -> 0 | O180: =(D180/D181)-1 -> -0.010830325 | P180: =(E180/E181)-1 -> 0.018181818 | Q180: =(F180/F181)-1 -> 0.020742181 | R180: =(G180/G181)-1 -> 0 | S180: =(H180/H181)-1 -> 0.0068106312 | T180: =(I180/I181)-1 -> 0.0010531859 | ... W180: =(L180/L181)-1 -> 0.021212121
A181: 28/01/2025 | B181: 93.1 | C181: 936,1 | D181: 277 | E181: 1100 | F181: 617.1 | G181: 1800 | H181: 602 | I181: 1899 | J181: 4295 | K181: 530 | L181: 6600 | M181: =(B181/B182)-1 -> 0.012066529 | N181: =(C181/C182)-1 -> 0 | O181: =(D181/D182)-1 -> -0.010714286 | P181: =(E181/E182)-1 -> -0.0045248869 | Q181: =(F181/F182)-1 -> 0.0035778175 | R181: =(G181/G182)-1 -> -0.029126214 | S181: =(H181/H182)-1 -> 0.0050083472 | T181: =(I181/I182)-1 -> -0.0073183481 | ... W181: =(L181/L182)-1 -> 0.0015174507
A182: 27/01/2025 | B182: 91.99 | C182: 936,1 | D182: 280 | E182: 1105 | F182: 614.9 | G182: 1854 | H182: 599 | I182: 1913 | J182: 4295 | K182: 530 | L182: 6590 | M182: =(B182/B183)-1 -> -0.00010869565 | N182: =(C182/C183)-1 -> -0.0094179894 | O182: =(D182/D183)-1 -> 0.010830325 | P182: =(E182/E183)-1 -> 0.0045454545 | Q182: =(F182/F183)-1 -> -0.00016260163 | R182: =(G182/G183)-1 -> 0 | S182: =(H182/H183)-1 -> -0.0082781457 | T182: =(I182/I183)-1 -> 0.0094986807 | ... W182: =(L182/L183)-1 -> -0.013473054
A183: 24/01/2025 | B183: 92 | C183: 945 | D183: 277 | E183: 1100 | F183: 615 | G183: 1854 | H183: 604 | I183: 1895 | J183: 4295 | K183: 530 | L183: 6680 | M183: =(B183/B184)-1 -> 0.01210121 | N183: =(C183/C184)-1 -> 0.0031847134 | O183: =(D183/D184)-1 -> 0.014652015 | P183: =(E183/E184)-1 -> 0 | Q183: =(F183/F184)-1 -> 0.0039177277 | R183: =(G183/G184)-1 -> 0 | S183: =(H183/H184)-1 -> -0.0014878492 | T183: =(I183/I184)-1 -> -0.013020833 | ... W183: =(L183/L184)-1 -> 0.0060240964
A184: 23/01/2025 | B184: 90.9 | C184: 942 | D184: 273 | E184: 1100 | F184: 612.6 | G184: 1854 | H184: 604.9 | I184: 1920 | J184: 4295 | K184: 516 | L184: 6640 | M184: =(B184/B185)-1 -> 0.019058296 | N184: =(C184/C185)-1 -> -0.0010604454 | O184: =(D184/D185)-1 -> 0.06640625 | P184: =(E184/E185)-1 -> 0.044634378 | Q184: =(F184/F185)-1 -> -0.00065252855 | R184: =(G184/G185)-1 -> 0 | S184: =(H184/H185)-1 -> 0.013232831 | T184: =(I184/I185)-1 -> 0.010526316 | ... W184: =(L184/L185)-1 -> -0.0015037594
A185: 22/01/2025 | B185: 89.2 | C185: 943 | D185: 256 | E185: 1053 | F185: 613 | G185: 1854 | H185: 597 | I185: 1900 | J185: 4369 | K185: 514.1 | L185: 6650 | M185: =(B185/B186)-1 -> -0.0033519553 | N185: =(C185/C186)-1 -> 0.010718114 | O185: =(D185/D186)-1 -> 0.024 | P185: =(E185/E186)-1 -> -0.01588785 | Q185: =(F185/F186)-1 -> -0.0013033561 | R185: =(G185/G186)-1 -> 0 | S185: =(H185/H186)-1 -> 0 | T185: =(I185/I186)-1 -> -0.0026246719 | ... W185: =(L185/L186)-1 -> -0.0015015015
A186: 21/01/2025 | B186: 89.5 | C186: 933 | D186: 250 | E186: 1070 | F186: 613.8 | G186: 1854 | H186: 597 | I186: 1905 | J186: 4373 | K186: 520 | L186: 6660 | M186: =(B186/B187)-1 -> -0.016483516 | N186: =(C186/C187)-1 -> 0.0010729614 | O186: =(D186/D187)-1 -> -0.025151102 | P186: =(E186/E187)-1 -> -0.027272727 | Q186: =(F186/F187)-1 -> -0.013341906 | R186: =(G186/G187)-1 -> 0 | S186: =(H186/H187)-1 -> -0.011589404 | T186: =(I186/I187)-1 -> -0.0052219321 | ... W186: =(L186/L187)-1 -> -0.0074515648
A187: 20/01/2025 | B187: 91 | C187: 932 | D187: 256.45 | E187: 1100 | F187: 622.1 | G187: 1854 | H187: 604 | I187: 1915 | J187: 4360 | K187: 530.5 | L187: 6710 | M187: =(B187/B188)-1 -> -0.01610985 | N187: =(C187/C188)-1 -> -0.011664899 | O187: =(D187/D188)-1 -> 0.038259109 | P187: =(E187/E188)-1 -> 0.026119403 | Q187: =(F187/F188)-1 -> 0.0017713366 | R187: =(G187/G188)-1 -> 0 | S187: =(H187/H188)-1 -> -0.0016528926 | T187: =(I187/I188)-1 -> 0 | ... W187: =(L187/L188)-1 -> 0.0014925373
A188: 17/01/2025 | B188: 92.49 | C188: 943 | D188: 247 | E188: 1072 | F188: 621 | G188: 1854 | H188: 605 | I188: 1915 | J188: 4299 | K188: 535 | L188: 6700 | M188: =(B188/B189)-1 -> -0.0014035845 | N188: =(C188/C189)-1 -> 0.00053050398 | O188: =(D188/D189)-1 -> 0.046610169 | P188: =(E188/E189)-1 -> -0.015610652 | Q188: =(F188/F189)-1 -> -0.005922843 | R188: =(G188/G189)-1 -> -0.019047619 | S188: =(H188/H189)-1 -> 0 | T188: =(I188/I189)-1 -> -0.0067427386 | ... W188: =(L188/L189)-1 -> -0.0074074074
A189: 16/01/2025 | B189: 92.62 | C189: 942.5 | D189: 236 | E189: 1089 | F189: 624.7 | G189: 1890 | H189: 605 | I189: 1928 | J189: 4295 | K189: 540 | L189: 6750 | M189: =(B189/B190)-1 -> 0.0067391304 | N189: =(C189/C190)-1 -> 0 | O189: =(D189/D190)-1 -> 0.012006861 | P189: =(E189/E190)-1 -> -0.044736842 | Q189: =(F189/F190)-1 -> -0.0044621514 | R189: =(G189/G190)-1 -> 0 | S189: =(H189/H190)-1 -> -0.016260163 | T189: =(I189/I190)-1 -> -0.0010362694 | ... W189: =(L189/L190)-1 -> -0.0058910162
A190: 15/01/2025 | B190: 92 | C190: 942.5 | D190: 233.2 | E190: 1140 | F190: 627.5 | G190: 1890 | H190: 615 | I190: 1930 | J190: 4299 | K190: 540 | L190: 6790 | M190: =(B190/B191)-1 -> 0.029658646 | N190: =(C190/C191)-1 -> 0.018918919 | O190: =(D190/D191)-1 -> -0.0076595745 | P190: =(E190/E191)-1 -> -0.0043668122 | Q190: =(F190/F191)-1 -> 0.012096774 | R190: =(G190/G191)-1 -> 0 | S190: =(H190/H191)-1 -> 0.019562334 | T190: =(I190/I191)-1 -> -0.020304569 | ... W190: =(L190/L191)-1 -> 0.0016226582
A191: 13/01/2025 | B191: 89.35 | C191: 925 | D191: 235 | E191: 1145 | F191: 620 | G191: 1890 | H191: 603.2 | I191: 1970 | J191: 4235 | K191: 530 | L191: 6779 | M191: =(B191/B192)-1 -> -0.0022333892 | N191: =(C191/C192)-1 -> -0.015957447 | O191: =(D191/D192)-1 -> -0.0084388186 | P191: =(E191/E192)-1 -> 0.013274336 | Q191: =(F191/F192)-1 -> 0 | R191: =(G191/G192)-1 -> 0 | S191: =(H191/H192)-1 -> -0.011147541 | T191: =(I191/I192)-1 -> 0.017561983 | ... W191: =(L191/L192)-1 -> -0.0026482272
A192: 10/01/2025 | B192: 89.55 | C192: 940 | D192: 237 | E192: 1130 | F192: 620 | G192: 1890 | H192: 610 | I192: 1936 | J192: 4249 | K192: 530 | L192: 6797 | M192: =(B192/B193)-1 -> 0.026949541 | N192: =(C192/C193)-1 -> -0.0021231423 | O192: =(D192/D193)-1 -> -0.0050377834 | P192: =(E192/E193)-1 -> 0.0017730496 | Q192: =(F192/F193)-1 -> -0.0028948215 | R192: =(G192/G193)-1 -> 0.013948498 | S192: =(H192/H193)-1 -> 0.0016420361 | T192: =(I192/I193)-1 -> -0.0020618557 | ... W192: =(L192/L193)-1 -> 0.020264185
A193: 09/01/2025 | B193: 87.2 | C193: 942 | D193: 238.2 | E193: 1128 | F193: 621.8 | G193: 1864 | H193: 609 | I193: 1940 | J193: 4299 | K193: 535 | L193: 6662 | M193: =(B193/B194)-1 -> 0.0022988506 | N193: =(C193/C194)-1 -> 0.010729614 | O193: =(D193/D194)-1 -> 0.013617021 | P193: =(E193/E194)-1 -> -0.056066946 | Q193: =(F193/F194)-1 -> 0.01237382 | R193: =(G193/G194)-1 -> 0.018579235 | S193: =(H193/H194)-1 -> -0.0018029831 | T193: =(I193/I194)-1 -> -0.0051282051 | ... W193: =(L193/L194)-1 -> 0.0409375
A194: 08/01/2025 | B194: 87 | C194: 932 | D194: 235 | E194: 1195 | F194: 614.2 | G194: 1830 | H194: 610.1 | I194: 1950 | J194: 4080 | K194: 531.2 | L194: 6400 | M194: =(B194/B195)-1 -> -0.010238908 | N194: =(C194/C195)-1 -> 0 | O194: =(D194/D195)-1 -> 0.043980453 | P194: =(E194/E195)-1 -> 0.012711864 | Q194: =(F194/F195)-1 -> 0.013364131 | R194: =(G194/G195)-1 -> 0.013850416 | S194: =(H194/H195)-1 -> 0.016663889 | T194: =(I194/I195)-1 -> 0.0093167702 | ... W194: =(L194/L195)-1 -> -0.0046656299
... A692: 03/01/2023 | B692: 101.4 | C692: 1300 | D692: 118.95 | E692: 519.5 | F692: 384 | G692: 950 | H692: 207 | I692: 1252 | J692: 4500 | K692: 121 | L692: 6500 | M692: =(B692/B693)-1 -> 0.04 | N692: =(C692/C693)-1 -> -0.015151515 | O692: =(D692/D693)-1 -> 0.043421053 | P692: =(E692/E693)-1 -> 0.028712871 | Q692: =(F692/F693)-1 -> -0.0025974026 | R692: =(G692/G693)-1 -> 0 | S692: =(H692/H693)-1 -> -0.037209302 | T692: =(I692/I693)-1 -> -0.021875 | ... W692: =(L692/L693)-1 -> 0.031746032
A693: 02/01/2023 | B693: 97.5 | C693: 1320 | D693: 114 | E693: 505 | F693: 385 | G693: 950 | H693: 215 | I693: 1280 | J693: 4650 | K693: 123.95 | L693: 6300 | M693: -
L694: Rendement Moyen | M694: =AVERAGE(M3:M692) -> 0.00037524955 | N694: =AVERAGE(N3:N692) -> 0.00062822796 | O694: =AVERAGE(O3:O692) -> 0.0021214683 | P694: =AVERAGE(P3:P692) -> 0.0025114593 | Q694: =AVERAGE(Q3:Q692) -> 0.00098563204 | R694: =AVERAGE(R3:R692) -> 0.0014134294 | S694: =AVERAGE(S3:S692) -> 0.002230273 | T694: =AVERAGE(T3:T692) -> 0.00076560201 | ... W694: =AVERAGE(W3:W692) -> -0.00017179514
L695: Risque | M695: =_xlfn.STDEV.S(M3:M692) -> 0.016079668 | N695: =_xlfn.STDEV.S(N3:N692) -> 0.022511193 | O695: =_xlfn.STDEV.S(O3:O692) -> 0.02150755 | P695: =_xlfn.STDEV.S(P3:P692) -> 0.022104798 | Q695: =_xlfn.STDEV.S(Q3:Q692) -> 0.011167903 | R695: =_xlfn.STDEV.S(R3:R692) -> 0.025140799 | S695: =_xlfn.STDEV.S(S3:S692) -> 0.015646625 | T695: =_xlfn.STDEV.S(T3:T692) -> 0.018874635 | ... W695: =_xlfn.STDEV.S(W3:W692) -> 0.016329342
L696: Variance | M696: =_xlfn.VAR.S(M3:M692) -> 0.00025855573 | N696: =_xlfn.VAR.S(N3:N692) -> 0.0005067538 | O696: =_xlfn.VAR.S(O3:O692) -> 0.00046257472 | P696: =_xlfn.VAR.S(P3:P692) -> 0.0004886221 | Q696: =_xlfn.VAR.S(Q3:Q692) -> 0.00012472206 | R696: =_xlfn.VAR.S(R3:R692) -> 0.00063205976 | S696: =_xlfn.VAR.S(S3:S692) -> 0.00024481686 | T696: =_xlfn.VAR.S(T3:T692) -> 0.00035625183 | ... W696: =_xlfn.VAR.S(W3:W692) -> 0.00026664742

Sheet Beta
A1: Les rendements | L1: Rendement Masi20
A2: IAM | B2: Sothema | C2: RISMA | D2: Sonasid | E2: ATTIJARIWAFA BANK | F2: Sanlam | G2: Marsa maroc | H2: Ciments du Maroc | I2: Label vie | J2: Tgcc | K2: HPS
A3: 0.0052173913 | B3: -0.059373282 | C3: 0.037037037 | D3: 0.014705882 | E3: -0.002739726 | F3: 0.061780105 | G3: 0.010989011 | H3: -0.034690799 | I3: -0.012631579 | J3: 0 | K3: 0.0023575639 | L3: 0.00066958158
A4: 0.018149624 | B4: 0.012242627 | C4: 0.0074626866 | D4: =_xlfn.VAR.S([1]Feuil2!A3:A692) -> #REF! | E4: 0.020979021 | F4: 0.0052631579 | G4: 0.0068599248 | H4: 0.046842105 | I4: 0.046255507 | J4: 0.034482759 | K4: 0.0039447732 | L4: 0.016865255
A5: -0.00044247788 | B5: -0.012094557 | C5: -0.016874541 | D5: -0.012605042 | E5: -0.020547945 | F5: -0.073170732 | G5: -0.016539717 | H5: 0 | I5: -0.0021978022 | J5: -0.0057142857 | K5: 0 | L5: -0.0043521883
A6: -0.013100437 | B6: -0.028830753 | C6: 0.0045448962 | D6: -0.018556701 | E6: -0.013246823 | F6: 0.081794195 | G6: -0.012995382 | H6: -0.025641026 | I6: -0.010869565 | J6: -0.027669741 | K6: -0.015533981 | L6: -0.024133369
A7: 0 | B7: 0.040555556 | C7: -0.019156627 | D7: 0 | E7: 0.013424658 | F7: 0 | G7: -0.004171123 | H7: 0.0051546392 | I7: 0 | J7: 0.018908514 | K7: 0.0098039216 | L7: 0.0063445778
A8: -0.01250539 | B8: 0 | C8: 0.0026576468 | D8: 0.014644351 | E8: 0 | F8: 0.014997322 | G8: 0.014099783 | H8: -0.0046177527 | I8: 0 | J8: -0.018666667 | K8: 0.02 | L8: -0.0024505897
A9: -0.00043103448 | B9: -0.04204364 | C9: 0.021470879 | D9: -0.0041666667 | E9: -0.021447721 | F9: 0 | G9: -0.014430786 | H9: 0.0036045314 | I9: -0.031578947 | J9: -0.010989011 | K9: -0.019607843 | L9: -0.016466685 | P9: COV(I;M) | Q9: VAR(M) | R9: BETA | S9: Poids dans PF | T9: BETA Pondere par le poids
A10: -0.0089705254 | B10: 0.026775956 | C10: -0.011707317 | D10: -0.0045624222 | E10: -0.0066577896 | F10: 0.0091891892 | G10: -0.015263158 | H10: -0.0041025641 | I10: 0.010638298 | J10: -0.01194354 | K10: 0 | L10: -0.0070113765 | O10: IAM | P10: =_xlfn.COVARIANCE.P(A3:A692,$L$3:$L$692) -> 8.6378848e-05 | Q10: =_xlfn.VAR.S([1]Feuil2!$L$3:$L$692) -> #DIV/0! | R10: =P10/Q10 -> #DIV/0! | S10: 0.065513667 | T10: =R10*S10 -> #DIV/0!
A11: -0.0021312873 | B11: -0.031746032 | C11: 0 | D11: 0.012174643 | E11: -0.0066137566 | F11: 0 | G11: 0 | H11: -0.025 | I11: 0 | J11: -0.014973262 | K11: 0.040179482 | L11: -0.0069433709 | O11: Sothema | P11: =_xlfn.COVARIANCE.P(B3:B692,$L$3:$L$692) -> 4.2683841e-05 | Q11: =_xlfn.VAR.S([1]Feuil2!$L$3:$L$692) -> #DIV/0! | R11: =P11/Q11 -> #DIV/0! | S11: 0.10278822 | T11: =R11*S11 -> #DIV/0!
A12: 0.0077319588 | B12: 0.021621622 | C12: 0 | D12: -0.0075 | E12: 0.021621622 | F12: 0 | G12: 0.014957265 | H12: 0.01010101 | I12: 0.021961296 | J12: 0.021746257 | K12: 0.0006122449 | L12: 0.014115419 | O12: RISMA | P12: =_xlfn.COVARIANCE.P(C3:C692,$L$3:$L$692) -> 3.6730223e-05 | Q12: =_xlfn.VAR.S([1]Feuil2!$L$3:$L$692) -> #DIV/0! | R12: =P12/Q12 -> #DIV/0! | S12: 0.10282435 | T12: =R12*S12 -> #DIV/0!
A13: 0.020157756 | B13: 0.045788581 | C13: 0.051282051 | D13: 0.034482759 | E13: 0.020830459 | F13: 0.014254386 | G13: 0.02295082 | H13: 0.00050530571 | I13: -0.0002173913 | J13: 0.028202247 | K13: -0.02970297 | L13: 0.020225243 | O13: Sonasid | P13: =_xlfn.COVARIANCE.P(D3:D692,$L$3:$L$692) -> #REF! | Q13: =_xlfn.VAR.S([1]Feuil2!$L$3:$L$692) -> #DIV/0! | R13: =P13/Q13 -> #REF! | S13: 0.099732545 | T13: =R13*S13 -> #REF!
A14: 0.0052863436 | B14: -0.017222222 | C14: 0.012987013 | D14: 0 | E14: -0.00013793103 | F14: 0 | G14: 0.0054945055 | H14: 0.041578947 | I14: 0.0067848545 | J14: 0.011363636 | K14: 0.030612245 | L14: 0.0064521322 | O14: ATTIJARIWAFA BANK | P14: =_xlfn.COVARIANCE.P([1]Feuil2!E3:E692,[1]Feuil2!$L$3:$L$692) -> #DIV/0! | Q14: =_xlfn.VAR.S([1]Feuil2!$L$3:$L$692) -> #DIV/0! | R14: =P14/Q14 -> #DIV/0! | S14: 0.19858 | T14: =R14*S14 -> #DIV/0!
A15: -0.032395567 | B15: -0.044585987 | C15: -0.060861081 | D15: -0.0085470085 | E15: -0.026845638 | F15: -0.064615385 | G15: -0.042105263 | H15: -0.073170732 | I15: -0.018052869 | J15: -0.032967033 | K15: -0.02 | L15: -0.036915505 | O15: Sanlam | P15: =_xlfn.COVARIANCE.P([1]Feuil2!F3:F692,[1]Feuil2!$L$3:$L$692) -> #DIV/0! | Q15: =_xlfn.VAR.S([1]Feuil2!$L$3:$L$692) -> #DIV/0! | R15: =P15/Q15 -> #DIV/0! | S15: 0.09912141 | T15: =R15*S15 -> #DIV/0!
A16: 0.0068669528 | B16: -0.0063291139 | C16: 0.024875 | D16: 0.017391304 | E16: -0.0079893475 | F16: -0.025 | G16: -0.0052356021 | H16: 0.035353535 | I16: -0.024528302 | J16: 0.028248588 | K16: 0 | L16: 0.0039493139 | O16: Marsa maroc | P16: =_xlfn.COVARIANCE.P([1]Feuil2!G3:G692,[1]Feuil2!$L$3:$L$692) -> #DIV/0! | Q16: =_xlfn.VAR.S([1]Feuil2!$L$3:$L$692) -> #DIV/0! | R16: =P16/Q16 -> #DIV/0! | S16: 0.099023066 | T16: =R16*S16 -> #DIV/0!
A17: -0.016877637 | B17: -0.0021052632 | C17: 0.025641026 | D17: -0.043659044 | E17: -0.01482356 | F17: -0.0099009901 | G17: -0.0052083333 | H17: -0.033674963 | I17: -0.026530612 | J17: -0.029605263 | K17: -0.029126214 | L17: -0.021163148 | O17: Ciments du Maroc | P17: =_xlfn.COVARIANCE.P([1]Feuil2!H3:H692,[1]Feuil2!$L$3:$L$692) -> #DIV/0! | Q17: =_xlfn.VAR.S([1]Feuil2!$L$3:$L$692) -> #DIV/0! | R17: =P17/Q17 -> #DIV/0! | S17: 0.098417449 | T17: =R17*S17 -> #DIV/0!
A18: -0.0046199076 | B18: 0.0052910053 | C18: -0.060693642 | D18: -0.018367347 | E18: -0.0035294118 | F18: -0.038095238 | G18: -0.0010405827 | H18: -0.00048780488 | I18: 0.020833333 | J18: -0.010845987 | K18: -0.028301887 | L18: -0.0042538129 | O18: Label vie | P18: =_xlfn.COVARIANCE.P([1]Feuil2!I3:I692,[1]Feuil2!$L$3:$L$692) -> #DIV/0! | Q18: =_xlfn.VAR.S([1]Feuil2!$L$3:$L$692) -> #DIV/0! | R18: =P18/Q18 -> #DIV/0! | S18: 0.033001333 | T18: =R18*S18 -> #DIV/0!
A19: -0.016115702 | B19: -0.010471204 | C19: -0.029906542 | D19: -0.027777778 | E19: -0.0066225166 | F19: 0 | G19: -0.011621927 | H19: 0.0019550342 | I19: 0.0043942247 | J19: -0.025369979 | K19: 0.041871437 | L19: -0.010643287 | O19: Tgcc | P19: =_xlfn.COVARIANCE.P([1]Feuil2!J3:J692,[1]Feuil2!$L$3:$L$692) -> #DIV/0! | Q19: =_xlfn.VAR.S([1]Feuil2!$L$3:$L$692) -> #DIV/0! | R19: =P19/Q19 -> #DIV/0! | S19: 0.098097832 | T19: =R19*S19 -> #DIV/0!
A20: -0.0098199673 | B20: -0.0026109661 | C20: -0.0045354111 | D20: -0.0082644628 | E20: -0.0064507805 | F20: 0 | G20: -0.016885743 | H20: 0.049230769 | I20: -0.014435966 | J20: -0.024742268 | K20: -0.099964614 | L20: -0.0086541978 | O20: HPS | P20: =_xlfn.COVARIANCE.P([1]Feuil2!K3:K692,[1]Feuil2!$L$3:$L$692) -> #DIV/0! | Q20: =_xlfn.VAR.S([1]Feuil2!$L$3:$L$692) -> #DIV/0! | R20: =P20/Q20 -> #DIV/0! | S20: 0 | T20: =R20*S20 -> #DIV/0!
A21: -0.013720743 | B21: 0 | C21: 0.0022144522 | D21: -0.011284047 | E21: -0.015746032 | F21: -0.0094339623 | G21: -0.001010101 | H21: -0.057059961 | I21: -0.020206102 | J21: 0.0072689512 | K21: -0.020450607 | L21: -0.010082724 | O21: BETA MOYEN DU PORTEFEUILLE | S21: =SUM(T10:T20) -> #DIV/0!
A22: 0.0073170732 | B22: 0 | C22: -0.011520737 | D22: -0.011538462 | E22: 0.012210797 | F22: 0.00047192072 | G22: -0.0070210632 | H22: -0.038139535 | I22: 0.01 | J22: -0.0072164948 | K22: 0.021238938 | L22: 0.0014134536
A23: 0.0049019608 | B23: -0.0067427386 | C23: 0.023584906 | D23: -0.013282732 | E23: 0.0012870013 | F23: 0 | G23: 0.0020100503 | H23: 0.091924835 | I23: 0.022110972 | J23: -0.010204082 | K23: 0.0089285714 | L23: 0.0071923744
A24: 0.019150708 | B24: -0.0010362694 | C24: -0.0023529412 | D24: 0.033333333 | E24: 0.0023219814 | F24: 0.028640777 | G24: 0.025667457 | H24: 0.025520833 | I24: 0.015677966 | J24: 0.020833333 | K24: -0.012519838 | L24: 0.012344132
A25: 0.00083333333 | B25: -0.009748589 | C25: 0.024096386 | D25: 0.0111023 | E25: 0.0041450777 | F25: -0.019047619 | G25: -0.0020574015 | H25: -0.025380711 | I25: -0.016461763 | J25: 0.0052356021 | K25: -0.0050877193 | L25: -0.0040812761 | R25: 0.859211
A26: -0.00083263947 | B26: 0.02687039 | C26: -0.023529412 | D26: -0.0015835313 | E26: 0.002727627 | F26: 0 | G26: -0.0019507187 | H26: 0.01025641 | I26: 0.016737288 | J26: -0.016477858 | K26: 0.017857143 | L26: 0.0010307411
A27: -0.01879085 | B27: -0.00052659294 | C27: -0.0070093458 | D27: -0.010963195 | E27: -0.0027202073 | F27: -0.0094339623 | G27: -0.012671059 | H27: -0.015151515 | I27: -0.016666667 | J27: -0.028028028 | K27: -0.018404908 | L27: -0.011577361
A28: -0.0048780488 | B28: -0.00052631579 | C28: 0 | D28: -0.014660494 | E28: -0.0064350064 | F28: 0.0095238095 | G28: 0.0066326531 | H28: -0.01 | I28: -0.018404908 | J28: -0.010891089 | K28: 0.00087719298 | L28: -0.0026050487
A29: 0.0040816327 | B29: 0.008492569 | C29: 0 | D29: 0.016072129 | E29: 0.0027100271 | F29: 0.0096153846 | G29: -0.0050761421 | H29: -0.014778325 | I29: -0.0020408163 | J29: 0.002979146 | K29: 0.0052910053 | L29: 0.0009246303
A30: 0.0040983607 | B30: 0.0080256822 | C30: 0.021479714 | D30: 0.00039215686 | E30: 0.022295515 | F30: 0 | G30: 0.015463918 | H30: 0.041025641 | I30: 0.010309278 | J30: 0.016145308 | K30: 0.0017667845 | L30: 0.017473548
A31: -0.024 | B31: -0.016315789 | C31: -0.014117647 | D31: -0.019230769 | E31: -0.028205128 | F31: -0.004784689 | G31: -0.027081244 | H31: -0.034653465 | I31: -0.010204082 | J31: -0.02747792 | K31: -0.024137931 | L31: -0.027193742
A32: -0.011857708 | B32: -0.010416667 | C32: -0.0067772844 | D32: 0.008142691 | E32: 0 | F32: 0.029049729 | G32: -0.003996004 | H32: -0.021791768 | I32: 0.010517633 | J32: -0.015458937 | K32: 0.0086956522 | L32: -0.003144482
A33: 0 | B33: 0.016410799 | C33: 0.018809524 | D33: -0.015273005 | E33: 0.0025706941 | F33: 0.0059435364 | G33: 0.001 | H33: -0.0024154589 | I33: -0.010408163 | J33: -0.00096525097 | K33: -0.0084497327 | L33: -0.0033884127
A34: -0.0031520883 | B34: 0.004787234 | C34: 0.024265333 | D34: 0.00038197097 | E34: 0.0011581521 | F34: -0.033045977 | G34: 0 | H34: 0 | I34: 0 | J34: 0 | K34: -0.0087179487 | L34: 0.00032136599
A35: 0.026699029 | B35: 0 | C35: 0.030276382 | D35: 0.010810811 | E35: -0.0038456608 | F35: 0.018536585 | G35: 0.023541453 | H35: -0.013346044 | I35: -0.01010101 | J35: 0.00096618357 | K35: 0 | L35: 0.0012810394
A36: -0.0024213075 | B36: 0.016216216 | C36: -0.017283951 | D36: -0.0038461538 | E36: -0.0011523688 | F36: -0.0096618357 | G36: 0.0051440329 | H36: -0.00095238095 | I36: 0.0095859678 | J36: -0.014285714 | K36: 0 | L36: 0.0017211285
A37: 0.0012121212 | B37: 0.0059815117 | C37: 0 | D37: -0.018497546 | E37: 0 | F37: -0.010516252 | G37: -0.015696203 | H37: -0.0047393365 | I37: -0.0194 | J37: -0.015932521 | K37: -0.013490725 | L37: -0.0045887944
... A692: 0.04 | B692: -0.015151515 | C692: 0.043421053 | D692: 0.028712871 | E692: -0.0025974026 | F692: 0 | G692: -0.037209302 | H692: -0.021875 | I692: -0.032258065 | J692: -0.023799919 | K692: 0.031746032 | L692: -0.0075509132
A693: -
A694: 0.00037524955 | B694: 0.00062822796 | C694: 0.0021214683 | D694: 0.0025114593 | E694: 0.00098563204 | F694: 0.0014134294 | G694: 0.002230273 | H694: 0.00076560201 | I694: 0.00020024109 | J694: 0.0030485553 | K694: -0.00017179514 | L694: =AVERAGE(L3:L692) -> 0.00084328586
A695: 0.016079668 | B695: 0.022511193 | C695: 0.02150755 | D695: 0.022104798 | E695: 0.011167903 | F695: 0.025140799 | G695: 0.015646625 | H695: 0.018874635 | I695: 0.019390999 | J695: 0.018604562 | K695: 0.016329342
A696: 0.00025855573 | B696: 0.0005067538 | C696: 0.00046257472 | D696: 0.0004886221 | E696: 0.00012472206 | F696: 0.00063205976 | G696: 0.00024481686 | H696: 0.00035625183 | I696: 0.00037601085 | J696: 0.00034612972 | K696: 0.00026664742

Sheet Souscription
C1: Poids dans le PTF | D1: MT dans chaque actif | E1: CMP | F1: CMP avec la commission | G1: NB d'actions souscris | H1: NB d'actions souscris | I1: NB de titre danns le PF apres la souscription
C2: 0.065513667 | D2: 13037.22 | E2: 120.45 | F2: 120.97998 | G2: 107.76345 | H2: 108 | I2: 674
C3: 0.10435636 | D3: 20766.915 | E3: 1794.8772 | F3: 1802.7747 | G3: 11.519418 | H3: 12 | I3: 69
A4: Souscription | B4: 200000 | C4: 0.1058228 | D4: 21058.738 | E4: 412.78261 | F4: 414.59885 | G4: 50.793045 | H4: 51 | I4: 304
A5: droit d'entree | B5: 1000 | C5: 0.099784315 | D5: 19857.079 | E5: 2408.0488 | F5: 2418.6442 | G5: 8.2100041 | H5: 8 | I5: 49
A6: MT de la souscription | B6: 199000 | C6: 0.19728461 | D6: 39259.637 | E6: 761.44961 | F6: 764.79999 | G6: 51.333208 | H6: 51 | I6: 309
A7: Le reste (CASH) | B7: 1194.4992 | C7: 0.099826242 | D7: 19865.422 | E7: 1948.76 | F7: 1957.3345 | G7: 10.149222 | H7: 10 | I7: 60
C8: 0.098797932 | D8: 19660.789 | E8: 974.11782 | F8: 978.40394 | G8: 20.094756 | H8: 20 | I8: 121
C9: 0.097829718 | D9: 19468.114 | E9: 2002.2653 | F9: 2011.0753 | G9: 9.6804501 | H9: 10 | I9: 59
C10: 0.032465491 | D10: 6460.6326 | E10: 4698 | F10: 4718.6712 | G10: 1.3691636 | H10: 1 | I10: 8
C11: 0.098318866 | D11: 19565.454 | E11: 931 | F11: 935.0964 | G11: 20.923462 | H11: 21 | I11: 126

Sheet Attribution
A1: N° | E1: Poids dans le PTF | F1: Poids dans le MASI20 | G1: Performance du titres VENDREDI (w)/ (w-1) dans le PTF | H1: Contribution de la performance dans le PTF | I1: Contribution de la performance dans MASI20 | J1: ATTRIBUTION
A2: 1 | B2: IAM | C2: 674 | D2: 119.90684 | E2: 0.065116991 | F2: 0.092650024 | G2: -0.032999245 | H2: -0.0021488116 | I2: -0.0030573809 | J2: 0.00090856932
A3: 2 | B3: Sothema | C3: 69 | D3: 1801.6812 | E3: 0.10544163 | F3: 0 | G3: 0.017938158 | H3: 0.0018914285 | I3: 0 | J3: 0.0018914285
A4: 3 | B4: RISMA | C4: 304 | D4: 413.82566 | E4: 0.10613321 | F4: 0 | G4: 0.012503676 | H4: 0.0013270553 | I4: 0 | J4: 0.0013270553
A5: 4 | B5: Sonasid | C5: 49 | D5: 2412.9388 | E5: 0.099539042 | F5: 0.012437914 | G5: 0.010386183 | H5: 0.0010338307 | I5: 0.00012918245 | J5: 0.00090464828
A6: 5 | B6: ATTIJARIWAFA BANK | C6: 309 | D6: 762.20065 | E6: 0.19721999 | F6: 0.22738755 | G6: 0.0049847147 | H6: 0.00098308536 | I6: 0.0011334621 | J6: -0.00015037671
A7: 6 | B7: Sanlam | C7: 60 | D7: 1957.3 | E7: 0.099987318 | F7: 0 | G7: 0.021815767 | H7: 0.0021813 | I7: 0 | J7: 0.0021813
A8: 7 | B8: Marsa maroc | C8: 121 | D8: 975.07355 | E8: 0.098794053 | F8: 0.10329772 | G8: 0.0049498279 | H8: 0.00048901356 | I8: 0.00051130593 | J8: -2.2292375e-05
A9: 8 | B9: Ciments du Maroc | C9: 59 | D9: 2001.8814 | E9: 0.098320863 | F9: 0.059009379 | G9: -0.00093979392 | H9: -9.2401349e-05 | I9: -5.5456656e-05 | J9: -3.6944694e-05
A10: 9 | B10: Label vie | C10: 8 | D10: 4692.2222 | E10: 0.030969405 | F10: 0.024111792 | G10: -0.009850817 | H10: -0.00030507394 | I10: -0.00023752085 | J10: -6.7553095e-05
A11: 10 | B11: Tgcc | C11: 126 | D11: 932.16667 | E11: 0.09847751 | F11: 0.04019962 | G11: 0.0062578223 | H11: 0.00061625475 | I11: 0.00025156208 | J11: 0.00036469268
A12: 11 | B12: HPS | C12: 0 | D12: 0 | E12: 0 | F12: - | G12: - | H12: -
A13: 12
A14: 13
A15: 14
A16: 15
A17: TOTAL | E17: =SUM(E2:E12) -> 1 | G17: =AVERAGE(G2:G12) -> 0.0035046293 | H17: =AVERAGE(H2:H11) -> 0.00059756813 | I17: =AVERAGE(I2:I11) -> -0.00013248458 | J17: =AVERAGE(J2:J11) -> 0.00073005272

Sheet Solution SOLVEUR-REBALENCEMENT
B3: Poids 24/10/25 | C3: {=TRANSPOSE(B5:B15)} -> 0.068252741 | D3: 0.1 | E3: 0.1 | F3: 0.1 | G3: 0.2 | H3: 0.1 | I3: 0.1 | J3: 0.1 | K3: 0.031747259 | L3: 0.1 | M3: 0
C4: IAM | D4: Sothema | E4: RISMA | F4: Sonasid | G4: ATTIJARIWAFA BANK | H4: Sanlam | I4: Marsa maroc | J4: Ciments du Maroc | K4: Label vie | L4: Tgcc | M4: HPS
A5: IAM | B5: 0.068252741 | C5: 0.00025818101 | D5: 5.2395908e-05 | E5: 3.8325566e-05 | F5: 7.5496172e-05 | G5: 6.3581355e-05 | H5: 2.6730913e-05 | I5: 8.2262401e-05 | J5: 7.4573262e-05 | K5: 3.5410992e-05 | L5: 5.4761933e-05 | M5: 6.1546498e-05
A6: Sothema | B6: 0.1 | C6: 5.2395908e-05 | D6: 0.00050601937 | E6: 1.5890033e-05 | F6: 4.7021876e-05 | G6: 4.8928282e-05 | H6: 3.1576843e-05 | I6: 3.4025378e-05 | J6: 2.8947978e-05 | K6: 4.496443e-05 | L6: 4.8550988e-05 | M6: 4.1878286e-05
A7: RISMA | B7: 0.1 | C7: 3.8325566e-05 | D7: 1.5890033e-05 | E7: 0.00046190432 | F7: 6.7797943e-05 | G7: 3.6435111e-05 | H7: 2.2590282e-05 | I7: 3.051776e-05 | J7: 2.1329936e-05 | K7: -5.9453031e-06 | L7: 3.5570373e-05 | M7: 1.2919385e-05 | P7: Titre | Q7: Sens de l'operation | R7: Nombre de titre initial | S7: Poids initial | T7: Poids après solveur | U7: Nb de titre après | V7: Nb de titre échangé | W7: Prix initial | X7: Prix de Vente/Achat | Y7: ="+/- Value" -> +/- Value
A8: Sonasid | B8: 0.1 | C8: 7.5496172e-05 | D8: 4.7021876e-05 | E8: 6.7797943e-05 | F8: 0.00048791395 | G8: 6.7597524e-05 | H8: 4.1212494e-05 | I8: 9.601211e-05 | J8: 9.7283919e-05 | K8: 3.076744e-05 | L8: 0.00013067084 | M8: 3.0227588e-05 | P8: IAM | Q8: Vente | R8: 823 | S8: 0.097187221 | T8: 0.068252741 | U8: 566 | V8: 257 | W8: 120.45 | X8: 118 | Y8: =V8*X8-V8*W8 -> -629.65
A9: ATTIJARIWAFA BANK | B9: 0.2 | C9: 6.3581355e-05 | D9: 4.8928282e-05 | E9: 3.6435111e-05 | F9: 6.7597524e-05 | G9: 0.00012454131 | H9: 1.558514e-05 | I9: 6.9615653e-05 | J9: 5.043689e-05 | K9: 4.1678841e-05 | L9: 6.1119694e-05 | M9: 2.9845703e-05 | P9: Sothema | Q9: Achat | R9: 50 | S9: 0.090953631 | T9: 0.1 | U9: 57 | V9: 7 | W9: 1795 | X9: 1794
A10: Sanlam | B10: 0.1 | C10: 2.6730913e-05 | D10: 3.1576843e-05 | E10: 2.2590282e-05 | F10: 4.1212494e-05 | G10: 1.558514e-05 | H10: 0.00063114373 | I10: 2.2010182e-05 | J10: 1.985823e-05 | K10: 7.9440264e-06 | L10: -3.5297333e-06 | M10: 1.2261681e-05 | P10: RISMA | Q10: Achat | R10: 216 | S10: 0.085530584 | T10: 0.1 | U10: 253 | V10: 37 | W10: 416 | X10: 394
A11: Marsa maroc | B11: 0.1 | C11: 8.2262401e-05 | D11: 3.4025378e-05 | E11: 3.051776e-05 | F11: 9.601211e-05 | G11: 6.9615653e-05 | H11: 2.2010182e-05 | I11: 0.00024446206 | J11: 7.1711476e-05 | K11: 5.0915e-05 | L11: 0.00012996106 | M11: 4.0331677e-05 | P11: Sonasid | Q11: Achat | R11: 33 | S11: 0.081255261 | T11: 0.1 | U11: 41 | V11: 8 | W11: 2410 | X11: 2400
A12: Ciments du Maroc | B12: 0.1 | C12: 7.4573262e-05 | D12: 2.8947978e-05 | E12: 2.1329936e-05 | F12: 9.7283919e-05 | G12: 5.043689e-05 | H12: 1.985823e-05 | I12: 7.1711476e-05 | J12: 0.00035573553 | K12: 6.3162733e-06 | L12: 5.5440785e-05 | M12: 3.6818338e-05 | P12: ATTIJARIWAFA BANK | Q12: Achat | R12: 128 | S12: 0.099054032 | T12: 0.2 | U12: 258 | V12: 130 | W12: 768 | X12: 755
A13: Label vie | B13: 0.031747259 | C13: 3.5410992e-05 | D13: 4.496443e-05 | E13: -5.9453031e-06 | F13: 3.076744e-05 | G13: 4.1678841e-05 | H13: 7.9440264e-06 | I13: 5.0915e-05 | J13: 6.3162733e-06 | K13: 0.0003754659 | L13: 4.6709254e-05 | M13: 4.2518643e-05 | P13: Sanlam | Q13: Achat | R13: 46 | S13: 0.09246115 | T13: 0.1 | U13: 50 | V13: 4 | W13: 1951 | X13: 1923
A14: Tgcc | B14: 0.1 | C14: 5.4761933e-05 | D14: 4.8550988e-05 | E14: 3.5570373e-05 | F14: 0.00013067084 | G14: 6.1119694e-05 | H14: -3.5297333e-06 | I14: 0.00012996106 | J14: 5.5440785e-05 | K14: 4.6709254e-05 | L14: 0.00034562808 | M14: 2.1641772e-05 | P14: Marsa maroc | Q14: Achat | R14: 92 | S14: 0.091813922 | T14: 0.1 | U14: 101 | V14: 9 | W14: 975 | X14: 965.1
A15: HPS | B15: 0 | C15: 6.1546498e-05 | D15: 4.1878286e-05 | E15: 1.2919385e-05 | F15: 3.0227588e-05 | G15: 2.9845703e-05 | H15: 1.2261681e-05 | I15: 4.0331677e-05 | J15: 3.6818338e-05 | K15: 4.2518643e-05 | L15: 2.1641772e-05 | M15: 0.00026626098 | P15: Ciments du Maroc | Q15: Achat | R15: 37 | S15: 0.076118642 | T15: 0.1 | U15: 49 | V15: 12 | W15: 2003 | X15: 2000
B16: =SUM(B5:B15) -> 1 | P16: Label vie | Q16: Vente | R16: 18 | S16: 0.082527606 | T16: 0.031747259 | U16: 7 | V16: 11 | W16: 4698 | X16: 4696 | Y16: =V16*X16-V16*W16 -> -22
B17: Rendement Moyen | C17: 0.00037524955 | D17: 0.00062822796 | E17: 0.0021214683 | F17: 0.0025114593 | G17: 0.00098563204 | H17: 0.0014134294 | I17: 0.002230273 | J17: 0.00076560201 | K17: 0.00020024109 | L17: 0.0030485553 | M17: -0.00017179514 | P17: Tgcc | Q17: Achat | R17: 106 | S17: 0.1006721 | T17: 0.1 | U17: 105 | V17: 1 | W17: 931 | X17: 951.8 | Y17: =V17*X17-V17*W17 -> 20.8
P18: HPS | Q18: Vente | R18: 187 | S18: 0.10242585 | T18: 0 | U18: 0 | V18: 185 | W18: 528 | X18: 545 | Y18: =V18*X18-V18*W18 -> 3145
C19: Rendement PF | D19: =SUMPRODUCT(C17:M17,C3:M3) -> 0.0015009968 | Y19: =SUM(Y8:Y18) -> 2514.15
C20: Variance PF | D20: {=MMULT(C3:M3,MMULT(C5:M15,B5:B15))} -> 8.0862982e-05
C21: Ecart Type PF | D21: =SQRT(D20) -> 0.0089923847
C22: Ecart Type PF Annualisé | D22: =D21*SQRT(250) -> 0.14218209

Sheet Matrice de corrélation
C4: IAM | D4: Sothema | E4: RISMA | F4: Sonasid | G4: ATTIJARIWAFA BANK | H4: Sanlam | I4: Marsa maroc | J4: Ciments du Maroc | K4: Label vie | L4: Tgcc | M4: HPS
B5: IAM | C5: 1 | D5: =CORREL('R-R PF'!$M$3:$M$692,'R-R PF'!N3:N692) -> 0.14496116 | E5: =CORREL('R-R PF'!$M$3:$M$692,'R-R PF'!O3:O692) -> 0.11098146 | F5: =CORREL('R-R PF'!$M$3:$M$692,'R-R PF'!P3:P692) -> 0.2127116 | G5: =CORREL('R-R PF'!$M$3:$M$692,'R-R PF'!Q3:Q692) -> 0.3545773 | H5: =CORREL('R-R PF'!$M$3:$M$692,'R-R PF'!R3:R692) -> 0.066219745 | I5: =CORREL('R-R PF'!$M$3:$M$692,'R-R PF'!S3:S692) -> 0.32744134 | J5: =CORREL('R-R PF'!$M$3:$M$692,'R-R PF'!T3:T692) -> 0.24606927 | K5: =CORREL('R-R PF'!$M$3:$M$692,'R-R PF'!U3:U692) -> 0.1137341 | ... M5: =CORREL('R-R PF'!$M$3:$M$692,'R-R PF'!W3:W692) -> 0.23474018
B6: Sothema | C6: 0.14496116 | D6: 1 | E6: =CORREL('R-R PF'!$N$3:$N$692,'R-R PF'!O3:O692) -> 0.03286739 | F6: =CORREL('R-R PF'!$N$3:$N$692,'R-R PF'!P3:P692) -> 0.09463347 | G6: =CORREL('R-R PF'!$N$3:$N$692,'R-R PF'!Q3:Q692) -> 0.19490352 | H6: =CORREL('R-R PF'!$N$3:$N$692,'R-R PF'!R3:R692) -> 0.055875446 | I6: =CORREL('R-R PF'!$N$3:$N$692,'R-R PF'!S3:S692) -> 0.096741686 | J6: =CORREL('R-R PF'!$N$3:$N$692,'R-R PF'!T3:T692) -> 0.06822932 | K6: =CORREL('R-R PF'!$N$3:$N$692,'R-R PF'!U3:U692) -> 0.10315737 | L6: =CORREL('R-R PF'!$N$3:$N$692,'R-R PF'!V3:V692) -> 0.11609406 | M6: =CORREL('R-R PF'!$N$3:$N$692,'R-R PF'!W3:W692) -> 0.11409105
B7: RISMA | C7: 0.11098146 | D7: 0.03286739 | E7: 1 | F7: =CORREL('R-R PF'!$O$3:$O$692,'R-R PF'!P3:P692) -> 0.14281338 | G7: =CORREL('R-R PF'!$O$3:$O$692,'R-R PF'!Q3:Q692) -> 0.15191036 | H7: =CORREL('R-R PF'!$O$3:$O$692,'R-R PF'!R3:R692) -> 0.041839021 | I7: =CORREL('R-R PF'!$O$3:$O$692,'R-R PF'!S3:S692) -> 0.090817786 | J7: =CORREL('R-R PF'!$O$3:$O$692,'R-R PF'!T3:T692) -> 0.052619888 | K7: =CORREL('R-R PF'!$O$3:$O$692,'R-R PF'!U3:U692) -> -0.014276204 | L7: =CORREL('R-R PF'!$O$3:$O$692,'R-R PF'!V3:V692) -> 0.089024163 | M7: =CORREL('R-R PF'!$O$3:$O$692,'R-R PF'!W3:W692) -> 0.036839359
B8: Sonasid | C8: 0.2127116 | D8: 0.09463347 | E8: 0.14281338 | F8: 1 | G8: =CORREL('R-R PF'!$P$3:$P$692,'R-R PF'!Q3:Q692) -> 0.27422211 | H8: =CORREL('R-R PF'!$P$3:$P$692,'R-R PF'!R3:R692) -> 0.074266531 | I8: =CORREL('R-R PF'!$P$3:$P$692,'R-R PF'!S3:S692) -> 0.27800248 | J8: =CORREL('R-R PF'!$P$3:$P$692,'R-R PF'!T3:T692) -> 0.23351018 | K8: =CORREL('R-R PF'!$P$3:$P$692,'R-R PF'!U3:U692) -> 0.071884373 | L8: =CORREL('R-R PF'!$P$3:$P$692,'R-R PF'!V3:V692) -> 0.31820175 | M8: =CORREL('R-R PF'!$P$3:$P$692,'R-R PF'!W3:W692) -> 0.083864492
B9: ATTIJARIWAFA BANK | C9: 0.3545773 | D9: 0.19490352 | E9: 0.15191036 | F9: 0.27422211 | G9: 1 | H9: =CORREL('R-R PF'!$Q$3:$Q$692,'R-R PF'!R3:R692) -> 0.055589129 | I9: =CORREL('R-R PF'!$Q$3:$Q$692,'R-R PF'!S3:S692) -> 0.39897388 | J9: =CORREL('R-R PF'!$Q$3:$Q$692,'R-R PF'!T3:T692) -> 0.23962271 | K9: =CORREL('R-R PF'!$Q$3:$Q$692,'R-R PF'!U3:U692) -> 0.19274081 | L9: =CORREL('R-R PF'!$Q$3:$Q$692,'R-R PF'!V3:V692) -> 0.29459133 | M9: =CORREL('R-R PF'!$Q$3:$Q$692,'R-R PF'!W3:W692) -> 0.16389713
B10: Sanlam | C10: 0.066219745 | D10: 0.055875446 | E10: 0.041839021 | F10: 0.074266531 | G10: 0.055589129 | H10: 1 | I10: =CORREL('R-R PF'!$R$3:$R$692,'R-R PF'!S3:S692) -> 0.056034277 | J10: =CORREL('R-R PF'!$R$3:$R$692,'R-R PF'!T3:T692) -> 0.041909528 | K10: =CORREL('R-R PF'!$R$3:$R$692,'R-R PF'!U3:U692) -> 0.016318915 | L10: =CORREL('R-R PF'!$R$3:$R$692,'R-R PF'!V3:V692) -> -0.0075574146 | M10: =CORREL('R-R PF'!$R$3:$R$692,'R-R PF'!W3:W692) -> 0.02991108
B11: Marsa maroc | C11: 0.32744134 | D11: 0.096741686 | E11: 0.090817786 | F11: 0.27800248 | G11: 0.39897388 | H11: 0.056034277 | I11: 1 | J11: =CORREL('R-R PF'!$S$3:$S$692,'R-R PF'!T3:T692) -> 0.24317521 | K11: =CORREL('R-R PF'!$S$3:$S$692,'R-R PF'!U3:U692) -> 0.16805629 | L11: =CORREL('R-R PF'!$S$3:$S$692,'R-R PF'!V3:V692) -> 0.44709827 | M11: =CORREL('R-R PF'!$S$3:$S$692,'R-R PF'!W3:W692) -> 0.15808359
B12: Ciments du Maroc | C12: 0.24606927 | D12: 0.06822932 | E12: 0.052619888 | F12: 0.23351018 | G12: 0.23962271 | H12: 0.041909528 | I12: 0.24317521 | J12: 1 | K12: =CORREL('R-R PF'!$T$3:$T$692,'R-R PF'!U3:U692) -> 0.017282718 | L12: =CORREL('R-R PF'!$T$3:$T$692,'R-R PF'!V3:V692) -> 0.15811069 | M12: =CORREL('R-R PF'!$T$3:$T$692,'R-R PF'!W3:W692) -> 0.11963184
B13: Label vie | C13: 0.1137341 | D13: 0.10315737 | E13: -0.014276204 | F13: 0.071884373 | G13: 0.19274081 | H13: 0.016318915 | I13: 0.16805629 | J13: 0.017282718 | K13: 1 | L13: =CORREL('R-R PF'!$U$3:$U$692,'R-R PF'!V3:V692) -> 0.12966214 | M13: =CORREL('R-R PF'!$U$3:$U$692,'R-R PF'!W3:W692) -> 0.13447464
B14: Tgcc | C14: 0.18332096 | D14: 0.11609406 | E14: 0.089024163 | F14: 0.31820175 | G14: 0.29459133 | H14: -0.0075574146 | I14: 0.44709827 | J14: 0.15811069 | K14: 0.12966214 | L14: 1 | M14: =CORREL('R-R PF'!$V$3:$V$692,'R-R PF'!W3:W692) -> 0.071340235
B15: HPS | C15: 0.23474018 | D15: 0.11409105 | E15: 0.036839359 | F15: 0.083864492 | G15: 0.16389713 | H15: 0.02991108 | I15: 0.15808359 | J15: 0.11963184 | K15: 0.13447464 | L15: 0.071340235 | M15: 1
A18: Le coefficient de corrélation égal à 1 | E18: Une corrélation positive | N18: Une corrélation faible | U18: Une corrélation négative
A19: Correspond à une corrélation parfaite positive ce qui n’existe que lorsqu’on parle d’une même valeur bien évidement parce qu’il évoluent exactement de la même manière | E19: Indique qu’il existe une évolution similaire entre les valeurs , mais pas parfaite : lorsque la première valeur augmente, la seconde tend également à augmenter. Dans notre portefeuille, nous observons par exemple qu’Attijariwafa Bank et IAM présentent un coefficient de corrélation de 0,360, ce qui constitue la corrélation la plus élevée parmi nos titres. De même, IAM et Marsa Maroc affichent une corrélation de 0,330. Bien que ces entreprises appartiennent à des secteurs d’activité distincts, cette corrélation positive s’explique par la structure du marché marocain, qui demeure peu diversifié et largement dominé par quelques grandes capitalisations telles qu’IAM ou Attijariwafa Bank. Ces valeurs dites “Blue Chips” réagissent souvent aux mêmes mouvements du marché et aux décisions des investisseurs institutionnels. De plus, plusieurs facteurs macroéconomiques communs influencent simultanément ces sociétés : la croissance économique globale, la stabilité politique et monétaire, ainsi que la politique monétaire conduite par Bank Al-Maghrib. Enfin, le marché marocain étant relativement concentré, les investisseurs ont tendance à acheter ou à vendre les titres du MASI de manière collective, sans cibler un seul actif en particulier. | N19: Une corrélation faible entre les valeurs on constate que dans notre portfeuille c’était le cous pour risma et toute autres valeurs en outre de sanlam et HPS qui est de 0,029 Risma (secteur du tourisme et de l’hôtellerie)évolue selon un cycle économique différent de celui qui influencent les grandes entreprises marocaines généralement Son activité dépend du tourisme international, du taux de change du dirham, de la stabilité politique mondiale et de la demande étrangère.ce qui réduit naturellement sa corrélation avec les autres valeurs. Leurs sources de revenus et facteurs de risque n’ont presque aucun lien, d’où cette corrélation très faible. En plus, le marché boursier marocain est peu liquide, donc les cours des entreprises de niche comme HPS peuvent bouger indépendamment des grandes tendances du MASI. | U19: C’est-à-dire les rendements des couples d’entreprises évoluent de manière légèrement en sens opposé, mais sans lien fort. Par exemple RISMA et Label vie correéle de -0,0142 les deux secteurs ne réagissent pas aux mêmes moteurs de croissance.En période où le tourisme ralentit (ex. crise internationale, baisse du pouvoir d’achat des touristes), la consommation locale peut se maintenir, soutenant Label Vie. Prenant aussi l’exemple de Sanlam et TGCC avec une corrélation de -0,00755 car Chacune réagit différemment aux politiques monétaires et budgétaires marocaines.Lorsque par exemple les taux d’intérêt montent, cela peut freiner l’investissement immobilier (impactant TGCC) mais profiter aux sociétés d’assurance (comme Sanlam) qui obtiennent de meilleurs rendements sur leurs placements obligataires.
D38: Synthèse | F38: La matrice de corrélation de notre portefeuille révèle des coefficients majoritairement positifs, variant d’intensité faible à forte, traduisant une évolution globalement cohérente des titres du portefeuille. Cette situation reflète une diversification modérée, pas très forte mais c une caractéristique d’un marché où plusieurs valeurs réagissent de manière similaire aux conditions économiques nationales

Sheet VAR-COVAR PF
B3: Poids 24/10/25 | C3: 0.098732772 | D3: 0.089874712 | E3: 0.090065614 | F3: 0.082062796 | G3: 0.10287334 | H3: 0.087861197 | I3: 0.091050267 | J3: 0.075094868 | K3: 0.084820829 | L3: 0.097983029 | M3: 0.099580578
C4: IAM | D4: Sothema | E4: RISMA | F4: Sonasid | G4: ATTIJARIWAFA BANK | H4: Sanlam | I4: Marsa maroc | J4: Ciments du Maroc | K4: Label vie | L4: Tgcc | M4: HPS
A5: IAM | B5: 0.098732772 | C5: 0.00025818101 | D5: 5.2395908e-05 | E5: 3.8325566e-05 | F5: 7.5496172e-05 | G5: 6.3581355e-05 | H5: 2.6730913e-05 | I5: 8.2262401e-05 | J5: 7.4573262e-05 | K5: 3.5410992e-05 | L5: 5.4761933e-05 | M5: 6.1546498e-05
A6: Sothema | B6: 0.089874712 | C6: 5.2395908e-05 | D6: 0.00050601937 | E6: 1.5890033e-05 | F6: 4.7021876e-05 | G6: 4.8928282e-05 | H6: 3.1576843e-05 | I6: 3.4025378e-05 | J6: 2.8947978e-05 | K6: 4.496443e-05 | L6: 4.8550988e-05 | M6: 4.1878286e-05
A7: RISMA | B7: 0.090065614 | C7: 3.8325566e-05 | D7: 1.5890033e-05 | E7: 0.00046190432 | F7: 6.7797943e-05 | G7: 3.6435111e-05 | H7: 2.2590282e-05 | I7: 3.051776e-05 | J7: 2.1329936e-05 | K7: -5.9453031e-06 | L7: 3.5570373e-05 | M7: 1.2919385e-05
A8: Sonasid | B8: 0.082062796 | C8: 7.5496172e-05 | D8: 4.7021876e-05 | E8: 6.7797943e-05 | F8: 0.00048791395 | G8: 6.7597524e-05 | H8: 4.1212494e-05 | I8: 9.601211e-05 | J8: 9.7283919e-05 | K8: 3.076744e-05 | L8: 0.00013067084 | M8: 3.0227588e-05
A9: ATTIJARIWAFA BANK | B9: 0.10287334 | C9: 6.3581355e-05 | D9: 4.8928282e-05 | E9: 3.6435111e-05 | F9: 6.7597524e-05 | G9: 0.00012454131 | H9: 1.558514e-05 | I9: 6.9615653e-05 | J9: 5.043689e-05 | K9: 4.1678841e-05 | L9: 6.1119694e-05 | M9: 2.9845703e-05
A10: Sanlam | B10: 0.087861197 | C10: 2.6730913e-05 | D10: 3.1576843e-05 | E10: 2.2590282e-05 | F10: 4.1212494e-05 | G10: 1.558514e-05 | H10: 0.00063114373 | I10: 2.2010182e-05 | J10: 1.985823e-05 | K10: 7.9440264e-06 | L10: -3.5297333e-06 | M10: 1.2261681e-05
A11: Marsa maroc | B11: 0.091050267 | C11: 8.2262401e-05 | D11: 3.4025378e-05 | E11: 3.051776e-05 | F11: 9.601211e-05 | G11: 6.9615653e-05 | H11: 2.2010182e-05 | I11: 0.00024446206 | J11: 7.1711476e-05 | K11: 5.0915e-05 | L11: 0.00012996106 | M11: 4.0331677e-05 | O11: Rendement PF | P11: =SUMPRODUCT(C16:M16,C3:M3) -> 0.0012754044
A12: Ciments du Maroc | B12: 0.075094868 | C12: 7.4573262e-05 | D12: 2.8947978e-05 | E12: 2.1329936e-05 | F12: 9.7283919e-05 | G12: 5.043689e-05 | H12: 1.985823e-05 | I12: 7.1711476e-05 | J12: 0.00035573553 | K12: 6.3162733e-06 | L12: 5.5440785e-05 | M12: 3.6818338e-05 | O12: Variance PF | P12: {=MMULT(C3:M3,MMULT(C5:M15,B5:B15))} -> 7.3139335e-05
A13: Label vie | B13: 0.084820829 | C13: 3.5410992e-05 | D13: 4.496443e-05 | E13: -5.9453031e-06 | F13: 3.076744e-05 | G13: 4.1678841e-05 | H13: 7.9440264e-06 | I13: 5.0915e-05 | J13: 6.3162733e-06 | K13: 0.0003754659 | L13: 4.6709254e-05 | M13: 4.2518643e-05 | O13: Ecart Type PF | P13: =SQRT(P12) -> 0.0085521538
A14: Tgcc | B14: 0.097983029 | C14: 5.4761933e-05 | D14: 4.8550988e-05 | E14: 3.5570373e-05 | F14: 0.00013067084 | G14: 6.1119694e-05 | H14: -3.5297333e-06 | I14: 0.00012996106 | J14: 5.5440785e-05 | K14: 4.6709254e-05 | L14: 0.00034562808 | M14: 2.1641772e-05 | O14: Ecart Type PF Annualisé | P14: =P13*SQRT(250) -> 0.13522142
A15: HPS | B15: 0.099580578 | C15: 6.1546498e-05 | D15: 4.1878286e-05 | E15: 1.2919385e-05 | F15: 3.0227588e-05 | G15: 2.9845703e-05 | H15: 1.2261681e-05 | I15: 4.0331677e-05 | J15: 3.6818338e-05 | K15: 4.2518643e-05 | L15: 2.1641772e-05 | M15: 0.00026626098
B16: Rendement Moyen | C16: 0.00037524955 | D16: 0.00062822796 | E16: 0.0021214683 | F16: 0.0025114593 | G16: 0.00098563204 | H16: 0.0014134294 | I16: 0.002230273 | J16: 0.00076560201 | K16: 0.00020024109 | L16: 0.0030485553 | M16: -0.00017179514
B20: Interprétation des résultats du matrice de var covar :
B22: La matrice de variance-covariance permet d’évaluer à la fois le risque individuel de chaque actif et la relation entre les rendements des différentes entreprises. Les valeurs situées sur la diagonale représentent les variances, c’est-à-dire le niveau de volatilité propre à chaque titre.
B26: Dans cette matrice, les variances les plus élevées concernent principalement Sanlam (0,000631), Sothema (0,000506), Risma (0,000462) et Sonasid (0,000489), indiquant que ces entreprises présentent une plus forte instabilité de rendement et donc un niveau de risque plus élevé. À l’inverse, Attijariwafa Bank (0,000124) se distingue par une variance plus faible, traduisant une meilleure stabilité et un profil moins risqué. | G26: Les valeurs hors diagonale correspondent aux covariances entre les différentes entreprises. De manière générale, la plupart de ces covariances sont positives, ce qui suggère que les rendements des titres évoluent dans le même sens. Cela traduit une corrélation positive au sein du marché boursier marocain, caractéristique d’un environnement où les entreprises réagissent souvent de manière similaire aux conditions économiques. Cependant, quelques covariances légèrement négatives, notamment entre Label Vie et Sanlam (-5,94E-06) ou entre Sanlam et TGCC (-3,53E-06), indiquent la présence d’un léger effet de diversification, bien que limité. | M26: Ainsi, cette matrice met en évidence un niveau de corrélation globalement positif, reflétant une diversification moyenne du portefeuille. D’un point de vue global, le rendement moyen du portefeuille s’établit à 0,128 %, pour une variance de 0,007 % et un écart-type de 0,855 %, soit une volatilité annualisée de 13,52 %. Ces résultats montrent un portefeuille relativement stable avec un compromis acceptable entre risque et rendement. Néanmoins, la corrélation positive dominante limite la possibilité d’une diversification optimale, car la majorité des titres évoluent dans la même direction, réduisant ainsi l’effet de réduction du risque espéré dans un portefeuille parfaitement diversifié.

Sheet VAR-COVAR MASI 20
C2: Poids 24/10/25 | D2: 0.041282943 | E2: 0.022101995 | F2: 0.22945386 | G2: 0.05282422 | H2: 0.08382313 | I2: 0.023931136 | J2: 0.013011736 | K2: 0.059069181 | L2: 0.015495378 | M2: 0.057535735 | N2: 0.023870729 | O2: 0.094557862 | P2: 0.014216538 | Q2: 0.023866722 | R2: 0.041885859 | S2: 0.0092279969 | T2: 0.10291146 | U2: 0.012514329 | V2: 0.039341805 | W2: 0.039077383
D3: AKDITAL | E3: ALLIANCES | F3: ATTIJARI WAFA BANK | G3: BANK OF AFRICA | H3: BCP | I3: CDM | J3: CFG BANK | K3: CIMENTS DU MAROC | L3: CMGP GROUP | M3: COSUMAR | N3: DOUJA PROM ADDOHA | O3: ITISSALAT AL-MAGHRIB | P3: JET CONTRACTORS | Q3: LABEL VIE | R3: LAFARGEHOLCIM MAROC | S3: RESIDENCES DAR SAADA | T3: SODEP- Marsa Maroc | U3: SONASID | V3: TAQA MOROCCO | W3: TGCC S.A
B4: AKDITAL | C4: 0.041282943 | D4: 0.00024198693 | E4: 9.4967526e-05 | F4: 5.4314249e-05 | G4: 4.5667749e-05 | H4: 4.0416621e-05 | I4: 3.7610664e-05 | J4: 4.5674518e-05 | K4: 8.5498938e-05 | L4: 0.00015524761 | M4: 3.5581233e-05 | N4: 0.00010232875 | O4: 6.2486835e-05 | P4: 8.3996678e-05 | Q4: 3.4399084e-05 | R4: 4.0766181e-05 | S4: 6.3893962e-05 | T4: 7.8804162e-05 | U4: 7.0432856e-05 | V4: 7.3822115e-05 | W4: 7.2507663e-05
B5: ALLIANCES | C5: 0.022101995 | D5: 9.4967526e-05 | E5: 0.00059417106 | F5: 8.5230724e-05 | G5: 4.9647725e-05 | H5: 7.6694053e-05 | I5: 7.2102706e-05 | J5: 8.6530659e-05 | K5: 0.00012174143 | L5: 0.00022005211 | M5: 6.1832691e-05 | N5: 0.00042086615 | O5: 0.0001016027 | P5: 0.00016946108 | Q5: 3.7343268e-05 | R5: 9.904629e-05 | S5: 0.00034291425 | T5: 0.00012639622 | U5: 0.00016572415 | V5: 9.1699292e-05 | W5: 0.00014385806
B6: ATTIJARI WAFA BANK | C6: 0.22945386 | D6: 5.4314249e-05 | E6: 8.5230724e-05 | F6: 0.00013211039 | G6: 4.5248534e-05 | H6: 6.607941e-05 | I6: 4.9142716e-05 | J6: 5.5214799e-05 | K6: 6.0469034e-05 | L6: 0.00016664929 | M6: 6.1857003e-05 | N6: 8.5797542e-05 | O6: 6.8472861e-05 | P6: 7.6193463e-05 | Q6: 3.9961029e-05 | R6: 5.1516254e-05 | S6: 5.7766741e-05 | T6: 7.3730022e-05 | U6: 7.525976e-05 | V6: 4.7114199e-05 | W6: 6.0848334e-05
B7: BANK OF AFRICA | C7: 0.05282422 | D7: 4.5667749e-05 | E7: 4.9647725e-05 | F7: 4.5248534e-05 | G7: 0.00021937269 | H7: 5.5492195e-05 | I7: 4.8189949e-05 | J7: 4.9685882e-05 | K7: 5.4002189e-05 | L7: 6.0589849e-05 | M7: 5.3627166e-05 | N7: 4.9534001e-05 | O7: 4.1851457e-05 | P7: 4.7746511e-05 | Q7: 2.8372321e-05 | R7: 4.1993766e-05 | S7: 3.3653378e-05 | T7: 4.0204152e-05 | U7: 5.7339011e-05 | V7: 4.247775e-05 | W7: 5.4253663e-05
B8: BCP | C8: 0.08382313 | D8: 4.0416621e-05 | E8: 7.6694053e-05 | F8: 6.607941e-05 | G8: 5.5492195e-05 | H8: 0.00016008451 | I8: 5.317289e-05 | J8: 5.4558841e-05 | K8: 4.4124435e-05 | L8: 9.6256837e-05 | M8: 6.9725555e-05 | N8: 5.8120249e-05 | O8: 6.7454658e-05 | P8: 3.6367882e-05 | Q8: 1.8864912e-05 | R8: 6.0670106e-05 | S8: 4.7795957e-05 | T8: 6.5568673e-05 | U8: 5.4490849e-05 | V8: 4.904746e-05 | W8: 5.2975952e-05
B9: CDM | C9: 0.023931136 | D9: 3.7610664e-05 | E9: 7.2102706e-05 | F9: 4.9142716e-05 | G9: 4.8189949e-05 | H9: 5.317289e-05 | I9: 0.00053585289 | J9: 8.3805341e-05 | K9: 4.7116658e-05 | L9: 8.1814146e-05 | M9: 1.4031786e-05 | N9: 7.6572847e-05 | O9: 6.0295949e-05 | P9: 4.3954196e-05 | Q9: 2.1734314e-05 | R9: 7.098174e-05 | S9: 5.2111373e-05 | T9: 4.4770628e-05 | U9: 7.3366972e-05 | V9: 7.0058135e-05 | W9: 6.7713812e-05
B10: CFG BANK | C10: 0.013011736 | D10: 4.5674518e-05 | E10: 8.6530659e-05 | F10: 5.5214799e-05 | G10: 4.9685882e-05 | H10: 5.4558841e-05 | I10: 8.3805341e-05 | J10: 0.00036558618 | K10: 7.7879251e-05 | L10: 0.00013187487 | M10: 6.9436143e-05 | N10: 8.4681665e-05 | O10: 7.6823974e-05 | P10: 5.66093e-05 | Q10: -4.3264912e-07 | R10: 0.00010892937 | S10: 7.723862e-05 | T10: 6.404022e-05 | U10: 9.9211012e-05 | V10: 7.9168962e-05 | W10: 5.6451378e-05
B11: CIMENTS DU MAROC | C11: 0.059069181 | D11: 8.5498938e-05 | E11: 0.00012174143 | F11: 6.0469034e-05 | G11: 5.4002189e-05 | H11: 4.4124435e-05 | I11: 4.7116658e-05 | J11: 7.7879251e-05 | K11: 0.00026232152 | L11: 0.00014565288 | M11: 4.8019651e-05 | N11: 0.00012104549 | O11: 6.2631215e-05 | P11: 0.00010138283 | Q11: 4.14589e-05 | R11: 6.5177421e-05 | S11: 9.7907261e-05 | T11: 6.9934801e-05 | U11: 9.0146569e-05 | V11: 6.2639252e-05 | W11: 7.2192357e-05
B12: CMGP GROUP | C12: 0.015495378 | D12: 0.00015524761 | E12: 0.00022005211 | F12: 0.00016664929 | G12: 6.0589849e-05 | H12: 9.6256837e-05 | I12: 8.1814146e-05 | J12: 0.00013187487 | K12: 0.00014565288 | L12: 0.00072869346 | M12: 0.0001656736 | N12: 0.00021322722 | O12: 0.00012926905 | P12: 0.00032191309 | Q12: 5.8256608e-05 | R12: 0.00013090825 | S12: 0.00021135716 | T12: 0.00011646617 | U12: 0.00020932015 | V12: 0.00015016004 | W12: 0.00011539969
B13: COSUMAR | C13: 0.057535735 | D13: 3.5581233e-05 | E13: 6.1832691e-05 | F13: 6.1857003e-05 | G13: 5.3627166e-05 | H13: 6.9725555e-05 | I13: 1.4031786e-05 | J13: 6.9436143e-05 | K13: 4.8019651e-05 | L13: 0.0001656736 | M13: 0.0002956171 | N13: 5.1277712e-05 | O13: 7.8483316e-05 | P13: 4.3036358e-05 | Q13: 3.7160864e-05 | R13: 7.0984724e-05 | S13: 4.1333538e-05 | T13: 6.9028973e-05 | U13: 7.4684468e-05 | V13: 3.9732272e-05 | W13: 2.4942359e-05
B14: DOUJA PROM ADDOHA | C14: 0.023870729 | D14: 0.00010232875 | E14: 0.00042086615 | F14: 8.5797542e-05 | G14: 4.9534001e-05 | H14: 5.8120249e-05 | I14: 7.6572847e-05 | J14: 8.4681665e-05 | K14: 0.00012104549 | L14: 0.00021322722 | M14: 5.1277712e-05 | N14: 0.0007175242 | O14: 8.0812554e-05 | P14: 0.00015190173 | Q14: 4.8654305e-05 | R14: 8.4352693e-05 | S14: 0.00044880943 | T14: 0.00010210135 | U14: 0.0001754349 | V14: 0.00012193667 | W14: 0.00013212331
B15: ITISSALAT AL-MAGHRIB | C15: 0.094557862 | D15: 6.2486835e-05 | E15: 0.0001016027 | F15: 6.8472861e-05 | G15: 4.1851457e-05 | H15: 6.7454658e-05 | I15: 6.0295949e-05 | J15: 7.6823974e-05 | K15: 6.2631215e-05 | L15: 0.00012926905 | M15: 7.8483316e-05 | N15: 8.0812554e-05 | O15: 0.00026208305 | P15: 5.0120157e-05 | Q15: 3.3111582e-05 | R15: 6.586934e-05 | S15: 7.7978419e-05 | T15: 8.3898716e-05 | U15: 8.2352526e-05 | V15: 6.8724137e-05 | W15: 5.7090106e-05
... B23: TGCC S.A | C23: 0.039077383 | D23: 7.2507663e-05 | E23: 0.00014385806 | F23: 6.0848334e-05 | G23: 5.4253663e-05 | H23: 5.2975952e-05 | I23: 6.7713812e-05 | J23: 5.6451378e-05 | K23: 7.2192357e-05 | L23: 0.00011539969 | M23: 2.4942359e-05 | N23: 0.00013212331 | O23: 5.7090106e-05 | P23: 0.00013041844 | Q23: 4.4273373e-05 | R23: 5.4021591e-05 | S23: 0.00012999182 | T23: 0.00012848405 | U23: 0.00012026444 | V23: 8.7463866e-05 | W23: 0.0003504491
C24: Rendements Moyens | D24: 0.00086678291 | E24: 0.00091175278 | F24: 0.0011496225 | G24: 0.001006879 | H24: -0.00017014446 | I24: 0.0003183058 | J24: 0.0010421557 | K24: 0.0001558358 | L24: 0.0030291307 | M24: 0.00080955268 | N24: 3.8534868e-05 | O24: 0.0015517782 | P24: 0.0023298712 | Q24: 0.00080208791 | R24: -0.00024361281 | S24: 0.0044370489 | T24: 0.0027625994 | U24: 0.0047772399 | V24: 0.0029739278 | W24: 0.0032404616
C29: Rendement MASI 20 | D29: =SUMPRODUCT(D24:W24,D2:W2) -> 0.0013009196
C30: Variance MASI 20 | D30: {=MMULT((D2:W2),MMULT(D4:W23,C4:C23))} -> 8.0863113e-05
C31: Ecart Type MASI 20 | D31: =+SQRT(D30) -> 0.008992392
C32: Ecart Type MASI 20 Annualisé | D32: =D31*SQRT(250) -> 0.1421822

Sheet La comparaison
E3: Beta avantsolveur | F3: rendement | G3: Ecartype avantsolveur
D4: Portfeuille | E4: 0.925 | F4: 0.0013 | G4: 0.1352
D5: Masi 20 | E5: 1 | F5: 0.0013009196 | G5: 0.1421822 | J5: La comparaison
D6: TOP 1 | E6: 0.345013 | F6: 0.0162 | G6: 0.1185 | K6: Lecture générale du risque et de la performance L’ensemble des portefeuilles présente des profils de risque très différents, comme en témoignent les niveaux de bêta. Alors que le MASI 20, avec un bêta de 1, représente parfaitement le risque systématique du marché marocain, plusieurs de tes portefeuilles affichent un risque systématique nettement plus faible, ce qui traduit une meilleure diversification ou une plus faible sensibilité aux fluctuations générales du marché. Les rendements montrent également des écarts importants : certains portefeuilles génèrent plus de rendement pour moins de risque, ce qui est typiquement un indicateur d’efficience financière. Comparaison entre mon portefeuille et le MASI 20 En comparant mon portefeuille au MASI 20, on remarque qu’ils affichent le même rendement (0,13 %), mais avec une différence au niveau du risque. Le MASI 20 a un bêta de 1, alors que mon portefeuille a un bêta légèrement plus faible (0,925), ce qui signifie qu’il est un peu moins sensible aux variations du marché. De plus, son écart-type est inférieur à celui du MASI, ce qui montre une volatilité plus faible. En résumé, mon portefeuille arrive à offrir la même performance que l’indice tout en étant un peu moins risqué. Comparaison entre mon portefeuille et les 5 TOP Par rapport aux cinq TOP, on voit rapidement que certains portefeuilles font mieux que le mien, surtout en termes de rendement. TOP 1, par exemple, combine un rendement très élevé avec un bêta faible et une volatilité réduite, ce qui le place largement au-dessus des autres. Des portefeuilles comme TOP 3 ou TOP 5 affichent aussi de meilleures performances tout en gardant un niveau de risque raisonnable. À l’inverse, TOP 4 reste en dessous de mon portefeuille, car il offre un rendement plus faible pour un risque similaire. Globalement, même si mon portefeuille est plus efficace que le MASI 20, certains TOP montrent une meilleure optimisation du couple rendement-risque.
D7: TOP2 | E7: 0.23421968 | F7: 0.0055 | G7: 0.1357
D8: TOP3 | E8: 0.97285681 | F8: 0.0098 | G8: 0.1424
D9: TOP4 | E9: 0.09196 | F9: 0.0008 | G9: 0.1422
D10: TOP5 | E10: 0.65439117 | F10: 0.0055 | G10: 0.1357
D15: Ecart type | E15: Rendement | F15: Beta | G15: Ratio de sharpe | H15: Rang
C16: 1 | D16: 0.1426 | E16: 0.0014 | F16: 0.8760084 | G16: =E16/F16 -> 0.0015981582
C17: 2 | D17: 0.1424 | E17: 0.0098 | F17: 0.23421968 | G17: =E17/F17 -> 0.041841061 | H17: 2
C18: 3 | D18: 0.1422 | E18: 0.0008 | F18: 0.09196 | G18: =E18/F18 -> 0.0086994345 | H18: 4
C19: 4 | D19: 0.1377 | E19: 0.0081 | F19: 0.99451 | G19: =E19/F19 -> 0.0081447145
C20: 5 | D20: 0.1357 | E20: 0.0055 | F20: 0.65439117 | G20: =E20/F20 -> 0.0084047589 | H20: 5
C21: 6 | D21: 0.1422 | E21: -0.0066 | F21: 0.4766494 | G21: =E21/F21 -> -0.013846656
C22: 7 | D22: 0.1422 | E22: 0.0015 | F22: 0.9795184 | G22: =E22/F22 -> 0.0015313648
C23: 8 | D23: 0.1446 | E23: 0.0015 | F23: 0.8183 | G23: =E23/F23 -> 0.0018330686
C24: 9 | D24: 0.1185 | E24: 0.0162 | F24: 0.345013 | G24: =E24/F24 -> 0.046954752 | H24: 1
C25: 10 | D25: 0.1424 | E25: 0.0098 | F25: 0.97285681 | G25: =E25/F25 -> 0.010073425 | H25: 3
C26: 11 | D26: 0.1425 | E26: 0.0015 | F26: 1.0661467 | G26: =E26/F26 -> 0.0014069358
C27: 12 | D27: 0.1421 | E27: 0.0011 | F27: 0.66640396 | G27: =E27/F27 -> 0.0016506505
C28: 13 | D28: 0.1371 | E28: 0.0013 | F28: 0.79905917 | G28: =E28/F28 -> 0.0016269133
C29: 14 | D29: 0.1352 | E29: 0.0013 | F29: 0.92563352 | G29: =E29/F29 -> 0.0014044435
C30: 15 | D30: 0.1158 | E30: 0.0017 | F30: 0.518718 | G30: =E30/F30 -> 0.0032773106
C31: 16 | D31: 14.06 | E31: -0.0112 | F31: 0.90366386 | G31: =E31/F31 -> -0.012393989
C32: 17 | D32: 14.08 | E32: -1.58 | F32: 0.345013 | G32: =E32/F32 -> -4.5795376
C33: 18 | D33: 0.1324 | E33: -0.0296 | F33: 0.073877046 | G33: =E33/F33 -> -0.40066572
C34: 19 | D34: 0.1406 | E34: 0.0014 | F34: 0.86563775 | G34: =E34/F34 -> 0.0016173047

Sheet Comparaison PF-MASI 20
B4: Masi 20 | F4: Notre PTF | J4: Masi 20 | K4: Notre PTF
I5: Rendement | J5: 0.0013009196 | K5: 0.0012754044
B6: Rendement MASI 20 | C6: 0.0013009196 | F6: Rendement PF | G6: 0.0012754044 | I6: Risque | J6: 0.1421822 | K6: 0.13522142
B7: Variance MASI 20 | C7: 8.0863113e-05 | F7: Variance PF | G7: 7.3139335e-05
B8: Ecart Type MASI 20 | C8: 0.008992392 | F8: Ecart Type PF | G8: 0.0085521538
B9: Ecart Type MASI 20 Annualisé | C9: 0.1421822 | F9: Ecart Type PF Annualisé | G9: 0.13522142
B22: Rendement | F22: Le rendement du portefeuille est légèrement inférieur à celui du MASI 20 (écart de 0,01%). Cela signifie que notre portefeuille a eu une performance légèrement en dessous du marché de référence(MASI 20)
B26: Risque | F26: L'écart-type de notre portefeuille est inférieur à celui du MASI 20 (écart de 0,70%). Cela indique que notre portefeuille est moins volatil et donc moins risqué donnant une bonne stabilité que l’indice de référence(MASI 20)

Sheet Argumentaire Ciments du Maroc
A1: TITRE | B1: Ciments Du Maroc
A2: SECTEUR | B2: CIMENTRETIES
A3: OVERVIEW SUR LE SECTEUR | B3: Le secteur du ciment et des matériaux de construction au Maroc est en pleine expansion en 2025, soutenu par une croissance de la demande de +9,4 % au premier trimestre et de +17 % au semestre (selon le rapport semestriel 2025) ,le secteur bénéficie d'une demande structurelle forte, estimée à +8-10 % annuels jusqu'en 2030, selon les prévisions du HCP et de l'AMC.
B6: **Sur le plan macroéconomique, la baisse des taux d'intérêt et la maîtrise de l'inflation des matériaux (~3-4 %) favorisent les investissements publics et privés, avec un Plan Maroc 2030 qui prévoit 200 Md DH pour les infrastructures (stades, routes, aéroports). Microéconomiquement, le secteur est cyclique, dépendant des projets nationaux comme la CAN 2025 et la Coupe du Monde 2030, qui boostent les livraisons de ciment (1,22 Mt en septembre 2025, +12,5 %)
A11: OVERVIEW SUR LA CONCCURENCE | B11: Ciments du Maroc, filiale de HeidelbergCement, détient ~40 % de parts de marché, en concurrence directe avec LafargeHolcim Maroc (~35 % parts, CA ~4,3 Md DH en 2024) et Asment Temara (~10 %). LafargeHolcim mène en innovation et export, avec une croissance CA de +4-5 % annuelle, tandis que Ciments du Maroc se distingue par son efficacité opérationnelle et son acquisition récente d'Asment Temara (99,96 % du capital, intégrée au périmètre de consolidation depuis juillet 2025, page 22). Cette acquisition renforce sa position dans le Nord du Maroc et diversifie ses produits (ciment blanc, chaux). La concurrence est oligopolistique, avec des barrières hautes (coûts fixes, normes environnementales). Ciments du Maroc bénéficie d'une stratégie de décarbonation, mais doit accélérer sur l'ESG pour contrer LafargeHolcim.
A20: Synthèse de l'analyse des ratios boursiers | B20: Les ratios boursiers de Ciments du Maroc (PER 29,65, PBR 8,32, DY 0,03, EV/EBITDA 14,05) renforcent l’attractivité de cette action dans un contexte économique favorable au Maroc en octobre 2025. Le PER élevé reflète une confiance marquée des investisseurs dans les perspectives de croissance à long terme, portées par les grands projets nationaux. Le PBR met en valeur la solidité des actifs et la stratégie d’expansion, soulignant une valorisation justifiée par le leadership de l’entreprise. Le DY modeste soutient une approche de reinvestissement stratégique, idéale pour capitaliser sur les opportunités futures, tandis que l’EV/EBITDA confirme une valorisation équilibrée, renforcée par une conjoncture positive. En somme, ces ratios défendent un investissement prometteur, avec une position à maintenir ou renforcer pour profiter des perspectives à venir, notamment avec les résultats attendus prochainement
A29: Synthèse de l'analyse des ratios comptables et financiers | B29: Les ratios offrent une vision rassurante de sa solidité financière dans le contexte économique marocain de octobre 2025. Le ratio d’autonomie financière élevé garantit une structure capitalistique stable, réduisant la dépendance aux dettes et renforçant la résilience. Le ratio de liquidité générale, supérieur à 1, assure une couverture solide des engagements à court terme, tandis que le ratio de rentabilité financière met en évidence une utilisation efficace des capitaux propres, générant une valeur notable pour les actionnaires. Face aux ratios boursiers (PER 29,65, PBR 8,32, DY 0,03, EV/EBITDA 14,05), qui suggèrent une valorisation élevée avec un potentiel de croissance mais aussi un risque de surévaluation, ces ratios financiers apportent un confort supplémentaire. Ils confirment une base solide pour absorber les volatilités boursières, rendant l’investissement dans Ciments du Maroc attractif et équilibré, surtout avec les perspectives liées aux projets futurs.
A39: Décision motivée | B39: L’action bénéficie d’une position de leader renforcée par des initiatives stratégiques et des efforts vers la durabilité, assurant une compétitivité accrue. Ses indicateurs boursiers reflètent un optimisme lié aux perspectives de croissance, tandis que ses ratios financiers soulignent une stabilité et une efficacité opérationnelle remarquables. Cette combinaison en fait un choix attractif pour un investissement à moyen terme, avec un potentiel de valorisation soutenu par les tendances actuelles du marché.
A48: CALCUL ET ANALYSE DES RATIOS BOURSIERS
A50: LE CALCUL | B50: PER: Price Earning Ratio=Cours de Bousre / BPA | G50: =L53/L56 -> 29.645445
B51: PBR: Price to Book Ratio= Capitalisation Boursière / Fonds Propres | G51: =(L53*L54)/L57 -> 8.3247817
B52: DY: Dividend Yield= Dividende / Cours de Bourse | G52: =L58/L53 -> 0.03125
B53: L'EV/EBITDA | G53: =L59/L60 -> 14.053103 | J53: Cours de l'action | L53: 1920
B54: Rendement Moyen | G54: 0.00083528596 | J54: Nombre d'actions | L54: 14436004
B55: Risque | G55: 0.018920341 | J55: Résultat Net | L55: 934954000
J56: BPA | L56: =+L55/L54 -> 64.76543
A57: Commentaire: | B57: 29.645445 | C57: Supérieur à la moyenne du marché, indique que les investisseurs anticipent une forte croissance future, typique pour une entreprise dans un secteur lié à de grands projets d'infrastructure. Cependant, cette valorisation élevée pourrait signaler une surévaluation si les résultats ne suivent pas les attentes. | J57: Fonds Propres | L57: 3329472000
J58: Dividende par action | L58: =866160240/L54 -> 60
J59: EV | L59: 26036254243
J60: EBITDA | L60: 1852705000
B61: 8.3247817 | C61: reflète une valorisation élevée par rapport aux fonds propres, suggérant une confiance dans les actifs intangibles ou les perspectives à long terme. Cela expose toutefois à un risque de correction si la rentabilité ou la stabilité financière faiblit.
B65: 0.03125 | C65: Modeste, indiquant une politique de rétention des bénéfices pour reinvestir dans l'entreprise, une pratique courante dans un secteur en expansion. Cela le rend moins attractif pour les investisseurs cherchant un revenu régulier.
B68: 14.053103 | C68: Dand la fourchette haute du secteur, valorise l'entreprise à un multiple raisonnable de son flux opérationnel, suggérant une efficacité opérationnelle solide. Ce ratio inclut toutefois un possible premium lié à sa position de leader, avec un risque de baisse si les performances opérationnelles stagnent.
B72: 0,084% / 1,892% | C72: Le rendement moyen de 0,084 % indique une performance relativement faible mais stable, ce qui est typique du secteur cimentier, souvent considéré comme défensif et peu spéculatif, l’écart-type de 1,892 % montre une volatilité modérée, donc un niveau de risque faible à moyen. C'est un placement prudent offrant une stabilité et la résistance aux fluctuations du marché, plutôt qu’une rentabilité élevée.
A81: ANALYSE ET DIAGNOSTIC FINANCIER
A83: LE CALCUL | B83: Ratio d autonomie financière = capitaux propres /dettes | G83: =L88/L87 -> 17.847325
B84: Ratio de liquidité générale = actif circulant / passif circulant | G84: =L89/L90 -> 1.9197527 | J84: Cours de l'action | L84: 1920
B85: Ratio de rentabilité financière = resultat net / capitaux propres | G85: =L86/L88 -> 0.28081149 | J85: Nombre d'actions | L85: 14436004
J86: Résultat Net | L86: 934954000
J87: Dettes | L87: 186553000
A88: Commentaire: | B88: 17.85 | C88: Une structure capitalistique solide pour Ciments du Maroc, reflétant une forte indépendance vis-à-vis des dettes. Cela assure une résilience face aux fluctuations économiques, renforçant sa stabilité dans un contexte de croissance au Maroc en 2025. | J88: Fonds Propres | L88: 3329472000
J89: Actif Circulant | L89: 2446289000
J90: Passif Circulant | L90: 1274273000
B92: 1.92 | C92: Une capacité confortable à couvrir les engagements à court terme, démontrant une gestion prudente des flux financiers. Cela soutient une flexibilité opérationnelle dans un marché dynamiqu
B96: 0.28 | C96: Une utilisation efficace des capitaux propres, générant une valeur significative pour les actionnaires. Cette performance souligne la capacité de l’entreprise à maximiser ses retours, renforçant son attrait dans un contexte de projets à venir.

Sheet Argumentaire HPS
A1: TITRE | B1: HPS (Hightech Payment Systems)
A2: SECTEUR | B2: TECHNOLOGIE
A3: OVERVIEW SUR LE SECTEUR | B3: Le secteur des technologies financières et de paiement électronique connaît une croissance soutenue à l’échelle mondiale. Porté par la digitalisation accélérée des services bancaires, le développement du e-commerce, et la généralisation des paiements dématérialisés, il constitue aujourd’hui un axe stratégique majeur pour les économies émergentes. Au Maroc, la croissance du PIB non agricole de +4,5 % en 2024, soutenue par les secteurs des services, de l’industrie et du commerce, crée un environnement favorable à l’expansion du digital et des solutions de paiement. Cette dynamique s’inscrit dans la stratégie nationale de transformation numérique et de modernisation du système financier, encouragée par la Banque Centrale et les opérateurs bancaires. Dans ce contexte, le segment des paiements électroniques et du digital banking se distingue par une forte demande structurelle, stimulée par : la généralisation des paiements sans contact et mobiles, la montée des services en ligne et du e-commerce, et la transformation des institutions financières vers des modèles SaaS (Software as a Service) et full-service. Cependant, ce secteur reste hautement concurrentiel et exigeant. Les acteurs doivent continuellement investir dans l’innovation, la cybersécurité et l’internationalisation pour conserver leur avantage. La rapidité des évolutions technologiques (cloud, API, open banking, monnaies numériques) impose une agilité stratégique permanente. HPS s’inscrit pleinement dans cette dynamique mondiale : elle vise à devenir un acteur intégré de la fintech, capable de couvrir toute la chaîne de valeur des paiements — du traitement back-end à l’expérience client digitale.
A23: OVERVIEW SUR LA CONCCURENCE | B23: Au Maroc, HPS fait face à une concurrence locale principalement composée d’acteurs spécialisés dans des segments particuliers du paiement et de la banque digitale. S2M est l’un des leaders sur le marché des terminaux de paiement et des solutions de paiement électroniques, offrant aux banques et commerçants des services fiables mais centrés sur le traitement des transactions, sans couvrir l’ensemble du back-end bancaire ni les solutions SaaS intégrées. De son côté, M2T (ou M2M) se concentre sur les solutions de transfert d’argent et le paiement mobile, avec une forte présence sur le e-commerce et le mobile banking, mais elle ne fournit pas de plateforme bancaire complète pour les institutions financières. Face à ces acteurs, HPS se distingue par sa capacité à proposer une solution globale et modulable, combinant le processing, le digital banking et les services SaaS, ce qui lui permet de répondre aux besoins d’intégration complète des banques et fintech marocaines tout en offrant des perspectives d’expansion internationale.
A34: Synthèse de l'analyse des ratios boursiers | B34: Les ratios boursiers montrent qu’HPS est une entreprise à forte croissance et innovante, avec un fort potentiel de création de valeur à long terme. Même si les rendements immédiats (dividendes, bénéfices actuels) sont modestes, l’investissement est justifié par la stratégie d’expansion, l’intégration complète de ses acquisitions et le positionnement international. En tant qu’investisseur, ces ratios confirment que HPS est une valeur de portefeuille solide orientée vers la croissance future.
A39: Synthèse de l'analyse des ratios comptables et financiers | B39: L’analyse des principaux ratios financiers de HPS montre une situation solide malgré les investissements importants réalisés en 2024. Le ratio d’autonomie financière de 0,59 indique que l’entreprise finance ses actifs en grande partie par ses capitaux propres, tout en ayant recours à l’endettement, notamment pour l’acquisition de CR2, ce qui reste maîtrisé. Le ratio de liquidité générale de 1,81 reflète une capacité satisfaisante à couvrir ses obligations à court terme, même si la pression sur la trésorerie s’est accrue avec les acquisitions et la croissance. Enfin, le ratio de rentabilité financière de 10 % traduit une rentabilité actuelle modeste des capitaux propres, conséquence du choix stratégique de réinvestir une partie significative des bénéfices dans la croissance et l’expansion internationale. Dans l’ensemble, ces ratios confirment que HPS maintient une structure financière saine, tout en poursuivant une stratégie d’investissement orientée vers le long terme.
A49: Décision motivée | B49: Après analyse des ratios financiers et boursiers de HPS, notre décision d’inclure cette entreprise dans notre portefeuille est motivée par plusieurs éléments stratégiques. Les ratios montrent que HPS possède une structure financière saine (autonomie financière de 0,59 et liquidité générale de 1,81) et reste rentable malgré une rentabilité financière actuelle modeste (10 %), conséquence des investissements dans les acquisitions et le développement international. Sur le plan boursier, le PER élevé et le PBR important reflètent la confiance du marché dans sa croissance future et la valorisation de ses actifs immatériels, tandis que le DY modeste confirme la réorientation des profits vers la croissance et l’innovation. Ces éléments démontrent qu’HPS est une entreprise stratégiquement ambitieuse, innovante et en phase de transformation, offrant un fort potentiel de création de valeur à long terme. Ainsi, l’investissement dans HPS correspond à notre objectif de privilégier des entreprises à croissance soutenue et positionnement international, avec un horizon d’investissement orienté vers le futur.
A64: CALCUL ET ANALYSE DES RATIOS BOURSIERS
A66: LE CALCUL | B66: PER: Price Earning Ratio=Cours de Bousre / BPA | G66: 50.181545
B67: PBR: Price to Book Ratio= Capitalisation Boursière / Fonds Propres | G67: 4.8774249
B68: DY: Dividend Yield= Dividende / Cours de Bourse | G68: 0.01372011
B69: L'EV/EBITDA | G69: 21.655368 | J69: Cours de l'action | L69: 510.2
B70: Rendement Moyen | G70: -0.0014468375 | J70: Nombre d'actions | L70: 7406190
B71: Risque | G71: 0.0377099 | J71: Résultat Net | L71: 75299358
J72: BPA | L72: 10.167084 | M72: 73 395 600
A73: Commentaire: | B73: 50.181545 | C73: Ce ratio indique que le marché paie 50 fois les bénéfices actuels, ce qui est très élevé. Cela reflète de fortes anticipations de croissance, en particulier avec les acquisitions (CR2, ICPS, IPRC) et l’expansion internationale, mais cela induit aussi une responsabilité : HPS doit générer une croissance tangible et une amélioration de la rentabilité pour justifier cette valorisation. | J73: Fonds Propres | L73: 774719895
J74: Dividende par action | L74: 7
J75: EV | L75: 4759849778
J76: EBITDA | L76: 219800000
B77: 4.8774249 | C77: Avec un PBR autour de 4,6‑4,7, le marché valorise largement les actifs immatériels de HPS (logiciels, plateformes, savoir‑faire, potentiel de croissance), et moins les actifs physiques. Cela correspond à une entreprise tech innovante. Mais cela signifie aussi que les attentes sont élevées quant à l’innovation, à la protection des actifs (brevets, sécurité), et à la capacité à créer de la valeur immatérielle.
B83: 0.01372011 | C83: Le rendement offert par le dividende reste modeste. HPS préfère réinvestir une grande partie de ses profits dans sa croissance (acquisitions, R&D, expansion géographique), ce qui est cohérent avec une stratégie de long terme. Pour les investisseurs, cela signifie accepter un retour immédiat plus faible mais un potentiel de gain futur si la stratégie réussit.
B88: 21.655368 | C88: Ce ratio confirme la valorisation élevée de l’entreprise, en prenant en compte sa dette. Ce multiple exigeant implique, comme le PER, que le marché attend Une forte croissance de la rentabilité opérationnelle dans les prochaines années, non seulement via la croissance des revenus, mais aussi via l’optimisation opérationnelle, la réduction des coûts unitaires, et l’amélioration des marges brutes et nettes.
B94: "-0,145% / 3,771%" | C94: Le rendement moyen négatif (-0,145 %) indique une contre-performance, c’est-à-dire que l’action a légèrement perdu de la valeur sur les 3ans, avec un risque de 3,771 %, HPS présente une volatilité assez élevée, ce qui signifie que son cours varie fortement un comportement courant dans le secteur technologique, souvent sensible aux innovations, à la concurrence et aux conditions du marché mondial
A101: ANALYSE ET DIAGNOSTIC FINANCIER
A103: LE CALCUL | B103: Ratio d autonomie financière = capitaux propres /dettes | G103: 0.5871448
B104: Ratio de liquidité générale = actif circulant / passif circulant | G104: 1.8128549 | J104: Cours de l'action | L104: 510.2
B105: Ratio de rentabilité financière = resultat net / capitaux propres | G105: 0.097195591 | J105: Nombre d'actions | L105: 7406190
J106: Résultat Net | L106: 75299358
J107: Dettes | L107: 1319469911
A108: Commentaire: | B108: 0.5871448 | C108: Moyenne autonomie, les capitaux propres représentent presque 60% du financement permanent. | J108: Fonds Propres | L108: 774719895
J109: Actif Circulant | L109: 1582915000
B110: 1.8128549 | C110: HPS présentait une bonne liquidité avec un niveau satisfaisant, la situation de liquidité générale reste stable et solide. | J110: Passif Circulant | L110: 873161459
B113: 0.097195591 | C113: Forte baisse à 9,72 % par rapport aux dernières années, signalant un affaiblissement de la rentabilité financière et donc une moindre rémunération des actionnaires.

Sheet Argumentaire Marsa Maroc
A1: TITRE | B1: SODEP- Marsa Maroc
A2: SECTEUR | B2: TRANSPORT
A3: OVERVIEW SUR LE SECTEUR | B3: Le secteur portuaire marocain est un pilier stratégique de l’économie nationale, assurant plus de 95 % des échanges extérieurs du pays. Le Maroc ambitionne de devenir un hub logistique régional reliant l’Europe, l’Afrique et l’Amérique. Les plans portuaires nationaux à l’horizon 2030 visent à renforcer la connectivité maritime, moderniser les installations et digitaliser les services logistiques. Après une légère baisse liée aux perturbations mondiales du commerce maritime (hausse des coûts, ralentissement du trafic international), le secteur connaît une reprise progressive depuis 2024 passant à 33.626.000 en S1 2025 (+8%) selon le rapport semestriel financier, grâce à : la hausse du trafic conteneurisé à Tanger Med et Casablanca, le développement du commerce africain intra-continental, et les investissements dans les ports secondaires (Agadir, Safi, Nador West Med). C’est un secteur stratégique et en croissance, porté par la diversification du commerce extérieur et la montée en puissance du Maroc comme plateforme logistique continentale.
A16: OVERVIEW SUR LA CONCCURENCE | B16: Le secteur portuaire marocain présente une structure quasi monopolistique, dominée par Marsa Maroc (SODEP), filiale du groupe Tanger Med depuis 2022. Marsa Maroc est le principal opérateur national de services portuaires, assurant plus de 95 % de la manutention des marchandises dans les ports gérés par l’Agence Nationale des Ports (ANP). Contrairement à d’autres secteurs économiques, Marsa Maroc ne fait face à aucune concurrence directe au niveau national, car ses activités s’inscrivent dans le cadre de concessions publiques exclusives sur la majorité des ports marocains (Casablanca, Safi, Agadir, Jorf Lasfar, Nador, etc.)
A23: Synthèse de l'analyse des ratios boursiers | B23: Ces ratios boursiers confirment la position dominante et la forte valorisation de Marsa Maroc sur le marché. L’action bénéficie d’une image de stabilité et de croissance soutenue par des perspectives nationales et régionales positives. Toutefois on va garder un niveau de vigilance quant à la capacité du groupe à maintenir ses performances et à concrétiser ses projets d’expansion.
A28: Synthèse de l'analyse des ratios comptables et financiers | B28: Les ratios financiers de Marsa Maroc confirment une situation financière exemplaire : une autonomie élevée, une liquidité très confortable, et une rentabilité remarquable. Ces indicateurs traduisent la stabilité, la solidité et la performance durable du modèle économique de Marsa Maroc, en cohérence avec son statut de leader du secteur portuaire marocain.
A34: Décision motivée | B34: L’analyse de Marsa Maroc met en évidence une entreprise stratégiquement positionnée dans un contexte macroéconomique favorable :une dynamique d’investissement public soutenue, portée par le Plan Maroc 2030, les projets d’infrastructures liés à la CAN 2025 et à la Coupe du Monde 2030, ainsi que par la modernisation du système logistique et portuaire national. Marsa Maroc consolide son leadership national grâce à son intégration au groupe Tanger Med, optimisant ses flux et son ouverture internationale. Ses ratios boursiers élevés traduisent la confiance du marché, tandis que ses indicateurs financiers solides (autonomie 2,29 ; liquidité 2,82 ; rentabilité 35 %) confirment sa stabilité et sa performance. Nous choisissons Marsa Maroc afin de diversifier notre portefeuille et de bénéficier de la solidité d’une entreprise leader dans son secteur, tout en restant vigilants quant à l’évolution de sa valorisation et de ses performances futures.
A49: CALCUL ET ANALYSE DES RATIOS BOURSIERS
A51: LE CALCUL | B51: PER: Price Earning Ratio=Cours de Bousre / BPA | G51: 53.295284
B52: PBR: Price to Book Ratio= Capitalisation Boursière / Fonds Propres | G52: 18.41952
B53: DY: Dividend Yield= Dividende / Cours de Bourse | G53: 0.010326087
B54: L'EV/EBITDA | G54: 16.466896 | J54: Cours de l'action | L54: 920
B55: Rendement Moyen | G55: 0.0023136226 | J55: Nombre d'actions | L55: 73395600
B56: Risque | G56: 0.015652924 | J56: Résultat Net | L56: 1266978000
J57: BPA | L57: 17.262315
J58: Fonds Propres | L58: 3665891000
J59: Dividende par action | L59: 9.5 | M59: 73 395 600
A60: Commentaire: | B60: 53.295574 | C60: Très supérieur à la moyenne du marché, ce qui indique que les investisseurs anticipent une forte croissance future des bénéfices de Marsa Maroc. Cette valorisation élevée reflète la confiance dans son statut quasi monopolistique, ses résultats solides et les perspectives liées à l’expansion portuaire nationale et africaine. | J60: EV | L60: 4.2467943e+10
J61: EBITDA | L61: 2578989000
B64: 18.41962 | C64: l montre que le marché valorise près de 18 fois les fonds propres de Marsa Maroc, ce qui traduit une forte confiance des investisseurs dans la solidité de ses actifs, sa position de leader national et ses perspectives de croissance.
B68: 0.010326087 | C68: Un rendement en dividendes faible, qui indique que l’entreprise privilégie le réinvestissement des bénéfices pour soutenir sa croissance et moderniser ses infrastructures plutôt que la distribution immédiate de revenus
B71: 16.466896 | C71: dans la fourchette haute du secteur logistique et portuaire. Il traduit une valorisation importante du potentiel opérationnel de l’entreprise. Le marché considère donc que Marsa Maroc dégage une efficacité opérationnelle durable et une rentabilité stable.
B75: 0,231% / 1,565% | C75: Avec un rendement moyen positif de 0,231 %, SODEP affiche une performance correcte et régulière donc c'est une action attractive. Son risque modéré (1,565 %) montre une bonne stabilité du titre, ce qui est cohérent avec le secteur du transport portuaire un domaine relativement prévisible et peu volatil, soutenu par la demande constante en échanges commerciaux.
A82: ANALYSE ET DIAGNOSTIC FINANCIER
A84: LE CALCUL | B84: Ratio d autonomie financière = capitaux propres /dettes | G84: 2.2940006
B85: Ratio de liquidité générale = actif circulant / passif circulant | G85: 2.8214933
B86: Ratio de rentabilité financière = resultat net / capitaux propres | G86: 0.34561257
A89: Commentaire: | B89: 2.2940006 | C89: Les capitaux propres dépassent largement les dettes, traduisant une structure financière extrêmement solide. Une autonomie supérieure à 1 signifie que l’entreprise finance la majorité de ses activités avec ses propres ressources, ce qui réduit sa dépendance vis-à-vis des emprunts. Pour Marsa Maroc, ce niveau reflète une gestion prudente et une grande capacité de résilience face aux chocs économiques ou aux fluctuations du trafic portuaire. | J89: Cours de l'action | L89: 920
J90: Nombre d'actions | L90: 73396000
J91: Résultat Net | L91: 1266978000
J92: Dettes | L92: 1598034000
J93: Fonds Propres | L93: 3665891000
J94: Actif Circulant | L94: 3266392000
B95: 2.8214933 | C95: Chaque dirham de dette à court terme, Marsa Maroc dispose de 2,82 dirhams d’actifs circulants, ce qui est nettement supérieur au seuil de sécurité (1,5). Cela traduit une souplesse financière, une excellente capacité à honorer ses engagements à court terme, une gestion saine du besoin en fonds de roulement et la capacité à saisir des opportunités d’investissement sans compromettre son équilibre financier. | J95: Passif Circulant | L95: 1157682000
B101: 0.34561257 | C101: 35 % : excellent rendement, très élevé par rapport à la moyenne de nombreuses entreprises.Cela signifie que l’entreprise est très performante pour ses actionnaires, générant beaucoup de profit pour chaque dirham investi en fonds propres.

Sheet Argumentaire Labelvie
A1: Titres | B1: label' vie
A2: Secteur d'activité | B2: Distribution
A3: OVERVIEW SUR LE SECTEUR | B3: Le secteur de la grande distribution au Maroc est en pleine expansion depuis plusieurs années. Il se caractérise par : Une transition progressive du commerce traditionnel vers le commerce moderne (supermarchés, hypermarchés, hard discount). Une hausse de la consommation des ménages soutenue par l’urbanisation et l’évolution des modes de vie. Une concurrence accrue entre enseignes locales et internationales (Marjane, Carrefour, BIM, Aswak Assalam…). Une professionnalisation croissante des circuits d’approvisionnement et de logistique. Tendances récentes : Développement du e-commerce alimentaire. Expansion du format de proximité (Carrefour Market, Carrefour Express). Focus sur la digitalisation et la fidélisation client. Label’Vie, grâce à son partenariat avec Carrefour, est un acteur clé du secteur, alliant expérience locale et standards internationaux.
A4: OVERVIEW SUR LA CONCCURENCE | B4: Marjane Holding : leader historique du marché marocain, filiale du groupe SNI (Al Mada). Présente dans l’alimentaire et le non-alimentaire. BIM : enseigne turque à bas prix, très présente dans les grandes villes avec un modèle de discount. Aswak Assalam : positionnement intermédiaire, avec une offre large mais croissance plus lente. Label’Vie : deuxième acteur du marché moderne, se distingue par : Une diversification des formats (Carrefour Market, Carrefour Express, Atacadao). Une forte politique d’expansion. Une bonne image de marque et une gestion efficace. Label’Vie combine ainsi croissance, rentabilité et innovation, ce qui la place parmi les valeurs les plus dynamiques du secteur.
A5: Synthèse de l'analyse des ratios boursiers | B5: Le titre Label’Vie présente une valorisation raisonnable (PER 24,27) et crée de la valeur au-delà de ses actifs comptables (PBR 3,86). Son rendement du dividende (2,35 %) est stable et supérieur à celui de Maroc Telecom. Globalement, l’action offre un bon équilibre entre croissance, solidité financière et rentabilité modérée, représentant un compromis attractif entre performance et sécurité.
A6: Synthèse de l'analyse des ratios comptables et financiers | B6: Label’Vie présente une structure financière saine (autonomie financière 61 %), une rentabilité élevée (ROE 15,91 %) et une liquidité correcte (0,62), reflétant une gestion performante. L’entreprise doit toutefois veiller à sa trésorerie pour accompagner sa croissance rapide.
A7: Décision motivée | B7: Label’Vie est une entreprise dynamique et rentable, bien positionnée sur un marché en croissance. Ses ratios financiers démontrent une bonne santé économique, une rentabilité élevée et une structure équilibrée. Son PER raisonnable et son rendement de dividende attractif en font une valeur intéressante pour un investisseur à moyen ou long terme. Décision finale : Acheter, car Label’Vie offre un potentiel de croissance solide et un bon rapport rendement/risque.
A10: CALCUL ET ANALYSE DES RATIOS BOURSIERS
A11: Ratio | B11: Formule | C11: Valeur | D11: Analyse | F11: Indicateur | G11: Valeur | H11: Interprétation et analyse
A12: PER (Price Earnings Ratio) | B12: PER = Capitalisation boursière ÷ Résultat net | C12: 24.27 | D12: Modéré. Les investisseurs paient environ 24 fois les bénéfices, ce qui traduit une valorisation raisonnable et une confiance équilibrée dans la croissance du groupe. | F12: Rendement moyen | G12: 0.0002 | H12: Cela indique que l’action Label Vie offre un gain très faible sur la période étudiée. Ce résultat traduit une performance modérée mais régulière. Le titre ne génère pas de forte rentabilité, mais il montre une certaine constance dans ses rendements, ce qui le rend intéressant pour les investisseurs recherchant la sécurité et la stabilité à long terme.
A13: PBR (Price to Book Ratio) | B13: PBR = Capitalisation boursière ÷ Fonds propres | C13: 3.86 | D13: Supérieur à 1, indiquant que Label’Vie crée de la valeur au-delà de ses actifs comptables. L’entreprise est valorisée plus que ses actifs comptables, signe de confiance du marché. | F13: Risque (écart-type) | G13: 0.0193 | H13: Cela montre une volatilité modérée. Cela signifie que le prix de l’action reste relativement stable, peu affecté par les fluctuations du marché. Ce niveau de risque indique que Label Vie est une valeur défensive, adaptée aux investisseurs prudents cherchant à minimiser les pertes potentielles.
A14: DY (Dividend Yield) | B14: DY = Dividende ÷ Cours de bourse | C14: 0.0235 | D14: Rendement du dividende correct, supérieur à celui de Maroc Telecom. Cela traduit une politique de distribution stable et attractive pour les investisseurs à la recherche de revenus. | F14: Variance | G14: 0.00037 | H14: C'est un niveau de risque modéré. Elle mesure la dispersion des rendements et montre que les écarts autour de la moyenne sont faibles. Ce résultat traduit une bonne stabilité financière et une gestion équilibrée de l’entreprise, renforçant l’image de Label Vie comme une action à faible volatilité et rendement stable.
A19: ANALYSE ET DIAGNOSTIC FINANCIER
A20: Ratio | B20: Formule | C20: Valeur | D20: Analyse
A21: Autonomie financière | B21: Capitaux propres ÷ Dettes | C21: 0.6138 | D21: Bonne structure financière. Plus de 61 % des ressources proviennent des capitaux propres, ce qui assure une solidité face aux dettes.
A22: Liquidité générale | B22: Actif circulant ÷ Passif circulant | C22: 0.6214 | D22: Correcte mais légèrement inférieure à 1. Cela indique une dépendance partielle au financement à court terme, ce qui est typique dans le commerce de détail.
A23: Rentabilité financière (ROE) | B23: Résultat net ÷ Capitaux propres | C23: 0,1591 (15,91 %) | D23: Très satisfaisante. Label’Vie génère une rentabilité supérieure à 15 % sur ses capitaux propres, signe d’une gestion performante et d’une forte productivité du capital.
A26: Données
A27: Cours | B27: 4690
A28: Nbre de titres | B28: 2893957
A29: Capitalisation | B29: 13572658330
A30: Res Net | B30: 5.5911365e+08
A31: Capitaux Propres | B31: 3513657000
A32: Dividende | B32: 280000000
A33: Fonds propres | B33: 3513657000
A34: Dettes | B34: 5.7236116e+09
A35: Actif circulant | B35: 3.5555691e+09
A36: Passif circulant | B36: 5721243000

Sheet Argumentaire IAM
A1: Titres | B1: IAM
A2: Secteur d'activité | B2: TELECOM
A3: OVERVIEW SUR LE SECTEUR | B3: Le secteur des télécommunications au Maroc est un pilier stratégique de l’économie nationale. Il est caractérisé par : • Une forte maturité du marché mobile (taux de pénétration supérieur à 130 %) et une croissance ralentie, mais soutenue par l’expansion de la data mobile et du haut débit. • Trois grands opérateurs : Maroc Telecom (IAM), Orange Maroc et Inwi (Wana Corporate). • Une réglementation stricte sous la supervision de l’ANRT (Agence Nationale de Réglementation des Télécommunications). • Tendances actuelles : digitalisation, migration vers la fibre optique, déploiement de la 5G, et diversification vers les services financiers mobiles. Position de Maroc Telecom : • Leader incontesté du marché marocain. • Présence dans 11 pays africains (filiales en Afrique de l’Ouest et Centrale). •Stratégie axée sur l’innovation, la qualité de service et la croissance à l’international.
A4: OVERVIEW SUR LA CONCCURENCE | B4: • Orange Maroc : deuxième opérateur du marché, fort dans le segment mobile et la data. Investit massivement dans la 4G et la fibre. • Inwi (Wana Corporate) : troisième opérateur, plus agressif sur les prix et le digital. Cible les jeunes et les entreprises par des offres innovantes. • Maroc Telecom conserve cependant : • La plus grande part de marché (mobile, fixe et Internet). • Une rentabilité plus élevée que ses concurrents. • Une solidité financière et une base clientèle stable.
A5: Synthèse de l'analyse des ratios boursiers | B5: Maroc Telecom est une entreprise solide et mature, fortement valorisée par le marché : Son PER élevé (38,20) montre que les investisseurs ont confiance en sa rentabilité future, mais indique aussi que l’action est relativement chère. Un PBR supérieur à 1 (6,08) reflète que le marché reconnaît que l’entreprise crée de la valeur au-delà de ses actifs comptables. Le rendement du dividende faible (1,23%) suggère que l’entreprise privilégie le réinvestissement de ses bénéfices plutôt que la distribution aux actionnaires. Conclusion : Maroc Telecom offre un profil défensif et stable, intéressant pour la sécurité, mais moins attractif pour les investisseurs recherchant un rendement élevé.
A6: Synthèse de l'analyse des ratios comptables et financiers | B6: Maroc Telecom présente une structure financière solide et rentable : Autonomie financière élevée (76,5%) : l’entreprise repose principalement sur ses capitaux propres, avec peu de dépendance à l’endettement. Rentabilité financière satisfaisante (14,22%) : les capitaux propres sont bien valorisés, reflétant une gestion efficace. Liquidité faible (0,33) : les dettes à court terme ne sont pas entièrement couvertes par l’actif circulant, nécessitant une vigilance sur le fonds de roulement. Conclusion : Maroc Telecom est financièrement saine et rentable, avec une structure robuste, mais doit surveiller sa liquidité à court terme.
A7: Décision motivée | B7: Maroc Telecom présente un profil de long terme stable et sécurisé._x000B_Sa forte rentabilité, sa solidité financière et son positionnement de leader justifient une confiance dans la valeur du titre._x000B_Toutefois, le PER élevé et le faible rendement du dividende incitent à la prudence pour un investisseur cherchant du rendement à court terme.
A10: CALCUL ET ANALYSE DES RATIOS BOURSIERS
A11: Ratio | B11: Formule | C11: Valeur | D11: Analyse | F11: Indicateur | G11: Valeur | H11: Interprétation et analyse
A12: PER (Price Earnings Ratio) | B12: PER = Capitalisation boursière ÷ Résultat net | C12: 38.2 | D12: Assez élevé. Le marché valorise fortement l’entreprise, signe de confiance dans sa rentabilité future, mais aussi d’un titre relativement cher. | F12: Rendement moyen | G12: 0.00042 | H12: Le rendement moyen de 0,042 % indique que l’action IAM a généré un léger gain moyen sur la période étudiée. Ce rendement, bien que faible, montre une tendance positive et régulière. Cela traduit une entreprise stable, offrant une rentabilité modérée mais constante. Pour un investisseur, IAM représente une valeur sûre privilégiant la stabilité des revenus à long terme plutôt qu’une forte croissance à court terme.
A13: PBR (Price to Book Ratio) | B13: PBR = Capitalisation boursière ÷ Fonds propres | C13: 6.08 | D13: Supérieur à 1. Le marché estime que Maroc Telecom crée de la valeur au-delà de ses actifs comptables, signe de confiance dans la solidité de l’entreprise. | F13: Risque (écart-type) | G13: 0.0161 | H13: Un risque de 1,61 % traduit une volatilité relativement faible du titre IAM. Les variations du rendement autour de la moyenne sont limitées, ce qui reflète une bonne stabilité du cours. Ce faible niveau de risque montre qu’IAM est moins exposée aux fluctuations du marché, ce qui en fait une action attractive pour les investisseurs prudents à la recherche de sécurité et de prévisibilité.
A14: DY (Dividend Yield) | B14: DY = Dividende ÷ Cours de bourse | C14: 0.0123 | D14: Rendement du dividende faible. L’entreprise réinvestit une partie de ses bénéfices plutôt que de distribuer largement, ce qui peut soutenir sa croissance future. | F14: Variance | G14: 0.00026 | H14: La variance de 0,026 % confirme ce faible niveau de risque. Elle mesure la dispersion des rendements autour de leur moyenne et indique que les performances d’IAM restent proches de la moyenne observée. Cela renforce l’image d’un titre peu volatil et stable, soutenu par une activité solide et une position dominante sur son marché.
A22: ANALYSE ET DIAGNOSTIC FINANCIER
A23: Ratio | B23: Formule | C23: Valeur | D23: Analyse
A24: Autonomie financière | B24: Capitaux propres ÷ Dettes | C24: 0.7651 | D24: Excellente solidité. Plus de 76 % des ressources proviennent des capitaux propres, ce qui traduit une faible dépendance à l’endettement.
A25: Liquidité générale | B25: Actif circulant ÷ Passif circulant | C25: 0.3333 | D25: Faible. Les dettes à court terme ne sont pas entièrement couvertes par l’actif circulant, ce qui oblige Maroc Telecom à gérer attentivement son fonds de roulement.
A26: Rentabilité financière (ROE) | B26: Résultat net ÷ Capitaux propres | C26: 0,1422 (14,22 %) | D26: Niveau satisfaisant. La société affiche une bonne rentabilité des capitaux propres et une gestion efficace du capital.
A29: Données
A30: Cours | B30: 115.6
A31: Nbre de titres | B31: 879095340
A32: Capitalisation | B32: 101623421304
A33: Res Net | B33: 2660000000
A34: Capitaux Propres | B34: 18702000000
A35: Dividende | B35: 1260000000
A36: Fonds propres | B36: 16699288000
A37: Dettes | B37: 24442000000
A38: Actif circulant | B38: 15089000000
A39: Passif circulant | B39: 45266000000

Sheet Argumentaire SANLAM
A1: Titres | B1: SANLAM
A2: Secteur d'activité | B2: Assurance
A3: OVERVIEW SUR LE SECTEUR | B3: Le secteur de l’assurance au Maroc présente de solides perspectives de croissance, portées par l’augmentation de la demande en produits d’assurance et par un cadre réglementaire favorable soutenu par l’Autorité de Contrôle des Assurances et de la Prévoyance Sociale (ACAPS). Sanlam Maroc illustre cette dynamique par la diversification de son offre, incluant l’assurance Vie, Santé, Automobile et Gestion de Patrimoine, ainsi que par le lancement de solutions innovantes telles que Sanlam Private Investment. L’entreprise se distingue également par des initiatives sur le marché marocain, étant la première à proposer une assurance dédiée aux chats et aux chiens. Ces éléments font de Sanlam Maroc un acteur attractif dans un secteur en pleine expansion et en mutation vers des services personnalisés et digitaux
A4: OVERVIEW SUR LA CONCCURENCE | B4: Sanlam Maroc évolue dans un environnement concurrentiel marqué par la présence de grands acteurs internationaux et d’assureurs locaux bien implantés. Parmi les principaux concurrents : Wafa Assurance le leader du marché avec une large part de marché et un réseau de distribution étendu, AXA Assurance Maroc un acteur international proposant des solutions diversifiées et innovantes, notamment sur le plan digital, RMA Watanya avec forte implantation locale et produits adaptés aux besoins des assurés marocains, et Allianz Maroc le concurrent direct sur plusieurs segments, malgré son lien avec Sanlam Allianz Africa, et soumis à un contrôle réglementaire strict. Cette diversité et la solidité des acteurs concurrents obligent Sanlam Maroc à se différencier par l’innovation, la qualité de ses produits, l’expertise en gestion de patrimoine, la capacité à lancer des offres inédites (comme l’assurance pour animaux de compagnie) et l’optimisation de ses canaux de distribution, afin de consolider sa position et de capter de nouvelles parts de marché
A5: Synthèse de l'analyse des ratios boursiers | B5: Les ratios boursiers montrent que Sanlam est raisonnablement valorisée (PER modéré et PBR proche de 1,57) et offre un rendement de dividende attractif (3,80 %). Cela indique que les investisseurs peuvent s’attendre à une croissance stable avec un revenu régulier, rendant le choix d’investissement motivé et équilibré
A6: Synthèse de l'analyse des ratios comptables et financiers | B6: L'analyse financier met en avant une performance opérationnelle solide : un ratio combiné inférieur à 100 %, une marge nette de réassurance élevée et un faible ratio de sinistralité. Cela traduit une gestion efficace des risques et une rentabilité durable, renforçant la sécurité et l’attrait de l’investissement dans Sanlam
A7: Décision motivée | B7: La solidité opérationnelle, la rentabilité maîtrisée et le rendement attractif du dividende font de Sanlam un choix d’investissement sûr et rationnel. Cet instrument combine stabilité financière et performance dans l’assurance, justifiant pleinement la décision d’investir
A9: CALCUL ET ANALYSE DES RATIOS BOURSIERS
A10: Indicateurs | B10: Valeur obtenue | C10: Interprétation
A11: Capitalisation boursière | B11: 8349020472
A12: PER | B12: =8349020472/412703180.13 -> 20.230085 | C12: Les investisseurs paient 20,23 dirhams pour 1 dirham de bénéfice. Un PER modéré indique une valorisation raisonnable et un équilibre entre risque et rentabilité
A13: PBR | B13: =8349020472/5331318403.28 -> 1.566033 | C13: L’action est légèrement au-dessus de sa valeur comptable. Cela traduit une valorisation réaliste des actifs, reflétant une gestion prudente et fiable
A14: DY | B14: =77/2028 -> 0.037968442 | C14: Le rendement du dividende est attractif. Les investisseurs bénéficient d’un revenu régulier, ce qui renforce l’attrait pour un investissement stable
A16: Variance = | B16: (Σ(x - μ)² / N-1) | D16: Moyenne des rendements = | E16: 0.0013
A17: = | B17: 0.063%
A19: Ecart-type = | B19: σ = √(Σ(x - μ)² / N-1)
A20: = | B20: 0.03
A22: Interprétation de la variance: | B22: Cette valeur faible indique que les rendements de l’action Sanlam Maroc sont peu dispersés de leur moyenne, donc relativement stables.
A26: Interprétation de l'écart type: | B26: Les rendements journaliers (ou hebdomadaires, selon ton calcul) de l’action Sanlam Maroc s’écartent en moyenne d’environ +3 % et -3% de leur rendement moyen
A33: ANALYSE ET DIAGNOSTIC FINANCIER
A35: Indicateurs | B35: Valeur obtenue | C35: Interprétation
A36: Ratio combiné | B36: 0.92 | C36: Ce ratio compare les dépenses d'une compagnie d'assurance en sinistres et en frais à ses primes acquises. Donc 92 % des primes sont consommées par les sinistres et les frais de gestion.
A37: La marge d’exploitation nette de réassurance | B37: 30442239 | C37: La marge d’exploitation nette de réassurance de 30 442 239,46 DH montre que la société dégage un bon profit sur son activité. Cela prouve une bonne gestion des dépenses et des risques.
A38: ratio de sinistralité S/p | B38: 0.69 | C38: Le ratio de sinistralité de 0,69 signifie que 69 % des primes encaissées servent à payer les sinistres. Ce niveau est bon, car il reste en dessous de 80 %, ce qui montre une activité bien contrôlée.
A40: Formules:
A41: Ratio combiné | B41: =sinistre+ch de fct/prime
A42: La marge d’exploitation nette de réassurance | B42: 30442239
A43: ratio de sinistralité S/p | B43: Sinistre/prime
A44: PER | B44: Cap bour/Rslt net=8349020472/412 703 180,13
A45: PBR | B45: cap bour/fonds propres=8349020472/5 331 318 403,28
A46: DY | B46: div/cours bours=77/2028

Sheet Argumentaire Sothema
A1: Titres | B1: SOTHEMA
A2: Secteur d'activité | B2: Pharmaceutiques
A3: OVERVIEW SUR LE SECTEUR | B3: Le secteur pharmaceutique marocain présente de solides perspectives de croissance, et un fort potentiel d’investissement, soutenues par une demande accrue liée à l’extension de la couverture médicale et par un cadre réglementaire favorable. Sothema illustre cette dynamique avec une hausse de 17 % de son chiffre d’affaires au premier semestre 2025 par rapport à la même période en 2024, le lancement prévus sur l’exercice de 15 nouveaux traitements en oncologie et cardiologie, et l’acquisition stratégique du laboratoire Soludia Maghreb, qui renforcera sa présence sur un segment clé de santé publique. Parallèlement, l’entreprise investit dans la montée en capacité industrielle et la transition énergétique, affirmant son positionnement d’acteur innovant et durable. Ces éléments font de Sothema une valeur attractive dans un secteur en pleine expansion.
A4: OVERVIEW SUR LA CONCCURENCE | B4: Sothema évolue dans un environnement concurrentiel marqué par la présence à la fois de grands groupes internationaux et de laboratoires locaux bien implantés. Parmi les principaux concurrents, Sanofi Maroc bénéficie de l’accès à des produits innovants et d’un réseau de distribution solide, tandis que Cooper Maroc tire parti de sa longue présence sur le marché et de la diversité de sa gamme. Maphar et Laprophan représentent des acteurs locaux majeurs, avec un ancrage territorial fort et une expertise dans les génériques. D’autres laboratoires nationaux ou filiales de multinationales se positionnent sur des niches spécifiques ou agissent en importation et distribution, augmentant la pression concurrentielle sur les segments stratégiques de Sothema. Cette diversité de concurrents oblige l’entreprise à se différencier par l’innovation, la qualité de ses produits et le développement de nouvelles capacités industrielles.
A5: Synthèse de l'analyse des ratios boursiers | B5: Les ratios boursiers de Sothema montrent une valorisation élevée et une forte confiance des investisseurs. Le PER et le PBR traduisent une croissance anticipée et une image solide, tandis que le DY, bien que faible, reflète une politique prudente et orientée vers le développement. Globalement, ces indicateurs confirment que l’investissement dans Sothema est rationnel et prometteur, particulièrement pour les investisseurs cherchant stabilité et potentiel de plus-value
A6: Synthèse de l'analyse des ratios comptables et financiers | B6: L'analyse financier de Sothema confirme une structure financière solide, une excellente liquidité et une rentabilité attrayante. Les indicateurs démontrent que la société est financièrement stable, performante et capable de générer de la valeur tout en maîtrisant ses risques
A7: Décision motivée | B7: La solidité financière, la rentabilité élevée et la confiance du marché envers Sothema justifient pleinement le choix d’investissement. Cet instrument offre à la fois stabilité, performance et potentiel de croissance durable, rendant la décision stratégiquement motivée et rationnelle
A9: CALCUL ET ANALYSE DES RATIOS BOURSIERS
A10: Indicateurs | B10: Valeur obtenue | C10: Interprétation
A11: Capitalisation boursière | B11: ='Argumentaire Sothema'!A13 -> PBR
A12: PER | B12: =12319200000/317224000 -> 38.834388 | C12: Cela signifie que les investisseurs paient environ 38,83 dirhams pour 1 dirham de bénéfice. Un PER élevé traduit une forte confiance du marché dans la rentabilité et la croissance future de l’entreprise.Cela suggère que Sothema est perçue comme une société solide et prometteuse, ce qui rend le choix d’investissement pertinent à long terme
A13: PBR | B13: =12319200000/1707312000 -> 7.2155529 | C13: L’action est valorisée plus de 7 fois sa valeur comptable. Ce niveau élevé indique que le marché valorise fortement les actifs de Sothema, en raison de sa rentabilité, de sa notoriété et de ses perspectives stables dans le secteur pharmaceutique. Cela traduit une bonne image de marque et un potentiel de création de valeur, renforçant le caractère attractif de l’investissement.
A14: DY | B14: =28/1711 -> 0.016364699 | C14: Le rendement du dividende reste modeste mais stable. Même si le rendement est faible, cela peut s’expliquer par une politique de réinvestissement des bénéfices pour soutenir la croissance.
B16: 12319200000
A18: Variance = | B18: (Σ(x - μ)² / N-1) | D18: Moyenne des rendements = | E18: 0.00068974569
A19: = | B19: 0.0005069447
A21: Ecart-type = | B21: σ = √(Σ(x - μ)² / N-1)
A22: = | B22: 0.022515433
A24: Interprétation de la variance: | B24: Une variance faible indiquant que les rendements de l’action Sothema sont peu dispersés autour de leur moyenne, donc relativement stables
A28: Interprétation de l'écart type: | B28: L’écart-type montre que les rendements de l’action Sothema s’écartent en moyenne de -2,3 % et +2,3% autour de leur moyenne. Cela montre une volatilité faible, donc un risque limité pour l’investisseur
A33: ANALYSE ET DIAGNOSTIC FINANCIER
A35: Indicateurs | B35: Valeur obtenue | C35: Interprétation
A36: Ratio d'autonomie financière | B36: =1707312000/(292022142.9+633601805.26) -> 1.8444985 | C36: Les capitaux propres sont supérieurs à l’endettement. Cela montre une grande indépendance financière et une capacité à financer ses activités sans dépendre excessivement des dettes. C’est un signal positif pour les investisseurs, car cela réduit le risque financier
